Workbook

Sheet Overview
C2: Manchester United | Corporate finance & valuation
C3: FY2024–26 reported • FY2027–31 scenarios • valuation at 30 September 2026
C4: Case selected | E4: =CHOOSE(Assumptions!$E$5,"Base","Downside","Upside") -> Base
C7: Financial result | E7: 2027 | F7: 2028 | G7: 2029 | H7: 2030 | I7: 2031
C8: Revenue | E8: =Statements!E8 -> 750 | F8: =Statements!F8 -> 714.7 | G8: =Statements!G8 -> 728.715 | H8: =Statements!H8 -> 743.11845 | I8: =Statements!I8 -> 757.92136
C9: EBITDA before disposal gains | E9: =Statements!E11 -> 215 | F9: =Statements!F11 -> 177 | G9: =Statements!G11 -> 183.501 | H9: =Statements!H11 -> 185.48017 | I9: =Statements!I11 -> 182.85032
C10: Net income | E10: =Statements!E23 -> -20.075187 | F10: =Statements!F23 -> -38.065207 | G10: =Statements!G23 -> -0.83279506 | H10: =Statements!H23 -> 32.614492 | I10: =Statements!I23 -> 53.310518
C11: Cash after operations / investment | E11: =Statements!E31 -> -119.89098 | F11: =Statements!F31 -> -30.391152 | G11: =Statements!G31 -> 85.591264 | H11: =Statements!H31 -> 58.778507 | I11: =Statements!I31 -> 60.709948
C12: Peak revolver usage | E12: =Statements!E52 -> 245.50323 | F12: =Statements!F52 -> 265.22178 | G12: =Statements!G52 -> 256.63236 | H12: =Statements!H52 -> 183.18726 | I12: =Statements!I52 -> 130.30953
C13: Maximum cash reserve shortfall | E13: =Statements!E53 -> 0 | F13: =Statements!F53 -> 0 | G13: =Statements!G53 -> 0 | H13: =Statements!H53 -> 3.5527137e-15 | I13: =Statements!I53 -> 0
C14: PL actual green headroom | E14: ='PL bridge'!E18 -> 205.40098 | F14: ='PL bridge'!F18 -> 185.3073 | G14: ='PL bridge'!G18 -> 214.21561 | H14: ='PL bridge'!H18 -> 240.84173 | I14: ='PL bridge'!I18 -> 259.64989
C15: PL in-season green headroom | E15: ='PL bridge'!E26 -> 187.65098 | F15: ='PL bridge'!F26 -> 167.5573 | G15: ='PL bridge'!G26 -> 196.46561 | H15: ='PL bridge'!H26 -> 223.09173 | I15: ='PL bridge'!I26 -> 241.89989
C16: PL adjusted-equity headroom | E16: ='PL bridge'!E49 -> 218.4101 | F16: ='PL bridge'!F49 -> 122.90852 | G16: ='PL bridge'!G49 -> 115.96387 | H16: ='PL bridge'!H49 -> 212.00618 | I16: ='PL bridge'!I49 -> 311.82191
C17: UEFA SCR headroom (CY2026–30) | E17: ='UEFA bridge'!E18 -> 81.602629 | F17: ='UEFA bridge'!F18 -> 80.547075 | G17: ='UEFA bridge'!G18 -> 87.628468 | H17: ='UEFA bridge'!H18 -> 114.80613 | I17: ='UEFA bridge'!I18 -> 136.28487
C18: UEFA earnings (licences 2026/27–30/31) | E18: ='UEFA bridge'!E27 -> -60.773 | F18: ='UEFA bridge'!F27 -> 58.83209 | G18: ='UEFA bridge'!G27 -> 14.130883 | H18: ='UEFA bridge'!H27 -> 61.283088 | I18: ='UEFA bridge'!I27 -> 106.01649
C21: Minimum modelled headroom across the horizon
C22: Cash reserve / funding | E22: =MIN('Debt cash'!E47:BL47) -> 134.77822
C23: EBITDA covenant | E23: =MIN('Debt cash'!E38:BL38) -> 52
C24: PL green cost limit | E24: =MIN('PL bridge'!E18:I18,'PL bridge'!E26:I26) -> 167.5573
C25: PL working capital | E25: =MIN('PL bridge'!E37:I37) -> 147.02822
C26: PL stressed liquidity | E26: =MIN('PL bridge'!E42:H42) -> 399.56387
C27: PL adjusted equity | E27: =MIN('PL bridge'!E49:I49) -> 115.96387
C28: UEFA squad-cost limit | E28: =MIN(IF('UEFA bridge'!E19=1,'UEFA bridge'!E18,1000000),IF('UEFA bridge'!F19=1,'UEFA bridge'!F18,1000000),IF('UEFA bridge'!G19=1,'UEFA bridge'!G18,1000000),IF('UEFA bridge'!H19=1,'UEFA bridge'!H18,1000000),IF('UEFA bridge'!I19=1,'UEFA bridge'!I18,1000000),IF(Assumptions!I303=1,'UEFA bridge'!E38,1000000)) -> 80.547075
C29: UEFA football earnings | E29: =MIN(IF('UEFA bridge'!E19=1,'UEFA bridge'!E27,1000000),IF('UEFA bridge'!F19=1,'UEFA bridge'!F27,1000000),IF('UEFA bridge'!G19=1,'UEFA bridge'!G27,1000000),IF('UEFA bridge'!H19=1,'UEFA bridge'!H27,1000000),IF('UEFA bridge'!I19=1,'UEFA bridge'!I27,1000000),IF(Assumptions!I303=1,'UEFA bridge'!E37,1000000)) -> -60.773
C30: UEFA December equity proxy | E30: =MIN(IF('UEFA bridge'!E19=1,'UEFA bridge'!E33,1000000),IF('UEFA bridge'!F19=1,'UEFA bridge'!F33,1000000),IF('UEFA bridge'!G19=1,'UEFA bridge'!G33,1000000),IF('UEFA bridge'!H19=1,'UEFA bridge'!H33,1000000),IF('UEFA bridge'!I19=1,'UEFA bridge'!I33,1000000)) -> 107.32723
C32: Tightest headroom screen | E32: =MIN(E22:E30) -> -60.773
C33: Most restrictive screen | E33: =INDEX(C22:C30,MATCH(E32,E22:E30,0)) -> UEFA football earnings
C34: Proxy feasibility | E34: =IF(E32>=0,"Within modelled screens","Outside modelled screens") -> Outside modelled screens
C36: Refinancing assumption | E36: =IF(Capacity!E8=1,"Uncommitted rollover assumed","Contractual repayment required") -> Uncommitted rollover assumed
C38: Results are public-data scenario proxies, not an internal budget or certified compliance.
C39: FY2032 SSR and full CY2031 UEFA require forecasts beyond this five-year model.
C40: Negative cash denotes unmet funding; the model does not assume payments can still settle.
C42: Prospective headroom excluding inherited FE | E42: =MIN(E22:E28,E30,IF('UEFA bridge'!F19=1,'UEFA bridge'!F27,1000000),IF('UEFA bridge'!G19=1,'UEFA bridge'!G27,1000000),IF('UEFA bridge'!H19=1,'UEFA bridge'!H27,1000000),IF('UEFA bridge'!I19=1,'UEFA bridge'!I27,1000000),IF(Assumptions!I303=1,'UEFA bridge'!E37,1000000)) -> 14.130883
C43: Historical FE extra eligible adjustments needed | E43: =MAX(0,-'UEFA bridge'!E27) -> 60.773
C44: Required historical average adjustment (£m/year) | E44: =MAX(0,-'UEFA bridge'!E22-'UEFA bridge'!E26)/3 -> 55.257667
C46: Prospective screen assumes the historical football-earnings return is reconciled separately.
C49: Valuation and cash generation • active operating case
C50: DCF enterprise value | E50: =Valuation!E63 -> 424.29787
C51: DCF equity value (limited liability) | E51: =Valuation!E71 -> 0
C52: Implied price / diluted economic share, USD | E52: =Valuation!E72 -> 0
C53: Observed Class A price, USD (30 Sep 2026) | E53: =Valuation!E10 -> 20.95
C54: Applied WACC | E54: =Valuation!E20 -> 0.1004724
C55: Terminal FCFF | E55: =Valuation!E57 -> 38.500937
C56: Valuation diagnostic | E56: =Valuation!E77 -> No positive DCF residual equity
C57: Funding condition | E57: =Valuation!E78 -> Conditional on uncommitted refinancing
C59: Start: Financial review → Assumptions → Statements → FCFF → Valuation → Comps. Monthly accounting and regulatory schedules remain supporting analysis.
C60: DCF values are scenario outputs, not a price target or proof of financeability. Reinvestment has no assumed automatic revenue benefit. See Case comparison for contractual repayment and rollover outcomes.
C61: Forensic review: source facts checked and selected formulas corrected. Terminal economics and private regulatory inputs remain material exceptions. Read the assurance report.

Sheet Capacity
C2: Capacity
C3: £m unless stated. Evidence cut-off: 8 October 2026.
C4: Case selected | E4: =CHOOSE(Assumptions!$E$5,"Base","Downside","Upside") -> Base
C6: FY2027 incremental transfer face cost | E6: 0
C7: FY2027 incremental annual all-in wages | E7: 0
C8: Refinance maturities: 0 no / 1 assumed rollover | E8: 1
C9: Squad payroll share override (−1 = scenario) | E9: -1
C10: Squad market value override (−1 = scenario) | E10: -1
C11: Sale proceeds multiplier | E11: 1
C12: Floating-rate shift | E12: 0
C14: Live matrix: minimum headroom (£m), all modelled screens
C15: Columns = incremental face fees; rows = annual employer cost. FY2027 January start.
E17: =Overview!E32 -> -60.773 | F17: 0 | G17: 25 | H17: 50 | I17: 100 | J17: 150
E18: 0 | F18: -60.773 | G18: -60.773 | H18: -60.773 | I18: -60.773 | J18: -60.773
E19: 5 | F19: -60.773 | G19: -60.773 | H19: -60.773 | I19: -60.773 | J19: -60.773
E20: 10 | F20: -60.773 | G20: -60.773 | H20: -60.773 | I20: -60.773 | J20: -60.773
E21: 20 | F21: -60.773 | G21: -60.773 | H21: -60.773 | I21: -60.773 | J21: -86.965282
E22: 30 | F22: -60.773 | G22: -60.773 | H22: -60.773 | I22: -82.705495 | J22: -113.93675
C24: A non-negative cell passes the modelled proxy screens only. It is not certification.
C25: If the zero/zero cell is negative, no incremental package is feasible under these inputs.
C28: Base conditional frontier - saved snapshot
C29: Conditional: assumed rollover; unresolved historical UEFA earnings screen excluded.
F30: 0 | G30: 25 | H30: 50 | I30: 100 | J30: 150
E31: 0 | F31: 14.130883 | G31: 4.9119191 | H31: -4.3019372 | I31: -22.716584 | J31: -41.116797
E32: 5 | F32: 6.2753888 | G32: -2.9435748 | H32: -12.157431 | I32: -30.572078 | J32: -48.972291
E33: 10 | F33: -1.5801052 | G33: -10.799069 | H33: -20.012925 | I33: -38.427572 | J33: -59.913037
E34: 20 | F34: -17.291093 | G34: -26.510057 | H34: -35.723913 | I34: -55.638952 | J34: -86.965282
E35: 30 | F35: -33.002081 | G35: -42.221045 | H35: -51.434901 | I35: -82.705495 | J35: -113.93675
C38: Downside conditional frontier - saved snapshot
C39: Conditional: assumed rollover; unresolved historical UEFA earnings screen excluded.
F40: 0 | G40: 25 | H40: 50 | I40: 100 | J40: 150
E41: 0 | F41: -758.65746 | G41: -784.14225 | H41: -809.35598 | I41: -859.41666 | J41: -909.41666
E42: 5 | F42: -778.71645 | G42: -804.18416 | H42: -829.37265 | I42: -879.41666 | J42: -929.41666
E43: 10 | F43: -798.77544 | G43: -824.22607 | H43: -849.38931 | I43: -899.41666 | J43: -949.41666
E44: 20 | F44: -838.89341 | G44: -864.30233 | H44: -889.41666 | I44: -939.41666 | J44: -989.41666
E45: 30 | F45: -879.01138 | G45: -904.35598 | H45: -929.41666 | I45: -979.41666 | J45: -1029.4167
C48: Upside conditional frontier - saved snapshot
C49: Conditional: assumed rollover; unresolved historical UEFA earnings screen excluded.
F50: 0 | G50: 25 | H50: 50 | I50: 100 | J50: 150
E51: 0 | F51: 92.123083 | G51: 92.123083 | H51: 92.123083 | I51: 92.123083 | J51: 92.123083
E52: 5 | F52: 92.123083 | G52: 92.123083 | H52: 92.123083 | I52: 92.123083 | J52: 92.123083
E53: 10 | F53: 92.123083 | G53: 92.123083 | H53: 92.123083 | I53: 92.123083 | J53: 92.123083
E54: 20 | F54: 90 | G54: 90 | H54: 90 | I54: 90 | J54: 90
E55: 30 | F55: 83.15 | G55: 83.15 | H55: 83.15 | I55: 83.15 | J55: 83.15

Sheet Assumptions
C2: Assumptions
C3: £m unless stated. Evidence cut-off: 8 October 2026.
C4: Case selected | E4: =CHOOSE(Assumptions!$E$5,"Base","Downside","Upside") -> Base
C5: Case number: 1 Base / 2 Downside / 3 Upside | E5: 1
C7: Driver / case | E7: 2027 | F7: 2028 | G7: 2029 | H7: 2030 | I7: 2031 | K7: F/E/A | L7: Basis and rationale
C8: Ordinary commercial revenue — active | E8: =CHOOSE($E$5,E9,E10,E11) -> 350 | F8: =CHOOSE($E$5,F9,F10,F11) -> 360.5 | G8: =CHOOSE($E$5,G9,G10,G11) -> 371.315 | H8: =CHOOSE($E$5,H9,H10,H11) -> 382.45445 | I8: =CHOOSE($E$5,I9,I10,I11) -> 393.92808 | K8: A | L8: A. Analyst scenario, 8 Oct 2026. Low confidence.
C9: Base | E9: 350 | F9: 360.5 | G9: 371.315 | H9: 382.45445 | I9: 393.92808
C10: Downside | E10: 335 | F10: 335 | G10: 335 | H10: 335 | I10: 335
C11: Upside | E11: 360 | F11: 378 | G11: 396.9 | H11: 416.745 | I11: 437.58225
C13: Domestic and other broadcast — active | E13: =CHOOSE($E$5,E14,E15,E16) -> 160 | F13: =CHOOSE($E$5,F14,F15,F16) -> 160 | G13: =CHOOSE($E$5,G14,G15,G16) -> 160 | H13: =CHOOSE($E$5,H14,H15,H16) -> 160 | I13: =CHOOSE($E$5,I14,I15,I16) -> 160 | K13: A | L13: A. Analyst scenario, 8 Oct 2026. Low confidence.
C14: Base | E14: 160 | F14: 160 | G14: 160 | H14: 160 | I14: 160
C15: Downside | E15: 155 | F15: 150.35 | G15: 145.8395 | H15: 141.46431 | I15: 137.22039
C16: Upside | E16: 165 | F16: 169.95 | G16: 175.0485 | H16: 180.30095 | I16: 185.70998
C18: European broadcast — active | E18: =CHOOSE($E$5,E19,E20,E21) -> 65 | F18: =CHOOSE($E$5,F19,F20,F21) -> 35 | G18: =CHOOSE($E$5,G19,G20,G21) -> 35 | H18: =CHOOSE($E$5,H19,H20,H21) -> 35 | I18: =CHOOSE($E$5,I19,I20,I21) -> 35 | K18: A | L18: A. Analyst scenario, 8 Oct 2026. Low confidence.
C19: Base | E19: 65 | F19: 35 | G19: 35 | H19: 35 | I19: 35
C20: Downside | E20: 60 | F20: 5 | G20: 5 | H20: 5 | I20: 5
C21: Upside | E21: 70 | F21: 80 | G21: 80 | H21: 80 | I21: 80
C23: Matchday — active | E23: =CHOOSE($E$5,E24,E25,E26) -> 175 | F23: =CHOOSE($E$5,F24,F25,F26) -> 160 | G23: =CHOOSE($E$5,G24,G25,G26) -> 163.2 | H23: =CHOOSE($E$5,H24,H25,H26) -> 166.464 | I23: =CHOOSE($E$5,I24,I25,I26) -> 169.79328 | K23: A | L23: A. Analyst scenario, 8 Oct 2026. Low confidence.
C24: Base | E24: 175 | F24: 160 | G24: 163.2 | H24: 166.464 | I24: 169.79328
C25: Downside | E25: 170 | F25: 145 | G25: 145 | H25: 145 | I25: 145
C26: Upside | E26: 185 | F26: 185 | G26: 190.55 | H26: 196.2665 | I26: 202.15449
C28: Additional CL misses versus opening contract estimate — active | E28: =CHOOSE($E$5,E29,E30,E31) -> 0 | F28: =CHOOSE($E$5,F29,F30,F31) -> 1 | G28: =CHOOSE($E$5,G29,G30,G31) -> 0 | H28: =CHOOSE($E$5,H29,H30,H31) -> 0 | I28: =CHOOSE($E$5,I29,I30,I31) -> 0 | K28: A | L28: A. Changes versus undisclosed opening adidas estimate. £0.8m annual recognition per additional miss. Not the full contractual £10m deduction.
C29: Base | E29: 0 | F29: 1 | G29: 0 | H29: 0 | I29: 0
C30: Downside | E30: 0 | F30: 1 | G30: 1 | H30: 1 | I30: 1
C31: Upside | E31: 0 | F31: 0 | G31: 0 | H31: 0 | I31: 0
C33: Adidas incremental cash deduction — active | E33: =CHOOSE($E$5,E34,E35,E36) -> 0 | F33: =CHOOSE($E$5,F34,F35,F36) -> 10 | G33: =CHOOSE($E$5,G34,G35,G36) -> 0 | H33: =CHOOSE($E$5,H34,H35,H36) -> 0 | I33: =CHOOSE($E$5,I34,I35,I36) -> 0 | K33: A | L33: A. Assumed same-year cash settlement of incremental missed seasons only. Difference from recognised revenue rolls through contract asset.
C34: Base | E34: 0 | F34: 10 | G34: 0 | H34: 0 | I34: 0
C35: Downside | E35: 0 | F35: 10 | G35: 10 | H35: 10 | I35: 10
C36: Upside | E36: 0 | F36: 0 | G36: 0 | H36: 0 | I36: 0
C38: Inherited group payroll before leavers — active | E38: =CHOOSE($E$5,E39,E40,E41) -> 350 | F38: =CHOOSE($E$5,F39,F40,F41) -> 350 | G38: =CHOOSE($E$5,G39,G40,G41) -> 350 | H38: =CHOOSE($E$5,H39,H40,H41) -> 350 | I38: =CHOOSE($E$5,I39,I40,I41) -> 350 | K38: A | L38: A. FY2027 envelope includes known summer transactions. Future retained payroll separately inflates and removes leavers.
C39: Base | E39: 350 | F39: 350 | G39: 350 | H39: 350 | I39: 350
C40: Downside | E40: 365 | F40: 365 | G40: 365 | H40: 365 | I40: 365
C41: Upside | E41: 365 | F41: 365 | G41: 365 | H41: 365 | I41: 365
C43: Retained payroll inflation — active | E43: =CHOOSE($E$5,E44,E45,E46) -> 0 | F43: =CHOOSE($E$5,F44,F45,F46) -> 0.02 | G43: =CHOOSE($E$5,G44,G45,G46) -> 0.02 | H43: =CHOOSE($E$5,H44,H45,H46) -> 0.02 | I43: =CHOOSE($E$5,I44,I45,I46) -> 0.02 | K43: A | L43: A. Analyst scenario, 8 Oct 2026. Low confidence.
C44: Base | E44: 0 | F44: 0.02 | G44: 0.02 | H44: 0.02 | I44: 0.02
C45: Downside | E45: 0 | F45: 0.03 | G45: 0.03 | H45: 0.03 | I45: 0.03
C46: Upside | E46: 0 | F46: 0.03 | G46: 0.03 | H46: 0.03 | I46: 0.03
C48: Relevant squad share — active | E48: =CHOOSE($E$5,E49,E50,E51) -> 0.75 | F48: =CHOOSE($E$5,F49,F50,F51) -> 0.75 | G48: =CHOOSE($E$5,G49,G50,G51) -> 0.75 | H48: =CHOOSE($E$5,H49,H50,H51) -> 0.75 | I48: =CHOOSE($E$5,I49,I50,I51) -> 0.75 | K48: A | L48: A. Identification range 70–85%; broader sensitivity 65–90%. Includes relevant professionals and coach.
C49: Base | E49: 0.75 | F49: 0.75 | G49: 0.75 | H49: 0.75 | I49: 0.75
C50: Downside | E50: 0.85 | F50: 0.85 | G50: 0.85 | H50: 0.85 | I50: 0.85
C51: Upside | E51: 0.7 | F51: 0.7 | G51: 0.7 | H51: 0.7 | I51: 0.7
C53: Annual inherited payroll savings — active | E53: =CHOOSE($E$5,E54,E55,E56) -> 0 | F53: =CHOOSE($E$5,F54,F55,F56) -> 20 | G53: =CHOOSE($E$5,G54,G55,G56) -> 15 | H53: =CHOOSE($E$5,H54,H55,H56) -> 10 | I53: =CHOOSE($E$5,I54,I55,I56) -> 5 | K53: A | L53: A. Contract exits/replacements independent of new fees. Savings already include sale-related wage exits; never deducted again.
C54: Base | E54: 0 | F54: 20 | G54: 15 | H54: 10 | I54: 5
C55: Downside | E55: 0 | F55: 10 | G55: 10 | H55: 5 | I55: 5
C56: Upside | E56: 0 | F56: 25 | G56: 20 | H56: 15 | I56: 10
C58: Other operating costs — active | E58: =CHOOSE($E$5,E59,E60,E61) -> 185 | F58: =CHOOSE($E$5,F59,F60,F61) -> 188.7 | G58: =CHOOSE($E$5,G59,G60,G61) -> 192.474 | H58: =CHOOSE($E$5,H59,H60,H61) -> 196.32348 | I58: =CHOOSE($E$5,I59,I60,I61) -> 200.24995 | K58: A | L58: A. Analyst scenario, 8 Oct 2026. Low confidence.
C59: Base | E59: 185 | F59: 188.7 | G59: 192.474 | H59: 196.32348 | I59: 200.24995
C60: Downside | E60: 190 | F60: 197.6 | G60: 205.504 | H60: 213.72416 | I60: 222.27313
C61: Upside | E61: 190 | F61: 195.7 | G61: 201.571 | H61: 207.61813 | I61: 213.84667
C63: Annual discretionary transfer face cost — active | E63: =CHOOSE($E$5,E64,E65,E66) -> 0 | F63: =CHOOSE($E$5,F64,F65,F66) -> 60 | G63: =CHOOSE($E$5,G64,G65,G66) -> 60 | H63: =CHOOSE($E$5,H64,H65,H66) -> 60 | I63: =CHOOSE($E$5,I64,I65,I66) -> 60 | K63: A | L63: A decision. FY2027 incremental package controlled on Capacity. No implied actual budget.
C64: Base | E64: 0 | F64: 60 | G64: 60 | H64: 60 | I64: 60
C65: Downside | E65: 0 | F65: 40 | G65: 40 | H65: 40 | I65: 40
C66: Upside | E66: 0 | F66: 80 | G66: 80 | H66: 80 | I66: 80
C68: Recurring wages for each new annual cohort — active | E68: =CHOOSE($E$5,E69,E70,E71) -> 0 | F68: =CHOOSE($E$5,F69,F70,F71) -> 12 | G68: =CHOOSE($E$5,G69,G70,G71) -> 12 | H68: =CHOOSE($E$5,H69,H70,H71) -> 12 | I68: =CHOOSE($E$5,I69,I70,I71) -> 12 | K68: A | L68: A decision. All-in employer cost, incremental to retained payroll. FY2027 package controlled on Capacity.
C69: Base | E69: 0 | F69: 12 | G69: 12 | H69: 12 | I69: 12
C70: Downside | E70: 0 | F70: 10 | G70: 10 | H70: 10 | I70: 10
C71: Upside | E71: 0 | F71: 15 | G71: 15 | H71: 15 | I71: 15
C73: Future net sale face consideration — active | E73: =CHOOSE($E$5,E74,E75,E76) -> 30 | F73: =CHOOSE($E$5,F74,F75,F76) -> 50 | G73: =CHOOSE($E$5,G74,G75,G76) -> 50 | H73: =CHOOSE($E$5,H74,H75,H76) -> 50 | I73: =CHOOSE($E$5,I74,I75,I76) -> 50 | K73: A | L73: A. Analyst scenario, 8 Oct 2026. Low confidence.
C74: Base | E74: 30 | F74: 50 | G74: 50 | H74: 50 | I74: 50
C75: Downside | E75: 10 | F75: 20 | G75: 20 | H75: 20 | I75: 20
C76: Upside | E76: 50 | F76: 80 | G76: 80 | H76: 80 | I76: 80
C78: Disposed NBV / sale present value — active | E78: =CHOOSE($E$5,E79,E80,E81) -> 0.3 | F78: =CHOOSE($E$5,F79,F80,F81) -> 0.3 | G78: =CHOOSE($E$5,G79,G80,G81) -> 0.3 | H78: =CHOOSE($E$5,H79,H80,H81) -> 0.3 | I78: =CHOOSE($E$5,I79,I80,I81) -> 0.3 | K78: A | L78: A. Zero-NBV academy case and loss-on-sale cases supported. NBV capped at available pre-sale assets; cap reported as audit exception.
C79: Base | E79: 0.3 | F79: 0.3 | G79: 0.3 | H79: 0.3 | I79: 0.3
C80: Downside | E80: 0.5 | F80: 0.5 | G80: 0.5 | H80: 0.5 | I80: 0.5
C81: Upside | E81: 0.2 | F81: 0.2 | G81: 0.2 | H81: 0.2 | I81: 0.2
C83: New cohort contract life — active | E83: =CHOOSE($E$5,E84,E85,E86) -> 5 | F83: =CHOOSE($E$5,F84,F85,F86) -> 5 | G83: =CHOOSE($E$5,G84,G85,G86) -> 5 | H83: =CHOOSE($E$5,H84,H85,H86) -> 5 | I83: =CHOOSE($E$5,I84,I85,I86) -> 5 | K83: A | L83: A. Analyst scenario, 8 Oct 2026. Low confidence.
C84: Base | E84: 5 | F84: 5 | G84: 5 | H84: 5 | I84: 5
C85: Downside | E85: 4 | F85: 4 | G85: 4 | H85: 4 | I85: 4
C86: Upside | E86: 5 | F86: 5 | G86: 5 | H86: 5 | I86: 5
C88: Known mixed acquisition/extension life — active | E88: =CHOOSE($E$5,E89,E90,E91) -> 5 | F88: =CHOOSE($E$5,F89,F90,F91) -> 5 | G88: =CHOOSE($E$5,G89,G90,G91) -> 5 | H88: =CHOOSE($E$5,H89,H90,H91) -> 5 | I88: =CHOOSE($E$5,I89,I90,I91) -> 5 | K88: A | L88: A. £191.731m face consideration discounted using the separate known-event payment vector with 4–5 year life; no unverified rescheduling of opening contracts. Extension-reset sensitivity remains separate.
C89: Base | E89: 5 | F89: 5 | G89: 5 | H89: 5 | I89: 5
C90: Downside | E90: 4 | F90: 4 | G90: 4 | H90: 4 | I90: 4
C91: Upside | E91: 5 | F91: 5 | G91: 5 | H91: 5 | I91: 5
C93: Transfer discount rate — active | E93: =CHOOSE($E$5,E94,E95,E96) -> 0.05 | F93: =CHOOSE($E$5,F94,F95,F96) -> 0.05 | G93: =CHOOSE($E$5,G94,G95,G96) -> 0.05 | H93: =CHOOSE($E$5,H94,H95,H96) -> 0.05 | I93: =CHOOSE($E$5,I94,I95,I96) -> 0.05 | K93: A | L93: A. Analyst scenario, 8 Oct 2026. Low confidence.
C94: Base | E94: 0.05 | F94: 0.05 | G94: 0.05 | H94: 0.05 | I94: 0.05
C95: Downside | E95: 0.07 | F95: 0.07 | G95: 0.07 | H95: 0.07 | I95: 0.07
C96: Upside | E96: 0.03 | F96: 0.03 | G96: 0.03 | H96: 0.03 | I96: 0.03
C98: Acquisition cash at recognition — active | E98: =CHOOSE($E$5,E99,E100,E101) -> 0.4 | F98: =CHOOSE($E$5,F99,F100,F101) -> 0.4 | G98: =CHOOSE($E$5,G99,G100,G101) -> 0.4 | H98: =CHOOSE($E$5,H99,H100,H101) -> 0.4 | I98: =CHOOSE($E$5,I99,I100,I101) -> 0.4 | K98: A | L98: A. Analyst scenario, 8 Oct 2026. Low confidence.
C99: Base | E99: 0.4 | F99: 0.4 | G99: 0.4 | H99: 0.4 | I99: 0.4
C100: Downside | E100: 0.6 | F100: 0.6 | G100: 0.6 | H100: 0.6 | I100: 0.6
C101: Upside | E101: 0.25 | F101: 0.25 | G101: 0.25 | H101: 0.25 | I101: 0.25
C103: Acquisition cash +12 months — active | E103: =CHOOSE($E$5,E104,E105,E106) -> 0.3 | F103: =CHOOSE($E$5,F104,F105,F106) -> 0.3 | G103: =CHOOSE($E$5,G104,G105,G106) -> 0.3 | H103: =CHOOSE($E$5,H104,H105,H106) -> 0.3 | I103: =CHOOSE($E$5,I104,I105,I106) -> 0.3 | K103: A | L103: A. Analyst scenario, 8 Oct 2026. Low confidence.
C104: Base | E104: 0.3 | F104: 0.3 | G104: 0.3 | H104: 0.3 | I104: 0.3
C105: Downside | E105: 0.25 | F105: 0.25 | G105: 0.25 | H105: 0.25 | I105: 0.25
C106: Upside | E106: 0.25 | F106: 0.25 | G106: 0.25 | H106: 0.25 | I106: 0.25
C108: Acquisition cash +24 months — active | E108: =CHOOSE($E$5,E109,E110,E111) -> 0.2 | F108: =CHOOSE($E$5,F109,F110,F111) -> 0.2 | G108: =CHOOSE($E$5,G109,G110,G111) -> 0.2 | H108: =CHOOSE($E$5,H109,H110,H111) -> 0.2 | I108: =CHOOSE($E$5,I109,I110,I111) -> 0.2 | K108: A | L108: A. Analyst scenario, 8 Oct 2026. Low confidence.
C109: Base | E109: 0.2 | F109: 0.2 | G109: 0.2 | H109: 0.2 | I109: 0.2
C110: Downside | E110: 0.15 | F110: 0.15 | G110: 0.15 | H110: 0.15 | I110: 0.15
C111: Upside | E111: 0.25 | F111: 0.25 | G111: 0.25 | H111: 0.25 | I111: 0.25
C113: Acquisition cash +36 months — active | E113: =CHOOSE($E$5,E114,E115,E116) -> 0.1 | F113: =CHOOSE($E$5,F114,F115,F116) -> 0.1 | G113: =CHOOSE($E$5,G114,G115,G116) -> 0.1 | H113: =CHOOSE($E$5,H114,H115,H116) -> 0.1 | I113: =CHOOSE($E$5,I114,I115,I116) -> 0.1 | K113: A | L113: A. Analyst scenario, 8 Oct 2026. Low confidence.
C114: Base | E114: 0.1 | F114: 0.1 | G114: 0.1 | H114: 0.1 | I114: 0.1
C115: Downside | E115: 0 | F115: 0 | G115: 0 | H115: 0 | I115: 0
C116: Upside | E116: 0.25 | F116: 0.25 | G116: 0.25 | H116: 0.25 | I116: 0.25
C118: Known summer cash at recognition — active | E118: =CHOOSE($E$5,E119,E120,E121) -> 0.4 | F118: =CHOOSE($E$5,F119,F120,F121) -> 0.4 | G118: =CHOOSE($E$5,G119,G120,G121) -> 0.4 | H118: =CHOOSE($E$5,H119,H120,H121) -> 0.4 | I118: =CHOOSE($E$5,I119,I120,I121) -> 0.4 | K118: A | L118: A. Analyst scenario, 8 Oct 2026. Low confidence.
C119: Base | E119: 0.4 | F119: 0.4 | G119: 0.4 | H119: 0.4 | I119: 0.4
C120: Downside | E120: 0.6 | F120: 0.6 | G120: 0.6 | H120: 0.6 | I120: 0.6
C121: Upside | E121: 0.2 | F121: 0.2 | G121: 0.2 | H121: 0.2 | I121: 0.2
C123: Known summer cash +12 months — active | E123: =CHOOSE($E$5,E124,E125,E126) -> 0.2 | F123: =CHOOSE($E$5,F124,F125,F126) -> 0.2 | G123: =CHOOSE($E$5,G124,G125,G126) -> 0.2 | H123: =CHOOSE($E$5,H124,H125,H126) -> 0.2 | I123: =CHOOSE($E$5,I124,I125,I126) -> 0.2 | K123: A | L123: A. Analyst scenario, 8 Oct 2026. Low confidence.
C124: Base | E124: 0.2 | F124: 0.2 | G124: 0.2 | H124: 0.2 | I124: 0.2
C125: Downside | E125: 0.2 | F125: 0.2 | G125: 0.2 | H125: 0.2 | I125: 0.2
...

Sheet Statements
C2: Statements
C3: £m unless stated. Evidence cut-off: 8 October 2026.
C4: Case selected | E4: =CHOOSE(Assumptions!$E$5,"Base","Downside","Upside") -> Base
C7: Fiscal year | E7: 2027 | F7: 2028 | G7: 2029 | H7: 2030 | I7: 2031
C8: Revenue | E8: =SUM('Revenue costs'!E14:P14) -> 750 | F8: =SUM('Revenue costs'!Q14:AB14) -> 714.7 | G8: =SUM('Revenue costs'!AC14:AN14) -> 728.715 | H8: =SUM('Revenue costs'!AO14:AZ14) -> 743.11845 | I8: =SUM('Revenue costs'!BA14:BL14) -> 757.92136
C9: Employee costs | E9: =SUM('Revenue costs'!E19:P19) -> 350 | F9: =SUM('Revenue costs'!Q19:AB19) -> 349 | G9: =SUM('Revenue costs'!AC19:AN19) -> 352.74 | H9: =SUM('Revenue costs'!AO19:AZ19) -> 361.3148 | I9: =SUM('Revenue costs'!BA19:BL19) -> 374.8211
C10: Other operating costs | E10: =SUM('Revenue costs'!E21:P21) -> 185 | F10: =SUM('Revenue costs'!Q21:AB21) -> 188.7 | G10: =SUM('Revenue costs'!AC21:AN21) -> 192.474 | H10: =SUM('Revenue costs'!AO21:AZ21) -> 196.32348 | I10: =SUM('Revenue costs'!BA21:BL21) -> 200.24995
C11: EBITDA before disposal gains | E11: =SUM('Revenue costs'!E22:P22) -> 215 | F11: =SUM('Revenue costs'!Q22:AB22) -> 177 | G11: =SUM('Revenue costs'!AC22:AN22) -> 183.501 | H11: =SUM('Revenue costs'!AO22:AZ22) -> 185.48017 | I11: =SUM('Revenue costs'!BA22:BL22) -> 182.85032
C12: Registration amortisation | E12: =SUM(Registrations!E89:P89) -> 183.95475 | F12: =SUM(Registrations!Q89:AB89) -> 167.57381 | G12: =SUM(Registrations!AC89:AN89) -> 141.0809 | H12: =SUM(Registrations!AO89:AZ89) -> 115.34468 | I12: =SUM(Registrations!BA89:BL89) -> 95.989274
C13: Tangible depreciation | E13: =SUM('Revenue costs'!E24:P24) -> 22 | F13: =SUM('Revenue costs'!Q24:AB24) -> 22 | G13: =SUM('Revenue costs'!AC24:AN24) -> 22 | H13: =SUM('Revenue costs'!AO24:AZ24) -> 22 | I13: =SUM('Revenue costs'!BA24:BL24) -> 22
C14: Other intangible amortisation | E14: =SUM('Revenue costs'!E25:P25) -> 3.4 | F14: =SUM('Revenue costs'!Q25:AB25) -> 3.4 | G14: =SUM('Revenue costs'!AC25:AN25) -> 3.4 | H14: =SUM('Revenue costs'!AO25:AZ25) -> 3.4 | I14: =SUM('Revenue costs'!BA25:BL25) -> 3.4
C15: Disposal gain / loss | E15: =SUM(Transfers!E25:P25) -> 40.632524 | F15: =SUM(Transfers!Q25:AB25) -> 33.849206 | G15: =SUM(Transfers!AC25:AN25) -> 33.849206 | H15: =SUM(Transfers!AO25:AZ25) -> 33.849206 | I15: =SUM(Transfers!BA25:BL25) -> 33.849206
C16: Operating profit | E16: =E11-E12-E13-E14+E15 -> 46.277773 | F16: =F11-F12-F13-F14+F15 -> 17.875401 | G16: =G11-G12-G13-G14+G15 -> 50.869305 | H16: =H11-H12-H13-H14+H15 -> 78.584699 | I16: =I11-I12-I13-I14+I15 -> 95.31025
C17: Accrued financial interest expense | E17: =SUM('Debt cash'!E22:P22)-SUM('Debt cash'!E57:P57)+SUM('Debt cash'!E48:P48)-SUM('Debt cash'!E49:P49) -> 43.613583 | F17: =SUM('Debt cash'!Q22:AB22)-SUM('Debt cash'!Q57:AB57)+SUM('Debt cash'!Q48:AB48)-SUM('Debt cash'!Q49:AB49) -> 45.790409 | G17: =SUM('Debt cash'!AC22:AN22)-SUM('Debt cash'!AC57:AN57)+SUM('Debt cash'!AC48:AN48)-SUM('Debt cash'!AC49:AN49) -> 44.253325 | H17: =SUM('Debt cash'!AO22:AZ22)-SUM('Debt cash'!AO57:AZ57)+SUM('Debt cash'!AO48:AZ48)-SUM('Debt cash'!AO49:AZ49) -> 39.828442 | I17: =SUM('Debt cash'!BA22:BL22)-SUM('Debt cash'!BA57:BL57)+SUM('Debt cash'!BA48:BL48)-SUM('Debt cash'!BA49:BL49) -> 35.911469
C18: Transfer net discount unwind | E18: =SUM(Transfers!E31:P31)-SUM(Transfers!E35:P35) -> 13.727933 | F18: =SUM(Transfers!Q31:AB31)-SUM(Transfers!Q35:AB35) -> 7.8757993 | G18: =SUM(Transfers!AC31:AN31)-SUM(Transfers!AC35:AN35) -> 5.174375 | H18: =SUM(Transfers!AO31:AZ31)-SUM(Transfers!AO35:AZ35) -> 3.8673646 | I18: =SUM(Transfers!BA31:BL31)-SUM(Transfers!BA35:BL35) -> 1.8973111
C19: Debt FX loss / gain | E19: =SUM('Debt cash'!E19:P19) -> -1.2192331 | F19: =SUM('Debt cash'!Q19:AB19) -> 0 | G19: =SUM('Debt cash'!AC19:AN19) -> 0 | H19: =SUM('Debt cash'!AO19:AZ19) -> 0 | I19: =SUM('Debt cash'!BA19:BL19) -> 0
C20: Debt cost amortisation | E20: =SUM('Debt cash'!E23:P23) -> 1.2744 | F20: =SUM('Debt cash'!Q23:AB23) -> 1.2744 | G20: =SUM('Debt cash'!AC23:AN23) -> 1.2744 | H20: =SUM('Debt cash'!AO23:AZ23) -> 1.2744 | I20: =SUM('Debt cash'!BA23:BL23) -> 1.2744
C21: Profit before tax | E21: =E16-SUM(E17:E20) -> -11.11891 | F21: =F16-SUM(F17:F20) -> -37.065207 | G21: =G16-SUM(G17:G20) -> 0.16720494 | H21: =H16-SUM(H17:H20) -> 33.614492 | I21: =I16-SUM(I17:I20) -> 56.22707
C22: Tax | E22: =SUM('Debt cash'!E10:P10) -> 8.9562772 | F22: =SUM('Debt cash'!Q10:AB10) -> 1 | G22: =SUM('Debt cash'!AC10:AN10) -> 1 | H22: =SUM('Debt cash'!AO10:AZ10) -> 1 | I22: =SUM('Debt cash'!BA10:BL10) -> 2.9165519
C23: Net income | E23: =SUM('Debt cash'!E40:P40) -> -20.075187 | F23: =SUM('Debt cash'!Q40:AB40) -> -38.065207 | G23: =SUM('Debt cash'!AC40:AN40) -> -0.83279506 | H23: =SUM('Debt cash'!AO40:AZ40) -> 32.614492 | I23: =SUM('Debt cash'!BA40:BL40) -> 53.310518
C26: Cash from operations before interest/tax | E26: =SUM('Debt cash'!E9:P9) -> 207.438 | F26: =SUM('Debt cash'!Q9:AB9) -> 167.8 | G26: =SUM('Debt cash'!AC9:AN9) -> 184.301 | H26: =SUM('Debt cash'!AO9:AZ9) -> 186.28017 | I26: =SUM('Debt cash'!BA9:BL9) -> 183.65032
C27: Operating cash after interest/tax | E27: =E26-SUM('Debt cash'!E22:P22)-E22 -> 153.46814 | F27: =F26-SUM('Debt cash'!Q22:AB22)-F22 -> 121.00959 | G27: =G26-SUM('Debt cash'!AC22:AN22)-G22 -> 139.04767 | H27: =H26-SUM('Debt cash'!AO22:AZ22)-H22 -> 145.45173 | I27: =I26-SUM('Debt cash'!BA22:BL22)-I22 -> 144.8223
C28: Acquisition cash | E28: =SUM(Transfers!E16:P16) -> 306.61404 | F28: =SUM(Transfers!Q16:AB16) -> 180.08643 | G28: =SUM(Transfers!AC16:AN16) -> 95.296384 | H28: =SUM(Transfers!AO16:AZ16) -> 108.27322 | I28: =SUM(Transfers!BA16:BL16) -> 105.71235
C29: Disposal receipts | E29: =SUM(Transfers!E28:P28) -> 61.65492 | F29: =SUM(Transfers!Q28:AB28) -> 57.085688 | G29: =SUM(Transfers!AC28:AN28) -> 70.239973 | H29: =SUM(Transfers!AO28:AZ28) -> 50 | I29: =SUM(Transfers!BA28:BL28) -> 50
C30: Tangible and other intangible capex | E30: =SUM('Debt cash'!E13:P13) -> 28.4 | F30: =SUM('Debt cash'!Q13:AB13) -> 28.4 | G30: =SUM('Debt cash'!AC13:AN13) -> 28.4 | H30: =SUM('Debt cash'!AO13:AZ13) -> 28.4 | I30: =SUM('Debt cash'!BA13:BL13) -> 28.4
C31: Cash after operating and investing | E31: =E27-E28+E29-E30 -> -119.89098 | F31: =F27-F28+F29-F30 -> -30.391152 | G31: =G27-G28+G29-G30 -> 85.591264 | H31: =H27-H28+H29-H30 -> 58.778507 | I31: =I27-I28+I29-I30 -> 60.709948
C32: Lease principal | E32: =SUM('Debt cash'!E14:P14) -> 1.2 | F32: =SUM('Debt cash'!Q14:AB14) -> 1.2 | G32: =SUM('Debt cash'!AC14:AN14) -> 0.87 | H32: =SUM('Debt cash'!AO14:AZ14) -> 0 | I32: =SUM('Debt cash'!BA14:BL14) -> 0
C33: Mandatory debt repayment | E33: =SUM('Debt cash'!E25:P25) -> 0 | F33: =SUM('Debt cash'!Q25:AB25) -> 0 | G33: =SUM('Debt cash'!AC25:AN25) -> 0 | H33: =SUM('Debt cash'!AO25:AZ25) -> 115.99294 | I33: =SUM('Debt cash'!BA25:BL25) -> 582.70677
C34: Assumed refinancing | E34: =SUM('Debt cash'!E26:P26) -> 0 | F34: =SUM('Debt cash'!Q26:AB26) -> 0 | G34: =SUM('Debt cash'!AC26:AN26) -> 0 | H34: =SUM('Debt cash'!AO26:AZ26) -> 115.99294 | I34: =SUM('Debt cash'!BA26:BL26) -> 582.70677
C35: Net revolver draw / (repayment) | E35: =SUM('Debt cash'!E30:P30)-SUM('Debt cash'!E31:P31)+SUM('Debt cash'!E51:P51) -> 78.844979 | F35: =SUM('Debt cash'!Q30:AB30)-SUM('Debt cash'!Q31:AB31)+SUM('Debt cash'!Q51:AB51) -> 31.591152 | G35: =SUM('Debt cash'!AC30:AN30)-SUM('Debt cash'!AC31:AN31)+SUM('Debt cash'!AC51:AN51) -> -84.721264 | H35: =SUM('Debt cash'!AO30:AZ30)-SUM('Debt cash'!AO31:AZ31)+SUM('Debt cash'!AO51:AZ51) -> -58.778507 | I35: =SUM('Debt cash'!BA30:BL30)-SUM('Debt cash'!BA31:BL31)+SUM('Debt cash'!BA51:BL51) -> -60.709948
C36: Closing cash | E36: ='Debt cash'!P33 -> 25 | F36: ='Debt cash'!AB33 -> 25 | G36: ='Debt cash'!AN33 -> 25 | H36: ='Debt cash'!AZ33 -> 25 | I36: ='Debt cash'!BL33 -> 25
C39: Registration NBV | E39: =Registrations!P92 -> 445.01703 | F39: =Registrations!AB92 -> 325.14666 | G39: =Registrations!AN92 -> 231.76919 | H39: =Registrations!AZ92 -> 164.12795 | I39: =Registrations!BL92 -> 115.84211
C40: Transfer receivables | E40: =Transfers!P36 -> 59.653769 | F40: =Transfers!AB36 -> 53.932397 | G40: =Transfers!AN36 -> 34.244211 | H40: =Transfers!AZ36 -> 34.244211 | I40: =Transfers!BL36 -> 34.244211
C41: Other assets | E41: ='Debt cash'!P43 -> 964.428 | F41: ='Debt cash'!AB43 -> 976.628 | G41: ='Debt cash'!AN43 -> 978.828 | H41: ='Debt cash'!AZ43 -> 981.028 | I41: ='Debt cash'!BL43 -> 983.228
C42: Total assets | E42: ='Debt cash'!P45 -> 1494.0988 | F42: ='Debt cash'!AB45 -> 1380.7071 | G42: ='Debt cash'!AN45 -> 1269.8414 | H42: ='Debt cash'!AZ45 -> 1204.4002 | I42: ='Debt cash'!BL45 -> 1158.3143
C44: Borrowings | E44: ='Debt cash'!P36 -> 766.45415 | F44: ='Debt cash'!AB36 -> 799.3197 | G44: ='Debt cash'!AN36 -> 715.87283 | H44: ='Debt cash'!AZ36 -> 658.36873 | I44: ='Debt cash'!BL36 -> 598.93318
C45: Transfer payables | E45: =Transfers!P32 -> 271.56784 | F45: =Transfers!AB32 -> 164.57575 | G45: =Transfers!AN32 -> 138.85976 | H45: =Transfers!AZ32 -> 98.30813 | I45: =Transfers!BL32 -> 58.34732
C46: Lease liabilities | E46: ='Debt cash'!P41 -> 2.07 | F46: ='Debt cash'!AB41 -> 0.87 | G46: ='Debt cash'!AN41 -> 0 | H46: ='Debt cash'!AZ41 -> 0 | I46: ='Debt cash'!BL41 -> 0
C47: Other liabilities | E47: ='Debt cash'!P44 -> 323.719 | F47: ='Debt cash'!AB44 -> 323.719 | G47: ='Debt cash'!AN44 -> 323.719 | H47: ='Debt cash'!AZ44 -> 323.719 | I47: ='Debt cash'!BL44 -> 323.719
C48: Total liabilities | E48: ='Debt cash'!P46 -> 1363.811 | F48: ='Debt cash'!AB46 -> 1288.4845 | G48: ='Debt cash'!AN46 -> 1178.4516 | H48: ='Debt cash'!AZ46 -> 1080.3959 | I48: ='Debt cash'!BL46 -> 980.9995
C49: Equity | E49: ='Debt cash'!P42 -> 130.28781 | F49: ='Debt cash'!AB42 -> 92.222605 | G49: ='Debt cash'!AN42 -> 91.38981 | H49: ='Debt cash'!AZ42 -> 124.0043 | I49: ='Debt cash'!BL42 -> 177.31482
C52: Peak RCF | E52: =MAX('Debt cash'!E32:P32) -> 245.50323 | F52: =MAX('Debt cash'!Q32:AB32) -> 265.22178 | G52: =MAX('Debt cash'!AC32:AN32) -> 256.63236 | H52: =MAX('Debt cash'!AO32:AZ32) -> 183.18726 | I52: =MAX('Debt cash'!BA32:BL32) -> 130.30953
C53: Maximum cash reserve shortfall | E53: =MAX('Debt cash'!E34:P34) -> 0 | F53: =MAX('Debt cash'!Q34:AB34) -> 0 | G53: =MAX('Debt cash'!AC34:AN34) -> 0 | H53: =MAX('Debt cash'!AO34:AZ34) -> 3.5527137e-15 | I53: =MAX('Debt cash'!BA34:BL34) -> 0
C54: Minimum covenant headroom | E54: =MIN('Debt cash'!E38:P38) -> 90 | F54: =MIN('Debt cash'!Q38:AB38) -> 52 | G54: =MIN('Debt cash'!AC38:AN38) -> 52.54175 | H54: =MIN('Debt cash'!AO38:AZ38) -> 58.665931 | I54: =MIN('Debt cash'!BA38:BL38) -> 57.850318

Sheet Revenue costs
C2: Revenue costs
C3: £m unless stated. Evidence cut-off: 8 October 2026.
C4: Case selected | E4: =CHOOSE(Assumptions!$E$5,"Base","Downside","Upside") -> Base
C7: Month | E7: 46204 | F7: 46235 | G7: 46266 | H7: 46296 | I7: 46327 | J7: 46357 | K7: 46388 | L7: 46419 | M7: 46447 | N7: 46478 | O7: 46508 | P7: 46539 | Q7: 46569 | R7: 46600 | S7: 46631 | T7: 46661 | U7: 46692 | V7: 46722 | W7: 46753 | X7: 46784 | Y7: 46813 | Z7: 46844 | AA7: 46874 | AB7: 46905 | AC7: 46935 | AD7: 46966 | AE7: 46997 | AF7: 47027 | AG7: 47058 | AH7: 47088 | AI7: 47119 | AJ7: 47150 | AK7: 47178 | AL7: 47209 | AM7: 47239 | AN7: 47270 | AO7: 47300 | AP7: 47331 | AQ7: 47362 | AR7: 47392 | AS7: 47423 | AT7: 47453 | AU7: 47484 | AV7: 47515 | AW7: 47543 | AX7: 47574 | AY7: 47604 | AZ7: 47635 | BA7: 47665 | BB7: 47696 | BC7: 47727 | BD7: 47757 | BE7: 47788 | BF7: 47818 | BG7: 47849 | BH7: 47880 | BI7: 47908 | BJ7: 47939 | BK7: 47969 | BL7: 48000
C8: Ordinary commercial revenue | E8: =Assumptions!E8/12 -> 29.166667 | F8: =Assumptions!E8/12 -> 29.166667 | G8: =Assumptions!E8/12 -> 29.166667 | H8: =Assumptions!E8/12 -> 29.166667 | I8: =Assumptions!E8/12 -> 29.166667 | J8: =Assumptions!E8/12 -> 29.166667 | K8: =Assumptions!E8/12 -> 29.166667 | L8: =Assumptions!E8/12 -> 29.166667 | M8: =Assumptions!E8/12 -> 29.166667 | N8: =Assumptions!E8/12 -> 29.166667 | O8: =Assumptions!E8/12 -> 29.166667 | P8: =Assumptions!E8/12 -> 29.166667 | Q8: =Assumptions!F8/12 -> 30.041667 | R8: =Assumptions!F8/12 -> 30.041667 | S8: =Assumptions!F8/12 -> 30.041667 | T8: =Assumptions!F8/12 -> 30.041667 | U8: =Assumptions!F8/12 -> 30.041667 | V8: =Assumptions!F8/12 -> 30.041667 | W8: =Assumptions!F8/12 -> 30.041667 | X8: =Assumptions!F8/12 -> 30.041667 | Y8: =Assumptions!F8/12 -> 30.041667 | Z8: =Assumptions!F8/12 -> 30.041667 | AA8: =Assumptions!F8/12 -> 30.041667 | AB8: =Assumptions!F8/12 -> 30.041667 | AC8: =Assumptions!G8/12 -> 30.942917 | AD8: =Assumptions!G8/12 -> 30.942917 | AE8: =Assumptions!G8/12 -> 30.942917 | AF8: =Assumptions!G8/12 -> 30.942917 | AG8: =Assumptions!G8/12 -> 30.942917 | AH8: =Assumptions!G8/12 -> 30.942917 | AI8: =Assumptions!G8/12 -> 30.942917 | AJ8: =Assumptions!G8/12 -> 30.942917 | AK8: =Assumptions!G8/12 -> 30.942917 | AL8: =Assumptions!G8/12 -> 30.942917 | AM8: =Assumptions!G8/12 -> 30.942917 | AN8: =Assumptions!G8/12 -> 30.942917 | AO8: =Assumptions!H8/12 -> 31.871204 | AP8: =Assumptions!H8/12 -> 31.871204 | AQ8: =Assumptions!H8/12 -> 31.871204 | AR8: =Assumptions!H8/12 -> 31.871204 | AS8: =Assumptions!H8/12 -> 31.871204 | AT8: =Assumptions!H8/12 -> 31.871204 | AU8: =Assumptions!H8/12 -> 31.871204 | AV8: =Assumptions!H8/12 -> 31.871204 | AW8: =Assumptions!H8/12 -> 31.871204 | AX8: =Assumptions!H8/12 -> 31.871204 | AY8: =Assumptions!H8/12 -> 31.871204 | AZ8: =Assumptions!H8/12 -> 31.871204 | BA8: =Assumptions!I8/12 -> 32.82734 | BB8: =Assumptions!I8/12 -> 32.82734 | BC8: =Assumptions!I8/12 -> 32.82734 | BD8: =Assumptions!I8/12 -> 32.82734 | BE8: =Assumptions!I8/12 -> 32.82734 | BF8: =Assumptions!I8/12 -> 32.82734 | BG8: =Assumptions!I8/12 -> 32.82734 | BH8: =Assumptions!I8/12 -> 32.82734 | BI8: =Assumptions!I8/12 -> 32.82734 | BJ8: =Assumptions!I8/12 -> 32.82734 | BK8: =Assumptions!I8/12 -> 32.82734 | BL8: =Assumptions!I8/12 -> 32.82734
C9: Adidas recognition reduction | E9: =SUM(Assumptions!E28:E28)*0.8/12 -> 0 | F9: =SUM(Assumptions!E28:E28)*0.8/12 -> 0 | G9: =SUM(Assumptions!E28:E28)*0.8/12 -> 0 | H9: =SUM(Assumptions!E28:E28)*0.8/12 -> 0 | I9: =SUM(Assumptions!E28:E28)*0.8/12 -> 0 | J9: =SUM(Assumptions!E28:E28)*0.8/12 -> 0 | K9: =SUM(Assumptions!E28:E28)*0.8/12 -> 0 | L9: =SUM(Assumptions!E28:E28)*0.8/12 -> 0 | M9: =SUM(Assumptions!E28:E28)*0.8/12 -> 0 | N9: =SUM(Assumptions!E28:E28)*0.8/12 -> 0 | O9: =SUM(Assumptions!E28:E28)*0.8/12 -> 0 | P9: =SUM(Assumptions!E28:E28)*0.8/12 -> 0 | Q9: =SUM(Assumptions!E28:F28)*0.8/12 -> 0.066666667 | R9: =SUM(Assumptions!E28:F28)*0.8/12 -> 0.066666667 | S9: =SUM(Assumptions!E28:F28)*0.8/12 -> 0.066666667 | T9: =SUM(Assumptions!E28:F28)*0.8/12 -> 0.066666667 | U9: =SUM(Assumptions!E28:F28)*0.8/12 -> 0.066666667 | V9: =SUM(Assumptions!E28:F28)*0.8/12 -> 0.066666667 | W9: =SUM(Assumptions!E28:F28)*0.8/12 -> 0.066666667 | X9: =SUM(Assumptions!E28:F28)*0.8/12 -> 0.066666667 | Y9: =SUM(Assumptions!E28:F28)*0.8/12 -> 0.066666667 | Z9: =SUM(Assumptions!E28:F28)*0.8/12 -> 0.066666667 | AA9: =SUM(Assumptions!E28:F28)*0.8/12 -> 0.066666667 | AB9: =SUM(Assumptions!E28:F28)*0.8/12 -> 0.066666667 | AC9: =SUM(Assumptions!E28:G28)*0.8/12 -> 0.066666667 | AD9: =SUM(Assumptions!E28:G28)*0.8/12 -> 0.066666667 | AE9: =SUM(Assumptions!E28:G28)*0.8/12 -> 0.066666667 | AF9: =SUM(Assumptions!E28:G28)*0.8/12 -> 0.066666667 | AG9: =SUM(Assumptions!E28:G28)*0.8/12 -> 0.066666667 | AH9: =SUM(Assumptions!E28:G28)*0.8/12 -> 0.066666667 | AI9: =SUM(Assumptions!E28:G28)*0.8/12 -> 0.066666667 | AJ9: =SUM(Assumptions!E28:G28)*0.8/12 -> 0.066666667 | AK9: =SUM(Assumptions!E28:G28)*0.8/12 -> 0.066666667 | AL9: =SUM(Assumptions!E28:G28)*0.8/12 -> 0.066666667 | AM9: =SUM(Assumptions!E28:G28)*0.8/12 -> 0.066666667 | AN9: =SUM(Assumptions!E28:G28)*0.8/12 -> 0.066666667 | AO9: =SUM(Assumptions!E28:H28)*0.8/12 -> 0.066666667 | AP9: =SUM(Assumptions!E28:H28)*0.8/12 -> 0.066666667 | AQ9: =SUM(Assumptions!E28:H28)*0.8/12 -> 0.066666667 | AR9: =SUM(Assumptions!E28:H28)*0.8/12 -> 0.066666667 | AS9: =SUM(Assumptions!E28:H28)*0.8/12 -> 0.066666667 | AT9: =SUM(Assumptions!E28:H28)*0.8/12 -> 0.066666667 | AU9: =SUM(Assumptions!E28:H28)*0.8/12 -> 0.066666667 | AV9: =SUM(Assumptions!E28:H28)*0.8/12 -> 0.066666667 | AW9: =SUM(Assumptions!E28:H28)*0.8/12 -> 0.066666667 | AX9: =SUM(Assumptions!E28:H28)*0.8/12 -> 0.066666667 | AY9: =SUM(Assumptions!E28:H28)*0.8/12 -> 0.066666667 | AZ9: =SUM(Assumptions!E28:H28)*0.8/12 -> 0.066666667 | BA9: =SUM(Assumptions!E28:I28)*0.8/12 -> 0.066666667 | BB9: =SUM(Assumptions!E28:I28)*0.8/12 -> 0.066666667 | BC9: =SUM(Assumptions!E28:I28)*0.8/12 -> 0.066666667 | BD9: =SUM(Assumptions!E28:I28)*0.8/12 -> 0.066666667 | BE9: =SUM(Assumptions!E28:I28)*0.8/12 -> 0.066666667 | BF9: =SUM(Assumptions!E28:I28)*0.8/12 -> 0.066666667 | BG9: =SUM(Assumptions!E28:I28)*0.8/12 -> 0.066666667 | BH9: =SUM(Assumptions!E28:I28)*0.8/12 -> 0.066666667 | BI9: =SUM(Assumptions!E28:I28)*0.8/12 -> 0.066666667 | BJ9: =SUM(Assumptions!E28:I28)*0.8/12 -> 0.066666667 | BK9: =SUM(Assumptions!E28:I28)*0.8/12 -> 0.066666667 | BL9: =SUM(Assumptions!E28:I28)*0.8/12 -> 0.066666667
C10: Commercial revenue | E10: =E8-E9 -> 29.166667 | F10: =F8-F9 -> 29.166667 | G10: =G8-G9 -> 29.166667 | H10: =H8-H9 -> 29.166667 | I10: =I8-I9 -> 29.166667 | J10: =J8-J9 -> 29.166667 | K10: =K8-K9 -> 29.166667 | L10: =L8-L9 -> 29.166667 | ... BL10: =BL8-BL9 -> 32.760674
C11: Domestic/other broadcasting | E11: =Assumptions!E13/12 -> 13.333333 | F11: =Assumptions!E13/12 -> 13.333333 | G11: =Assumptions!E13/12 -> 13.333333 | H11: =Assumptions!E13/12 -> 13.333333 | I11: =Assumptions!E13/12 -> 13.333333 | J11: =Assumptions!E13/12 -> 13.333333 | K11: =Assumptions!E13/12 -> 13.333333 | L11: =Assumptions!E13/12 -> 13.333333 | M11: =Assumptions!E13/12 -> 13.333333 | N11: =Assumptions!E13/12 -> 13.333333 | O11: =Assumptions!E13/12 -> 13.333333 | P11: =Assumptions!E13/12 -> 13.333333 | Q11: =Assumptions!F13/12 -> 13.333333 | R11: =Assumptions!F13/12 -> 13.333333 | S11: =Assumptions!F13/12 -> 13.333333 | T11: =Assumptions!F13/12 -> 13.333333 | U11: =Assumptions!F13/12 -> 13.333333 | V11: =Assumptions!F13/12 -> 13.333333 | W11: =Assumptions!F13/12 -> 13.333333 | X11: =Assumptions!F13/12 -> 13.333333 | Y11: =Assumptions!F13/12 -> 13.333333 | Z11: =Assumptions!F13/12 -> 13.333333 | AA11: =Assumptions!F13/12 -> 13.333333 | AB11: =Assumptions!F13/12 -> 13.333333 | AC11: =Assumptions!G13/12 -> 13.333333 | AD11: =Assumptions!G13/12 -> 13.333333 | AE11: =Assumptions!G13/12 -> 13.333333 | AF11: =Assumptions!G13/12 -> 13.333333 | AG11: =Assumptions!G13/12 -> 13.333333 | AH11: =Assumptions!G13/12 -> 13.333333 | AI11: =Assumptions!G13/12 -> 13.333333 | AJ11: =Assumptions!G13/12 -> 13.333333 | AK11: =Assumptions!G13/12 -> 13.333333 | AL11: =Assumptions!G13/12 -> 13.333333 | AM11: =Assumptions!G13/12 -> 13.333333 | AN11: =Assumptions!G13/12 -> 13.333333 | AO11: =Assumptions!H13/12 -> 13.333333 | AP11: =Assumptions!H13/12 -> 13.333333 | AQ11: =Assumptions!H13/12 -> 13.333333 | AR11: =Assumptions!H13/12 -> 13.333333 | AS11: =Assumptions!H13/12 -> 13.333333 | AT11: =Assumptions!H13/12 -> 13.333333 | AU11: =Assumptions!H13/12 -> 13.333333 | AV11: =Assumptions!H13/12 -> 13.333333 | AW11: =Assumptions!H13/12 -> 13.333333 | AX11: =Assumptions!H13/12 -> 13.333333 | AY11: =Assumptions!H13/12 -> 13.333333 | AZ11: =Assumptions!H13/12 -> 13.333333 | BA11: =Assumptions!I13/12 -> 13.333333 | BB11: =Assumptions!I13/12 -> 13.333333 | BC11: =Assumptions!I13/12 -> 13.333333 | BD11: =Assumptions!I13/12 -> 13.333333 | BE11: =Assumptions!I13/12 -> 13.333333 | BF11: =Assumptions!I13/12 -> 13.333333 | BG11: =Assumptions!I13/12 -> 13.333333 | BH11: =Assumptions!I13/12 -> 13.333333 | BI11: =Assumptions!I13/12 -> 13.333333 | BJ11: =Assumptions!I13/12 -> 13.333333 | BK11: =Assumptions!I13/12 -> 13.333333 | BL11: =Assumptions!I13/12 -> 13.333333
C12: European broadcasting | E12: =Assumptions!E18/12 -> 5.4166667 | F12: =Assumptions!E18/12 -> 5.4166667 | G12: =Assumptions!E18/12 -> 5.4166667 | H12: =Assumptions!E18/12 -> 5.4166667 | I12: =Assumptions!E18/12 -> 5.4166667 | J12: =Assumptions!E18/12 -> 5.4166667 | K12: =Assumptions!E18/12 -> 5.4166667 | L12: =Assumptions!E18/12 -> 5.4166667 | M12: =Assumptions!E18/12 -> 5.4166667 | N12: =Assumptions!E18/12 -> 5.4166667 | O12: =Assumptions!E18/12 -> 5.4166667 | P12: =Assumptions!E18/12 -> 5.4166667 | Q12: =Assumptions!F18/12 -> 2.9166667 | R12: =Assumptions!F18/12 -> 2.9166667 | S12: =Assumptions!F18/12 -> 2.9166667 | T12: =Assumptions!F18/12 -> 2.9166667 | U12: =Assumptions!F18/12 -> 2.9166667 | V12: =Assumptions!F18/12 -> 2.9166667 | W12: =Assumptions!F18/12 -> 2.9166667 | X12: =Assumptions!F18/12 -> 2.9166667 | Y12: =Assumptions!F18/12 -> 2.9166667 | Z12: =Assumptions!F18/12 -> 2.9166667 | AA12: =Assumptions!F18/12 -> 2.9166667 | AB12: =Assumptions!F18/12 -> 2.9166667 | AC12: =Assumptions!G18/12 -> 2.9166667 | AD12: =Assumptions!G18/12 -> 2.9166667 | AE12: =Assumptions!G18/12 -> 2.9166667 | AF12: =Assumptions!G18/12 -> 2.9166667 | AG12: =Assumptions!G18/12 -> 2.9166667 | AH12: =Assumptions!G18/12 -> 2.9166667 | AI12: =Assumptions!G18/12 -> 2.9166667 | AJ12: =Assumptions!G18/12 -> 2.9166667 | AK12: =Assumptions!G18/12 -> 2.9166667 | AL12: =Assumptions!G18/12 -> 2.9166667 | AM12: =Assumptions!G18/12 -> 2.9166667 | AN12: =Assumptions!G18/12 -> 2.9166667 | AO12: =Assumptions!H18/12 -> 2.9166667 | AP12: =Assumptions!H18/12 -> 2.9166667 | AQ12: =Assumptions!H18/12 -> 2.9166667 | AR12: =Assumptions!H18/12 -> 2.9166667 | AS12: =Assumptions!H18/12 -> 2.9166667 | AT12: =Assumptions!H18/12 -> 2.9166667 | AU12: =Assumptions!H18/12 -> 2.9166667 | AV12: =Assumptions!H18/12 -> 2.9166667 | AW12: =Assumptions!H18/12 -> 2.9166667 | AX12: =Assumptions!H18/12 -> 2.9166667 | AY12: =Assumptions!H18/12 -> 2.9166667 | AZ12: =Assumptions!H18/12 -> 2.9166667 | BA12: =Assumptions!I18/12 -> 2.9166667 | BB12: =Assumptions!I18/12 -> 2.9166667 | BC12: =Assumptions!I18/12 -> 2.9166667 | BD12: =Assumptions!I18/12 -> 2.9166667 | BE12: =Assumptions!I18/12 -> 2.9166667 | BF12: =Assumptions!I18/12 -> 2.9166667 | BG12: =Assumptions!I18/12 -> 2.9166667 | BH12: =Assumptions!I18/12 -> 2.9166667 | BI12: =Assumptions!I18/12 -> 2.9166667 | BJ12: =Assumptions!I18/12 -> 2.9166667 | BK12: =Assumptions!I18/12 -> 2.9166667 | BL12: =Assumptions!I18/12 -> 2.9166667
C13: Matchday | E13: =Assumptions!E23/12 -> 14.583333 | F13: =Assumptions!E23/12 -> 14.583333 | G13: =Assumptions!E23/12 -> 14.583333 | H13: =Assumptions!E23/12 -> 14.583333 | I13: =Assumptions!E23/12 -> 14.583333 | J13: =Assumptions!E23/12 -> 14.583333 | K13: =Assumptions!E23/12 -> 14.583333 | L13: =Assumptions!E23/12 -> 14.583333 | M13: =Assumptions!E23/12 -> 14.583333 | N13: =Assumptions!E23/12 -> 14.583333 | O13: =Assumptions!E23/12 -> 14.583333 | P13: =Assumptions!E23/12 -> 14.583333 | Q13: =Assumptions!F23/12 -> 13.333333 | R13: =Assumptions!F23/12 -> 13.333333 | S13: =Assumptions!F23/12 -> 13.333333 | T13: =Assumptions!F23/12 -> 13.333333 | U13: =Assumptions!F23/12 -> 13.333333 | V13: =Assumptions!F23/12 -> 13.333333 | W13: =Assumptions!F23/12 -> 13.333333 | X13: =Assumptions!F23/12 -> 13.333333 | Y13: =Assumptions!F23/12 -> 13.333333 | Z13: =Assumptions!F23/12 -> 13.333333 | AA13: =Assumptions!F23/12 -> 13.333333 | AB13: =Assumptions!F23/12 -> 13.333333 | AC13: =Assumptions!G23/12 -> 13.6 | AD13: =Assumptions!G23/12 -> 13.6 | AE13: =Assumptions!G23/12 -> 13.6 | AF13: =Assumptions!G23/12 -> 13.6 | AG13: =Assumptions!G23/12 -> 13.6 | AH13: =Assumptions!G23/12 -> 13.6 | AI13: =Assumptions!G23/12 -> 13.6 | AJ13: =Assumptions!G23/12 -> 13.6 | AK13: =Assumptions!G23/12 -> 13.6 | AL13: =Assumptions!G23/12 -> 13.6 | AM13: =Assumptions!G23/12 -> 13.6 | AN13: =Assumptions!G23/12 -> 13.6 | AO13: =Assumptions!H23/12 -> 13.872 | AP13: =Assumptions!H23/12 -> 13.872 | AQ13: =Assumptions!H23/12 -> 13.872 | AR13: =Assumptions!H23/12 -> 13.872 | AS13: =Assumptions!H23/12 -> 13.872 | AT13: =Assumptions!H23/12 -> 13.872 | AU13: =Assumptions!H23/12 -> 13.872 | AV13: =Assumptions!H23/12 -> 13.872 | AW13: =Assumptions!H23/12 -> 13.872 | AX13: =Assumptions!H23/12 -> 13.872 | AY13: =Assumptions!H23/12 -> 13.872 | AZ13: =Assumptions!H23/12 -> 13.872 | BA13: =Assumptions!I23/12 -> 14.14944 | BB13: =Assumptions!I23/12 -> 14.14944 | BC13: =Assumptions!I23/12 -> 14.14944 | BD13: =Assumptions!I23/12 -> 14.14944 | BE13: =Assumptions!I23/12 -> 14.14944 | BF13: =Assumptions!I23/12 -> 14.14944 | BG13: =Assumptions!I23/12 -> 14.14944 | BH13: =Assumptions!I23/12 -> 14.14944 | BI13: =Assumptions!I23/12 -> 14.14944 | BJ13: =Assumptions!I23/12 -> 14.14944 | BK13: =Assumptions!I23/12 -> 14.14944 | BL13: =Assumptions!I23/12 -> 14.14944
C14: Total revenue | E14: =SUM(E10:E13) -> 62.5 | F14: =SUM(F10:F13) -> 62.5 | G14: =SUM(G10:G13) -> 62.5 | H14: =SUM(H10:H13) -> 62.5 | I14: =SUM(I10:I13) -> 62.5 | J14: =SUM(J10:J13) -> 62.5 | K14: =SUM(K10:K13) -> 62.5 | L14: =SUM(L10:L13) -> 62.5 | ... BL14: =SUM(BL10:BL13) -> 63.160114
C16: Inherited group payroll | E16: =Assumptions!E38/12 -> 29.166667 | F16: =E16 -> 29.166667 | G16: =F16 -> 29.166667 | H16: =G16 -> 29.166667 | I16: =H16 -> 29.166667 | J16: =I16 -> 29.166667 | K16: =J16 -> 29.166667 | L16: =K16 -> 29.166667 | M16: =L16 -> 29.166667 | ... P16: =O16 -> 29.166667 | Q16: =P16*(1+Assumptions!F43)-Assumptions!F53/12 -> 28.083333 | R16: =Q16 -> 28.083333 | S16: =R16 -> 28.083333 | T16: =S16 -> 28.083333 | U16: =T16 -> 28.083333 | V16: =U16 -> 28.083333 | W16: =V16 -> 28.083333 | X16: =W16 -> 28.083333 | Y16: =X16 -> 28.083333 | ... AB16: =AA16 -> 28.083333 | AC16: =AB16*(1+Assumptions!G43)-Assumptions!G53/12 -> 27.395 | AD16: =AC16 -> 27.395 | AE16: =AD16 -> 27.395 | AF16: =AE16 -> 27.395 | AG16: =AF16 -> 27.395 | AH16: =AG16 -> 27.395 | AI16: =AH16 -> 27.395 | AJ16: =AI16 -> 27.395 | AK16: =AJ16 -> 27.395 | ... AN16: =AM16 -> 27.395 | AO16: =AN16*(1+Assumptions!H43)-Assumptions!H53/12 -> 27.109567 | AP16: =AO16 -> 27.109567 | AQ16: =AP16 -> 27.109567 | AR16: =AQ16 -> 27.109567 | AS16: =AR16 -> 27.109567 | AT16: =AS16 -> 27.109567 | AU16: =AT16 -> 27.109567 | AV16: =AU16 -> 27.109567 | AW16: =AV16 -> 27.109567 | ... AZ16: =AY16 -> 27.109567 | BA16: =AZ16*(1+Assumptions!I43)-Assumptions!I53/12 -> 27.235091 | BB16: =BA16 -> 27.235091 | BC16: =BB16 -> 27.235091 | BD16: =BC16 -> 27.235091 | BE16: =BD16 -> 27.235091 | BF16: =BE16 -> 27.235091 | BG16: =BF16 -> 27.235091 | BH16: =BG16 -> 27.235091 | BI16: =BH16 -> 27.235091 | ... BL16: =BK16 -> 27.235091
C17: Relevant retained squad payroll | E17: =E16*IF(Capacity!$E$9<0,Assumptions!E48,Capacity!$E$9) -> 21.875 | F17: =F16*IF(Capacity!$E$9<0,Assumptions!E48,Capacity!$E$9) -> 21.875 | G17: =G16*IF(Capacity!$E$9<0,Assumptions!E48,Capacity!$E$9) -> 21.875 | H17: =H16*IF(Capacity!$E$9<0,Assumptions!E48,Capacity!$E$9) -> 21.875 | I17: =I16*IF(Capacity!$E$9<0,Assumptions!E48,Capacity!$E$9) -> 21.875 | J17: =J16*IF(Capacity!$E$9<0,Assumptions!E48,Capacity!$E$9) -> 21.875 | K17: =K16*IF(Capacity!$E$9<0,Assumptions!E48,Capacity!$E$9) -> 21.875 | L17: =L16*IF(Capacity!$E$9<0,Assumptions!E48,Capacity!$E$9) -> 21.875 | M17: =M16*IF(Capacity!$E$9<0,Assumptions!E48,Capacity!$E$9) -> 21.875 | N17: =N16*IF(Capacity!$E$9<0,Assumptions!E48,Capacity!$E$9) -> 21.875 | O17: =O16*IF(Capacity!$E$9<0,Assumptions!E48,Capacity!$E$9) -> 21.875 | P17: =P16*IF(Capacity!$E$9<0,Assumptions!E48,Capacity!$E$9) -> 21.875 | Q17: =Q16*IF(Capacity!$E$9<0,Assumptions!F48,Capacity!$E$9) -> 21.0625 | R17: =R16*IF(Capacity!$E$9<0,Assumptions!F48,Capacity!$E$9) -> 21.0625 | S17: =S16*IF(Capacity!$E$9<0,Assumptions!F48,Capacity!$E$9) -> 21.0625 | T17: =T16*IF(Capacity!$E$9<0,Assumptions!F48,Capacity!$E$9) -> 21.0625 | U17: =U16*IF(Capacity!$E$9<0,Assumptions!F48,Capacity!$E$9) -> 21.0625 | V17: =V16*IF(Capacity!$E$9<0,Assumptions!F48,Capacity!$E$9) -> 21.0625 | W17: =W16*IF(Capacity!$E$9<0,Assumptions!F48,Capacity!$E$9) -> 21.0625 | X17: =X16*IF(Capacity!$E$9<0,Assumptions!F48,Capacity!$E$9) -> 21.0625 | Y17: =Y16*IF(Capacity!$E$9<0,Assumptions!F48,Capacity!$E$9) -> 21.0625 | Z17: =Z16*IF(Capacity!$E$9<0,Assumptions!F48,Capacity!$E$9) -> 21.0625 | AA17: =AA16*IF(Capacity!$E$9<0,Assumptions!F48,Capacity!$E$9) -> 21.0625 | AB17: =AB16*IF(Capacity!$E$9<0,Assumptions!F48,Capacity!$E$9) -> 21.0625 | AC17: =AC16*IF(Capacity!$E$9<0,Assumptions!G48,Capacity!$E$9) -> 20.54625 | AD17: =AD16*IF(Capacity!$E$9<0,Assumptions!G48,Capacity!$E$9) -> 20.54625 | AE17: =AE16*IF(Capacity!$E$9<0,Assumptions!G48,Capacity!$E$9) -> 20.54625 | AF17: =AF16*IF(Capacity!$E$9<0,Assumptions!G48,Capacity!$E$9) -> 20.54625 | AG17: =AG16*IF(Capacity!$E$9<0,Assumptions!G48,Capacity!$E$9) -> 20.54625 | AH17: =AH16*IF(Capacity!$E$9<0,Assumptions!G48,Capacity!$E$9) -> 20.54625 | AI17: =AI16*IF(Capacity!$E$9<0,Assumptions!G48,Capacity!$E$9) -> 20.54625 | AJ17: =AJ16*IF(Capacity!$E$9<0,Assumptions!G48,Capacity!$E$9) -> 20.54625 | AK17: =AK16*IF(Capacity!$E$9<0,Assumptions!G48,Capacity!$E$9) -> 20.54625 | AL17: =AL16*IF(Capacity!$E$9<0,Assumptions!G48,Capacity!$E$9) -> 20.54625 | AM17: =AM16*IF(Capacity!$E$9<0,Assumptions!G48,Capacity!$E$9) -> 20.54625 | AN17: =AN16*IF(Capacity!$E$9<0,Assumptions!G48,Capacity!$E$9) -> 20.54625 | AO17: =AO16*IF(Capacity!$E$9<0,Assumptions!H48,Capacity!$E$9) -> 20.332175 | AP17: =AP16*IF(Capacity!$E$9<0,Assumptions!H48,Capacity!$E$9) -> 20.332175 | AQ17: =AQ16*IF(Capacity!$E$9<0,Assumptions!H48,Capacity!$E$9) -> 20.332175 | AR17: =AR16*IF(Capacity!$E$9<0,Assumptions!H48,Capacity!$E$9) -> 20.332175 | AS17: =AS16*IF(Capacity!$E$9<0,Assumptions!H48,Capacity!$E$9) -> 20.332175 | AT17: =AT16*IF(Capacity!$E$9<0,Assumptions!H48,Capacity!$E$9) -> 20.332175 | AU17: =AU16*IF(Capacity!$E$9<0,Assumptions!H48,Capacity!$E$9) -> 20.332175 | AV17: =AV16*IF(Capacity!$E$9<0,Assumptions!H48,Capacity!$E$9) -> 20.332175 | AW17: =AW16*IF(Capacity!$E$9<0,Assumptions!H48,Capacity!$E$9) -> 20.332175 | AX17: =AX16*IF(Capacity!$E$9<0,Assumptions!H48,Capacity!$E$9) -> 20.332175 | AY17: =AY16*IF(Capacity!$E$9<0,Assumptions!H48,Capacity!$E$9) -> 20.332175 | AZ17: =AZ16*IF(Capacity!$E$9<0,Assumptions!H48,Capacity!$E$9) -> 20.332175 | BA17: =BA16*IF(Capacity!$E$9<0,Assumptions!I48,Capacity!$E$9) -> 20.426319 | BB17: =BB16*IF(Capacity!$E$9<0,Assumptions!I48,Capacity!$E$9) -> 20.426319 | BC17: =BC16*IF(Capacity!$E$9<0,Assumptions!I48,Capacity!$E$9) -> 20.426319 | BD17: =BD16*IF(Capacity!$E$9<0,Assumptions!I48,Capacity!$E$9) -> 20.426319 | BE17: =BE16*IF(Capacity!$E$9<0,Assumptions!I48,Capacity!$E$9) -> 20.426319 | BF17: =BF16*IF(Capacity!$E$9<0,Assumptions!I48,Capacity!$E$9) -> 20.426319 | BG17: =BG16*IF(Capacity!$E$9<0,Assumptions!I48,Capacity!$E$9) -> 20.426319 | BH17: =BH16*IF(Capacity!$E$9<0,Assumptions!I48,Capacity!$E$9) -> 20.426319 | BI17: =BI16*IF(Capacity!$E$9<0,Assumptions!I48,Capacity!$E$9) -> 20.426319 | BJ17: =BJ16*IF(Capacity!$E$9<0,Assumptions!I48,Capacity!$E$9) -> 20.426319 | BK17: =BK16*IF(Capacity!$E$9<0,Assumptions!I48,Capacity!$E$9) -> 20.426319 | BL17: =BL16*IF(Capacity!$E$9<0,Assumptions!I48,Capacity!$E$9) -> 20.426319
C18: New cohort all-in payroll | E18: =0 -> 0 | F18: =0 -> 0 | G18: =0 -> 0 | H18: =0 -> 0 | I18: =0 -> 0 | J18: =0 -> 0 | K18: =IF(0<Assumptions!E83*12,Capacity!$E$7/12,0) -> 0 | L18: =IF(1<Assumptions!E83*12,Capacity!$E$7/12,0) -> 0 | M18: =IF(2<Assumptions!E83*12,Capacity!$E$7/12,0) -> 0 | N18: =IF(3<Assumptions!E83*12,Capacity!$E$7/12,0) -> 0 | O18: =IF(4<Assumptions!E83*12,Capacity!$E$7/12,0) -> 0 | P18: =IF(5<Assumptions!E83*12,Capacity!$E$7/12,0) -> 0 | Q18: =IF(6<Assumptions!E83*12,Capacity!$E$7/12,0)+IF(0<Assumptions!F83*12,Assumptions!F68/12,0) -> 1 | R18: =IF(7<Assumptions!E83*12,Capacity!$E$7/12,0)+IF(1<Assumptions!F83*12,Assumptions!F68/12,0) -> 1 | S18: =IF(8<Assumptions!E83*12,Capacity!$E$7/12,0)+IF(2<Assumptions!F83*12,Assumptions!F68/12,0) -> 1 | T18: =IF(9<Assumptions!E83*12,Capacity!$E$7/12,0)+IF(3<Assumptions!F83*12,Assumptions!F68/12,0) -> 1 | U18: =IF(10<Assumptions!E83*12,Capacity!$E$7/12,0)+IF(4<Assumptions!F83*12,Assumptions!F68/12,0) -> 1 | V18: =IF(11<Assumptions!E83*12,Capacity!$E$7/12,0)+IF(5<Assumptions!F83*12,Assumptions!F68/12,0) -> 1 | W18: =IF(12<Assumptions!E83*12,Capacity!$E$7/12,0)+IF(6<Assumptions!F83*12,Assumptions!F68/12,0) -> 1 | X18: =IF(13<Assumptions!E83*12,Capacity!$E$7/12,0)+IF(7<Assumptions!F83*12,Assumptions!F68/12,0) -> 1 | Y18: =IF(14<Assumptions!E83*12,Capacity!$E$7/12,0)+IF(8<Assumptions!F83*12,Assumptions!F68/12,0) -> 1 | Z18: =IF(15<Assumptions!E83*12,Capacity!$E$7/12,0)+IF(9<Assumptions!F83*12,Assumptions!F68/12,0) -> 1 | AA18: =IF(16<Assumptions!E83*12,Capacity!$E$7/12,0)+IF(10<Assumptions!F83*12,Assumptions!F68/12,0) -> 1 | AB18: =IF(17<Assumptions!E83*12,Capacity!$E$7/12,0)+IF(11<Assumptions!F83*12,Assumptions!F68/12,0) -> 1 | AC18: =IF(18<Assumptions!E83*12,Capacity!$E$7/12,0)+IF(12<Assumptions!F83*12,Assumptions!F68/12,0)+IF(0<Assumptions!G83*12,Assumptions!G68/12,0) -> 2 | AD18: =IF(19<Assumptions!E83*12,Capacity!$E$7/12,0)+IF(13<Assumptions!F83*12,Assumptions!F68/12,0)+IF(1<Assumptions!G83*12,Assumptions!G68/12,0) -> 2 | AE18: =IF(20<Assumptions!E83*12,Capacity!$E$7/12,0)+IF(14<Assumptions!F83*12,Assumptions!F68/12,0)+IF(2<Assumptions!G83*12,Assumptions!G68/12,0) -> 2 | AF18: =IF(21<Assumptions!E83*12,Capacity!$E$7/12,0)+IF(15<Assumptions!F83*12,Assumptions!F68/12,0)+IF(3<Assumptions!G83*12,Assumptions!G68/12,0) -> 2 | AG18: =IF(22<Assumptions!E83*12,Capacity!$E$7/12,0)+IF(16<Assumptions!F83*12,Assumptions!F68/12,0)+IF(4<Assumptions!G83*12,Assumptions!G68/12,0) -> 2 | AH18: =IF(23<Assumptions!E83*12,Capacity!$E$7/12,0)+IF(17<Assumptions!F83*12,Assumptions!F68/12,0)+IF(5<Assumptions!G83*12,Assumptions!G68/12,0) -> 2 | AI18: =IF(24<Assumptions!E83*12,Capacity!$E$7/12,0)+IF(18<Assumptions!F83*12,Assumptions!F68/12,0)+IF(6<Assumptions!G83*12,Assumptions!G68/12,0) -> 2 | AJ18: =IF(25<Assumptions!E83*12,Capacity!$E$7/12,0)+IF(19<Assumptions!F83*12,Assumptions!F68/12,0)+IF(7<Assumptions!G83*12,Assumptions!G68/12,0) -> 2 | AK18: =IF(26<Assumptions!E83*12,Capacity!$E$7/12,0)+IF(20<Assumptions!F83*12,Assumptions!F68/12,0)+IF(8<Assumptions!G83*12,Assumptions!G68/12,0) -> 2 | AL18: =IF(27<Assumptions!E83*12,Capacity!$E$7/12,0)+IF(21<Assumptions!F83*12,Assumptions!F68/12,0)+IF(9<Assumptions!G83*12,Assumptions!G68/12,0) -> 2 | AM18: =IF(28<Assumptions!E83*12,Capacity!$E$7/12,0)+IF(22<Assumptions!F83*12,Assumptions!F68/12,0)+IF(10<Assumptions!G83*12,Assumptions!G68/12,0) -> 2 | AN18: =IF(29<Assumptions!E83*12,Capacity!$E$7/12,0)+IF(23<Assumptions!F83*12,Assumptions!F68/12,0)+IF(11<Assumptions!G83*12,Assumptions!G68/12,0) -> 2 | AO18: =IF(30<Assumptions!E83*12,Capacity!$E$7/12,0)+IF(24<Assumptions!F83*12,Assumptions!F68/12,0)+IF(12<Assumptions!G83*12,Assumptions!G68/12,0)+IF(0<Assumptions!H83*12,Assumptions!H68/12,0) -> 3 | AP18: =IF(31<Assumptions!E83*12,Capacity!$E$7/12,0)+IF(25<Assumptions!F83*12,Assumptions!F68/12,0)+IF(13<Assumptions!G83*12,Assumptions!G68/12,0)+IF(1<Assumptions!H83*12,Assumptions!H68/12,0) -> 3 | AQ18: =IF(32<Assumptions!E83*12,Capacity!$E$7/12,0)+IF(26<Assumptions!F83*12,Assumptions!F68/12,0)+IF(14<Assumptions!G83*12,Assumptions!G68/12,0)+IF(2<Assumptions!H83*12,Assumptions!H68/12,0) -> 3 | AR18: =IF(33<Assumptions!E83*12,Capacity!$E$7/12,0)+IF(27<Assumptions!F83*12,Assumptions!F68/12,0)+IF(15<Assumptions!G83*12,Assumptions!G68/12,0)+IF(3<Assumptions!H83*12,Assumptions!H68/12,0) -> 3 | AS18: =IF(34<Assumptions!E83*12,Capacity!$E$7/12,0)+IF(28<Assumptions!F83*12,Assumptions!F68/12,0)+IF(16<Assumptions!G83*12,Assumptions!G68/12,0)+IF(4<Assumptions!H83*12,Assumptions!H68/12,0) -> 3 | AT18: =IF(35<Assumptions!E83*12,Capacity!$E$7/12,0)+IF(29<Assumptions!F83*12,Assumptions!F68/12,0)+IF(17<Assumptions!G83*12,Assumptions!G68/12,0)+IF(5<Assumptions!H83*12,Assumptions!H68/12,0) -> 3 | AU18: =IF(36<Assumptions!E83*12,Capacity!$E$7/12,0)+IF(30<Assumptions!F83*12,Assumptions!F68/12,0)+IF(18<Assumptions!G83*12,Assumptions!G68/12,0)+IF(6<Assumptions!H83*12,Assumptions!H68/12,0) -> 3 | AV18: =IF(37<Assumptions!E83*12,Capacity!$E$7/12,0)+IF(31<Assumptions!F83*12,Assumptions!F68/12,0)+IF(19<Assumptions!G83*12,Assumptions!G68/12,0)+IF(7<Assumptions!H83*12,Assumptions!H68/12,0) -> 3 | AW18: =IF(38<Assumptions!E83*12,Capacity!$E$7/12,0)+IF(32<Assumptions!F83*12,Assumptions!F68/12,0)+IF(20<Assumptions!G83*12,Assumptions!G68/12,0)+IF(8<Assumptions!H83*12,Assumptions!H68/12,0) -> 3 | AX18: =IF(39<Assumptions!E83*12,Capacity!$E$7/12,0)+IF(33<Assumptions!F83*12,Assumptions!F68/12,0)+IF(21<Assumptions!G83*12,Assumptions!G68/12,0)+IF(9<Assumptions!H83*12,Assumptions!H68/12,0) -> 3 | AY18: =IF(40<Assumptions!E83*12,Capacity!$E$7/12,0)+IF(34<Assumptions!F83*12,Assumptions!F68/12,0)+IF(22<Assumptions!G83*12,Assumptions!G68/12,0)+IF(10<Assumptions!H83*12,Assumptions!H68/12,0) -> 3 | AZ18: =IF(41<Assumptions!E83*12,Capacity!$E$7/12,0)+IF(35<Assumptions!F83*12,Assumptions!F68/12,0)+IF(23<Assumptions!G83*12,Assumptions!G68/12,0)+IF(11<Assumptions!H83*12,Assumptions!H68/12,0) -> 3 | BA18: =IF(42<Assumptions!E83*12,Capacity!$E$7/12,0)+IF(36<Assumptions!F83*12,Assumptions!F68/12,0)+IF(24<Assumptions!G83*12,Assumptions!G68/12,0)+IF(12<Assumptions!H83*12,Assumptions!H68/12,0)+IF(0<Assumptions!I83*12,Assumptions!I68/12,0) -> 4 | BB18: =IF(43<Assumptions!E83*12,Capacity!$E$7/12,0)+IF(37<Assumptions!F83*12,Assumptions!F68/12,0)+IF(25<Assumptions!G83*12,Assumptions!G68/12,0)+IF(13<Assumptions!H83*12,Assumptions!H68/12,0)+IF(1<Assumptions!I83*12,Assumptions!I68/12,0) -> 4 | BC18: =IF(44<Assumptions!E83*12,Capacity!$E$7/12,0)+IF(38<Assumptions!F83*12,Assumptions!F68/12,0)+IF(26<Assumptions!G83*12,Assumptions!G68/12,0)+IF(14<Assumptions!H83*12,Assumptions!H68/12,0)+IF(2<Assumptions!I83*12,Assumptions!I68/12,0) -> 4 | BD18: =IF(45<Assumptions!E83*12,Capacity!$E$7/12,0)+IF(39<Assumptions!F83*12,Assumptions!F68/12,0)+IF(27<Assumptions!G83*12,Assumptions!G68/12,0)+IF(15<Assumptions!H83*12,Assumptions!H68/12,0)+IF(3<Assumptions!I83*12,Assumptions!I68/12,0) -> 4 | BE18: =IF(46<Assumptions!E83*12,Capacity!$E$7/12,0)+IF(40<Assumptions!F83*12,Assumptions!F68/12,0)+IF(28<Assumptions!G83*12,Assumptions!G68/12,0)+IF(16<Assumptions!H83*12,Assumptions!H68/12,0)+IF(4<Assumptions!I83*12,Assumptions!I68/12,0) -> 4 | BF18: =IF(47<Assumptions!E83*12,Capacity!$E$7/12,0)+IF(41<Assumptions!F83*12,Assumptions!F68/12,0)+IF(29<Assumptions!G83*12,Assumptions!G68/12,0)+IF(17<Assumptions!H83*12,Assumptions!H68/12,0)+IF(5<Assumptions!I83*12,Assumptions!I68/12,0) -> 4 | BG18: =IF(48<Assumptions!E83*12,Capacity!$E$7/12,0)+IF(42<Assumptions!F83*12,Assumptions!F68/12,0)+IF(30<Assumptions!G83*12,Assumptions!G68/12,0)+IF(18<Assumptions!H83*12,Assumptions!H68/12,0)+IF(6<Assumptions!I83*12,Assumptions!I68/12,0) -> 4 | BH18: =IF(49<Assumptions!E83*12,Capacity!$E$7/12,0)+IF(43<Assumptions!F83*12,Assumptions!F68/12,0)+IF(31<Assumptions!G83*12,Assumptions!G68/12,0)+IF(19<Assumptions!H83*12,Assumptions!H68/12,0)+IF(7<Assumptions!I83*12,Assumptions!I68/12,0) -> 4 | BI18: =IF(50<Assumptions!E83*12,Capacity!$E$7/12,0)+IF(44<Assumptions!F83*12,Assumptions!F68/12,0)+IF(32<Assumptions!G83*12,Assumptions!G68/12,0)+IF(20<Assumptions!H83*12,Assumptions!H68/12,0)+IF(8<Assumptions!I83*12,Assumptions!I68/12,0) -> 4 | BJ18: =IF(51<Assumptions!E83*12,Capacity!$E$7/12,0)+IF(45<Assumptions!F83*12,Assumptions!F68/12,0)+IF(33<Assumptions!G83*12,Assumptions!G68/12,0)+IF(21<Assumptions!H83*12,Assumptions!H68/12,0)+IF(9<Assumptions!I83*12,Assumptions!I68/12,0) -> 4 | BK18: =IF(52<Assumptions!E83*12,Capacity!$E$7/12,0)+IF(46<Assumptions!F83*12,Assumptions!F68/12,0)+IF(34<Assumptions!G83*12,Assumptions!G68/12,0)+IF(22<Assumptions!H83*12,Assumptions!H68/12,0)+IF(10<Assumptions!I83*12,Assumptions!I68/12,0) -> 4 | BL18: =IF(53<Assumptions!E83*12,Capacity!$E$7/12,0)+IF(47<Assumptions!F83*12,Assumptions!F68/12,0)+IF(35<Assumptions!G83*12,Assumptions!G68/12,0)+IF(23<Assumptions!H83*12,Assumptions!H68/12,0)+IF(11<Assumptions!I83*12,Assumptions!I68/12,0) -> 4
C19: Total employee cost | E19: =E16+E18 -> 29.166667 | F19: =F16+F18 -> 29.166667 | G19: =G16+G18 -> 29.166667 | H19: =H16+H18 -> 29.166667 | I19: =I16+I18 -> 29.166667 | J19: =J16+J18 -> 29.166667 | K19: =K16+K18 -> 29.166667 | L19: =L16+L18 -> 29.166667 | ... BL19: =BL16+BL18 -> 31.235091
C20: Relevant actual squad payroll | E20: =E17+E18 -> 21.875 | F20: =F17+F18 -> 21.875 | G20: =G17+G18 -> 21.875 | H20: =H17+H18 -> 21.875 | I20: =I17+I18 -> 21.875 | J20: =J17+J18 -> 21.875 | K20: =K17+K18 -> 21.875 | L20: =L17+L18 -> 21.875 | ... BL20: =BL17+BL18 -> 24.426319
C21: Other operating costs | E21: =Assumptions!E58/12 -> 15.416667 | F21: =Assumptions!E58/12 -> 15.416667 | G21: =Assumptions!E58/12 -> 15.416667 | H21: =Assumptions!E58/12 -> 15.416667 | I21: =Assumptions!E58/12 -> 15.416667 | J21: =Assumptions!E58/12 -> 15.416667 | K21: =Assumptions!E58/12 -> 15.416667 | L21: =Assumptions!E58/12 -> 15.416667 | M21: =Assumptions!E58/12 -> 15.416667 | N21: =Assumptions!E58/12 -> 15.416667 | O21: =Assumptions!E58/12 -> 15.416667 | P21: =Assumptions!E58/12 -> 15.416667 | Q21: =Assumptions!F58/12 -> 15.725 | R21: =Assumptions!F58/12 -> 15.725 | S21: =Assumptions!F58/12 -> 15.725 | T21: =Assumptions!F58/12 -> 15.725 | U21: =Assumptions!F58/12 -> 15.725 | V21: =Assumptions!F58/12 -> 15.725 | W21: =Assumptions!F58/12 -> 15.725 | X21: =Assumptions!F58/12 -> 15.725 | Y21: =Assumptions!F58/12 -> 15.725 | Z21: =Assumptions!F58/12 -> 15.725 | AA21: =Assumptions!F58/12 -> 15.725 | AB21: =Assumptions!F58/12 -> 15.725 | AC21: =Assumptions!G58/12 -> 16.0395 | AD21: =Assumptions!G58/12 -> 16.0395 | AE21: =Assumptions!G58/12 -> 16.0395 | AF21: =Assumptions!G58/12 -> 16.0395 | AG21: =Assumptions!G58/12 -> 16.0395 | AH21: =Assumptions!G58/12 -> 16.0395 | AI21: =Assumptions!G58/12 -> 16.0395 | AJ21: =Assumptions!G58/12 -> 16.0395 | AK21: =Assumptions!G58/12 -> 16.0395 | AL21: =Assumptions!G58/12 -> 16.0395 | AM21: =Assumptions!G58/12 -> 16.0395 | AN21: =Assumptions!G58/12 -> 16.0395 | AO21: =Assumptions!H58/12 -> 16.36029 | AP21: =Assumptions!H58/12 -> 16.36029 | AQ21: =Assumptions!H58/12 -> 16.36029 | AR21: =Assumptions!H58/12 -> 16.36029 | AS21: =Assumptions!H58/12 -> 16.36029 | AT21: =Assumptions!H58/12 -> 16.36029 | AU21: =Assumptions!H58/12 -> 16.36029 | AV21: =Assumptions!H58/12 -> 16.36029 | AW21: =Assumptions!H58/12 -> 16.36029 | AX21: =Assumptions!H58/12 -> 16.36029 | AY21: =Assumptions!H58/12 -> 16.36029 | AZ21: =Assumptions!H58/12 -> 16.36029 | BA21: =Assumptions!I58/12 -> 16.687496 | BB21: =Assumptions!I58/12 -> 16.687496 | BC21: =Assumptions!I58/12 -> 16.687496 | BD21: =Assumptions!I58/12 -> 16.687496 | BE21: =Assumptions!I58/12 -> 16.687496 | BF21: =Assumptions!I58/12 -> 16.687496 | BG21: =Assumptions!I58/12 -> 16.687496 | BH21: =Assumptions!I58/12 -> 16.687496 | BI21: =Assumptions!I58/12 -> 16.687496 | BJ21: =Assumptions!I58/12 -> 16.687496 | BK21: =Assumptions!I58/12 -> 16.687496 | BL21: =Assumptions!I58/12 -> 16.687496
C22: EBITDA before disposal gains | E22: =E14-E19-E21 -> 17.916667 | F22: =F14-F19-F21 -> 17.916667 | G22: =G14-G19-G21 -> 17.916667 | H22: =H14-H19-H21 -> 17.916667 | I22: =I14-I19-I21 -> 17.916667 | J22: =J14-J19-J21 -> 17.916667 | K22: =K14-K19-K21 -> 17.916667 | L22: =L14-L19-L21 -> 17.916667 | ... BL22: =BL14-BL19-BL21 -> 15.237526
C24: Tangible depreciation | E24: =Assumptions!E183/12 -> 1.8333333 | F24: =Assumptions!E183/12 -> 1.8333333 | G24: =Assumptions!E183/12 -> 1.8333333 | H24: =Assumptions!E183/12 -> 1.8333333 | I24: =Assumptions!E183/12 -> 1.8333333 | J24: =Assumptions!E183/12 -> 1.8333333 | K24: =Assumptions!E183/12 -> 1.8333333 | L24: =Assumptions!E183/12 -> 1.8333333 | M24: =Assumptions!E183/12 -> 1.8333333 | N24: =Assumptions!E183/12 -> 1.8333333 | O24: =Assumptions!E183/12 -> 1.8333333 | P24: =Assumptions!E183/12 -> 1.8333333 | Q24: =Assumptions!F183/12 -> 1.8333333 | R24: =Assumptions!F183/12 -> 1.8333333 | S24: =Assumptions!F183/12 -> 1.8333333 | T24: =Assumptions!F183/12 -> 1.8333333 | U24: =Assumptions!F183/12 -> 1.8333333 | V24: =Assumptions!F183/12 -> 1.8333333 | W24: =Assumptions!F183/12 -> 1.8333333 | X24: =Assumptions!F183/12 -> 1.8333333 | Y24: =Assumptions!F183/12 -> 1.8333333 | Z24: =Assumptions!F183/12 -> 1.8333333 | AA24: =Assumptions!F183/12 -> 1.8333333 | AB24: =Assumptions!F183/12 -> 1.8333333 | AC24: =Assumptions!G183/12 -> 1.8333333 | AD24: =Assumptions!G183/12 -> 1.8333333 | AE24: =Assumptions!G183/12 -> 1.8333333 | AF24: =Assumptions!G183/12 -> 1.8333333 | AG24: =Assumptions!G183/12 -> 1.8333333 | AH24: =Assumptions!G183/12 -> 1.8333333 | AI24: =Assumptions!G183/12 -> 1.8333333 | AJ24: =Assumptions!G183/12 -> 1.8333333 | AK24: =Assumptions!G183/12 -> 1.8333333 | AL24: =Assumptions!G183/12 -> 1.8333333 | AM24: =Assumptions!G183/12 -> 1.8333333 | AN24: =Assumptions!G183/12 -> 1.8333333 | AO24: =Assumptions!H183/12 -> 1.8333333 | AP24: =Assumptions!H183/12 -> 1.8333333 | AQ24: =Assumptions!H183/12 -> 1.8333333 | AR24: =Assumptions!H183/12 -> 1.8333333 | AS24: =Assumptions!H183/12 -> 1.8333333 | AT24: =Assumptions!H183/12 -> 1.8333333 | AU24: =Assumptions!H183/12 -> 1.8333333 | AV24: =Assumptions!H183/12 -> 1.8333333 | AW24: =Assumptions!H183/12 -> 1.8333333 | AX24: =Assumptions!H183/12 -> 1.8333333 | AY24: =Assumptions!H183/12 -> 1.8333333 | AZ24: =Assumptions!H183/12 -> 1.8333333 | BA24: =Assumptions!I183/12 -> 1.8333333 | BB24: =Assumptions!I183/12 -> 1.8333333 | BC24: =Assumptions!I183/12 -> 1.8333333 | BD24: =Assumptions!I183/12 -> 1.8333333 | BE24: =Assumptions!I183/12 -> 1.8333333 | BF24: =Assumptions!I183/12 -> 1.8333333 | BG24: =Assumptions!I183/12 -> 1.8333333 | BH24: =Assumptions!I183/12 -> 1.8333333 | BI24: =Assumptions!I183/12 -> 1.8333333 | BJ24: =Assumptions!I183/12 -> 1.8333333 | BK24: =Assumptions!I183/12 -> 1.8333333 | BL24: =Assumptions!I183/12 -> 1.8333333
C25: Other amortisation | E25: =Assumptions!E188/12 -> 0.28333333 | F25: =Assumptions!E188/12 -> 0.28333333 | G25: =Assumptions!E188/12 -> 0.28333333 | H25: =Assumptions!E188/12 -> 0.28333333 | I25: =Assumptions!E188/12 -> 0.28333333 | J25: =Assumptions!E188/12 -> 0.28333333 | K25: =Assumptions!E188/12 -> 0.28333333 | L25: =Assumptions!E188/12 -> 0.28333333 | M25: =Assumptions!E188/12 -> 0.28333333 | N25: =Assumptions!E188/12 -> 0.28333333 | O25: =Assumptions!E188/12 -> 0.28333333 | P25: =Assumptions!E188/12 -> 0.28333333 | Q25: =Assumptions!F188/12 -> 0.28333333 | R25: =Assumptions!F188/12 -> 0.28333333 | S25: =Assumptions!F188/12 -> 0.28333333 | T25: =Assumptions!F188/12 -> 0.28333333 | U25: =Assumptions!F188/12 -> 0.28333333 | V25: =Assumptions!F188/12 -> 0.28333333 | W25: =Assumptions!F188/12 -> 0.28333333 | X25: =Assumptions!F188/12 -> 0.28333333 | Y25: =Assumptions!F188/12 -> 0.28333333 | Z25: =Assumptions!F188/12 -> 0.28333333 | AA25: =Assumptions!F188/12 -> 0.28333333 | AB25: =Assumptions!F188/12 -> 0.28333333 | AC25: =Assumptions!G188/12 -> 0.28333333 | AD25: =Assumptions!G188/12 -> 0.28333333 | AE25: =Assumptions!G188/12 -> 0.28333333 | AF25: =Assumptions!G188/12 -> 0.28333333 | AG25: =Assumptions!G188/12 -> 0.28333333 | AH25: =Assumptions!G188/12 -> 0.28333333 | AI25: =Assumptions!G188/12 -> 0.28333333 | AJ25: =Assumptions!G188/12 -> 0.28333333 | AK25: =Assumptions!G188/12 -> 0.28333333 | AL25: =Assumptions!G188/12 -> 0.28333333 | AM25: =Assumptions!G188/12 -> 0.28333333 | AN25: =Assumptions!G188/12 -> 0.28333333 | AO25: =Assumptions!H188/12 -> 0.28333333 | AP25: =Assumptions!H188/12 -> 0.28333333 | AQ25: =Assumptions!H188/12 -> 0.28333333 | AR25: =Assumptions!H188/12 -> 0.28333333 | AS25: =Assumptions!H188/12 -> 0.28333333 | AT25: =Assumptions!H188/12 -> 0.28333333 | AU25: =Assumptions!H188/12 -> 0.28333333 | AV25: =Assumptions!H188/12 -> 0.28333333 | AW25: =Assumptions!H188/12 -> 0.28333333 | AX25: =Assumptions!H188/12 -> 0.28333333 | AY25: =Assumptions!H188/12 -> 0.28333333 | AZ25: =Assumptions!H188/12 -> 0.28333333 | BA25: =Assumptions!I188/12 -> 0.28333333 | BB25: =Assumptions!I188/12 -> 0.28333333 | BC25: =Assumptions!I188/12 -> 0.28333333 | BD25: =Assumptions!I188/12 -> 0.28333333 | BE25: =Assumptions!I188/12 -> 0.28333333 | BF25: =Assumptions!I188/12 -> 0.28333333 | BG25: =Assumptions!I188/12 -> 0.28333333 | BH25: =Assumptions!I188/12 -> 0.28333333 | BI25: =Assumptions!I188/12 -> 0.28333333 | BJ25: =Assumptions!I188/12 -> 0.28333333 | BK25: =Assumptions!I188/12 -> 0.28333333 | BL25: =Assumptions!I188/12 -> 0.28333333
C26: Ordinary tangible capex | E26: =Assumptions!E178/12 -> 2.0833333 | F26: =Assumptions!E178/12 -> 2.0833333 | G26: =Assumptions!E178/12 -> 2.0833333 | H26: =Assumptions!E178/12 -> 2.0833333 | I26: =Assumptions!E178/12 -> 2.0833333 | J26: =Assumptions!E178/12 -> 2.0833333 | K26: =Assumptions!E178/12 -> 2.0833333 | L26: =Assumptions!E178/12 -> 2.0833333 | M26: =Assumptions!E178/12 -> 2.0833333 | N26: =Assumptions!E178/12 -> 2.0833333 | O26: =Assumptions!E178/12 -> 2.0833333 | P26: =Assumptions!E178/12 -> 2.0833333 | Q26: =Assumptions!F178/12 -> 2.0833333 | R26: =Assumptions!F178/12 -> 2.0833333 | S26: =Assumptions!F178/12 -> 2.0833333 | T26: =Assumptions!F178/12 -> 2.0833333 | U26: =Assumptions!F178/12 -> 2.0833333 | V26: =Assumptions!F178/12 -> 2.0833333 | W26: =Assumptions!F178/12 -> 2.0833333 | X26: =Assumptions!F178/12 -> 2.0833333 | Y26: =Assumptions!F178/12 -> 2.0833333 | Z26: =Assumptions!F178/12 -> 2.0833333 | AA26: =Assumptions!F178/12 -> 2.0833333 | AB26: =Assumptions!F178/12 -> 2.0833333 | AC26: =Assumptions!G178/12 -> 2.0833333 | AD26: =Assumptions!G178/12 -> 2.0833333 | AE26: =Assumptions!G178/12 -> 2.0833333 | AF26: =Assumptions!G178/12 -> 2.0833333 | AG26: =Assumptions!G178/12 -> 2.0833333 | AH26: =Assumptions!G178/12 -> 2.0833333 | AI26: =Assumptions!G178/12 -> 2.0833333 | AJ26: =Assumptions!G178/12 -> 2.0833333 | AK26: =Assumptions!G178/12 -> 2.0833333 | AL26: =Assumptions!G178/12 -> 2.0833333 | AM26: =Assumptions!G178/12 -> 2.0833333 | AN26: =Assumptions!G178/12 -> 2.0833333 | AO26: =Assumptions!H178/12 -> 2.0833333 | AP26: =Assumptions!H178/12 -> 2.0833333 | AQ26: =Assumptions!H178/12 -> 2.0833333 | AR26: =Assumptions!H178/12 -> 2.0833333 | AS26: =Assumptions!H178/12 -> 2.0833333 | AT26: =Assumptions!H178/12 -> 2.0833333 | AU26: =Assumptions!H178/12 -> 2.0833333 | AV26: =Assumptions!H178/12 -> 2.0833333 | AW26: =Assumptions!H178/12 -> 2.0833333 | AX26: =Assumptions!H178/12 -> 2.0833333 | AY26: =Assumptions!H178/12 -> 2.0833333 | AZ26: =Assumptions!H178/12 -> 2.0833333 | BA26: =Assumptions!I178/12 -> 2.0833333 | BB26: =Assumptions!I178/12 -> 2.0833333 | BC26: =Assumptions!I178/12 -> 2.0833333 | BD26: =Assumptions!I178/12 -> 2.0833333 | BE26: =Assumptions!I178/12 -> 2.0833333 | BF26: =Assumptions!I178/12 -> 2.0833333 | BG26: =Assumptions!I178/12 -> 2.0833333 | BH26: =Assumptions!I178/12 -> 2.0833333 | BI26: =Assumptions!I178/12 -> 2.0833333 | BJ26: =Assumptions!I178/12 -> 2.0833333 | BK26: =Assumptions!I178/12 -> 2.0833333 | BL26: =Assumptions!I178/12 -> 2.0833333
C27: Other intangible cash capex | E27: =Assumptions!E193/12 -> 0.28333333 | F27: =Assumptions!E193/12 -> 0.28333333 | G27: =Assumptions!E193/12 -> 0.28333333 | H27: =Assumptions!E193/12 -> 0.28333333 | I27: =Assumptions!E193/12 -> 0.28333333 | J27: =Assumptions!E193/12 -> 0.28333333 | K27: =Assumptions!E193/12 -> 0.28333333 | L27: =Assumptions!E193/12 -> 0.28333333 | M27: =Assumptions!E193/12 -> 0.28333333 | N27: =Assumptions!E193/12 -> 0.28333333 | O27: =Assumptions!E193/12 -> 0.28333333 | P27: =Assumptions!E193/12 -> 0.28333333 | Q27: =Assumptions!F193/12 -> 0.28333333 | R27: =Assumptions!F193/12 -> 0.28333333 | S27: =Assumptions!F193/12 -> 0.28333333 | T27: =Assumptions!F193/12 -> 0.28333333 | U27: =Assumptions!F193/12 -> 0.28333333 | V27: =Assumptions!F193/12 -> 0.28333333 | W27: =Assumptions!F193/12 -> 0.28333333 | X27: =Assumptions!F193/12 -> 0.28333333 | Y27: =Assumptions!F193/12 -> 0.28333333 | Z27: =Assumptions!F193/12 -> 0.28333333 | AA27: =Assumptions!F193/12 -> 0.28333333 | AB27: =Assumptions!F193/12 -> 0.28333333 | AC27: =Assumptions!G193/12 -> 0.28333333 | AD27: =Assumptions!G193/12 -> 0.28333333 | AE27: =Assumptions!G193/12 -> 0.28333333 | AF27: =Assumptions!G193/12 -> 0.28333333 | AG27: =Assumptions!G193/12 -> 0.28333333 | AH27: =Assumptions!G193/12 -> 0.28333333 | AI27: =Assumptions!G193/12 -> 0.28333333 | AJ27: =Assumptions!G193/12 -> 0.28333333 | AK27: =Assumptions!G193/12 -> 0.28333333 | AL27: =Assumptions!G193/12 -> 0.28333333 | AM27: =Assumptions!G193/12 -> 0.28333333 | AN27: =Assumptions!G193/12 -> 0.28333333 | AO27: =Assumptions!H193/12 -> 0.28333333 | AP27: =Assumptions!H193/12 -> 0.28333333 | AQ27: =Assumptions!H193/12 -> 0.28333333 | AR27: =Assumptions!H193/12 -> 0.28333333 | AS27: =Assumptions!H193/12 -> 0.28333333 | AT27: =Assumptions!H193/12 -> 0.28333333 | AU27: =Assumptions!H193/12 -> 0.28333333 | AV27: =Assumptions!H193/12 -> 0.28333333 | AW27: =Assumptions!H193/12 -> 0.28333333 | AX27: =Assumptions!H193/12 -> 0.28333333 | AY27: =Assumptions!H193/12 -> 0.28333333 | AZ27: =Assumptions!H193/12 -> 0.28333333 | BA27: =Assumptions!I193/12 -> 0.28333333 | BB27: =Assumptions!I193/12 -> 0.28333333 | BC27: =Assumptions!I193/12 -> 0.28333333 | BD27: =Assumptions!I193/12 -> 0.28333333 | BE27: =Assumptions!I193/12 -> 0.28333333 | BF27: =Assumptions!I193/12 -> 0.28333333 | BG27: =Assumptions!I193/12 -> 0.28333333 | BH27: =Assumptions!I193/12 -> 0.28333333 | BI27: =Assumptions!I193/12 -> 0.28333333 | BJ27: =Assumptions!I193/12 -> 0.28333333 | BK27: =Assumptions!I193/12 -> 0.28333333 | BL27: =Assumptions!I193/12 -> 0.28333333
C28: Minimum tax charge / cash tax | E28: =Assumptions!E228/12 -> 0.083333333 | F28: =Assumptions!E228/12 -> 0.083333333 | G28: =Assumptions!E228/12 -> 0.083333333 | H28: =Assumptions!E228/12 -> 0.083333333 | I28: =Assumptions!E228/12 -> 0.083333333 | J28: =Assumptions!E228/12 -> 0.083333333 | K28: =Assumptions!E228/12 -> 0.083333333 | L28: =Assumptions!E228/12 -> 0.083333333 | M28: =Assumptions!E228/12 -> 0.083333333 | N28: =Assumptions!E228/12 -> 0.083333333 | O28: =Assumptions!E228/12 -> 0.083333333 | P28: =Assumptions!E228/12 -> 0.083333333 | Q28: =Assumptions!F228/12 -> 0.083333333 | R28: =Assumptions!F228/12 -> 0.083333333 | S28: =Assumptions!F228/12 -> 0.083333333 | T28: =Assumptions!F228/12 -> 0.083333333 | U28: =Assumptions!F228/12 -> 0.083333333 | V28: =Assumptions!F228/12 -> 0.083333333 | W28: =Assumptions!F228/12 -> 0.083333333 | X28: =Assumptions!F228/12 -> 0.083333333 | Y28: =Assumptions!F228/12 -> 0.083333333 | Z28: =Assumptions!F228/12 -> 0.083333333 | AA28: =Assumptions!F228/12 -> 0.083333333 | AB28: =Assumptions!F228/12 -> 0.083333333 | AC28: =Assumptions!G228/12 -> 0.083333333 | AD28: =Assumptions!G228/12 -> 0.083333333 | AE28: =Assumptions!G228/12 -> 0.083333333 | AF28: =Assumptions!G228/12 -> 0.083333333 | AG28: =Assumptions!G228/12 -> 0.083333333 | AH28: =Assumptions!G228/12 -> 0.083333333 | AI28: =Assumptions!G228/12 -> 0.083333333 | AJ28: =Assumptions!G228/12 -> 0.083333333 | AK28: =Assumptions!G228/12 -> 0.083333333 | AL28: =Assumptions!G228/12 -> 0.083333333 | AM28: =Assumptions!G228/12 -> 0.083333333 | AN28: =Assumptions!G228/12 -> 0.083333333 | AO28: =Assumptions!H228/12 -> 0.083333333 | AP28: =Assumptions!H228/12 -> 0.083333333 | AQ28: =Assumptions!H228/12 -> 0.083333333 | AR28: =Assumptions!H228/12 -> 0.083333333 | AS28: =Assumptions!H228/12 -> 0.083333333 | AT28: =Assumptions!H228/12 -> 0.083333333 | AU28: =Assumptions!H228/12 -> 0.083333333 | AV28: =Assumptions!H228/12 -> 0.083333333 | AW28: =Assumptions!H228/12 -> 0.083333333 | AX28: =Assumptions!H228/12 -> 0.083333333 | AY28: =Assumptions!H228/12 -> 0.083333333 | AZ28: =Assumptions!H228/12 -> 0.083333333 | BA28: =Assumptions!I228/12 -> 0.083333333 | BB28: =Assumptions!I228/12 -> 0.083333333 | BC28: =Assumptions!I228/12 -> 0.083333333 | BD28: =Assumptions!I228/12 -> 0.083333333 | BE28: =Assumptions!I228/12 -> 0.083333333 | BF28: =Assumptions!I228/12 -> 0.083333333 | BG28: =Assumptions!I228/12 -> 0.083333333 | BH28: =Assumptions!I228/12 -> 0.083333333 | BI28: =Assumptions!I228/12 -> 0.083333333 | BJ28: =Assumptions!I228/12 -> 0.083333333 | BK28: =Assumptions!I228/12 -> 0.083333333 | BL28: =Assumptions!I228/12 -> 0.083333333
C29: Other operating WC investment | E29: =Assumptions!E233/12 -> 0 | F29: =Assumptions!E233/12 -> 0 | G29: =Assumptions!E233/12 -> 0 | H29: =Assumptions!E233/12 -> 0 | I29: =Assumptions!E233/12 -> 0 | J29: =Assumptions!E233/12 -> 0 | K29: =Assumptions!E233/12 -> 0 | L29: =Assumptions!E233/12 -> 0 | M29: =Assumptions!E233/12 -> 0 | N29: =Assumptions!E233/12 -> 0 | O29: =Assumptions!E233/12 -> 0 | P29: =Assumptions!E233/12 -> 0 | Q29: =Assumptions!F233/12 -> 0 | R29: =Assumptions!F233/12 -> 0 | S29: =Assumptions!F233/12 -> 0 | T29: =Assumptions!F233/12 -> 0 | U29: =Assumptions!F233/12 -> 0 | V29: =Assumptions!F233/12 -> 0 | W29: =Assumptions!F233/12 -> 0 | X29: =Assumptions!F233/12 -> 0 | Y29: =Assumptions!F233/12 -> 0 | Z29: =Assumptions!F233/12 -> 0 | AA29: =Assumptions!F233/12 -> 0 | AB29: =Assumptions!F233/12 -> 0 | AC29: =Assumptions!G233/12 -> 0 | AD29: =Assumptions!G233/12 -> 0 | AE29: =Assumptions!G233/12 -> 0 | AF29: =Assumptions!G233/12 -> 0 | AG29: =Assumptions!G233/12 -> 0 | AH29: =Assumptions!G233/12 -> 0 | AI29: =Assumptions!G233/12 -> 0 | AJ29: =Assumptions!G233/12 -> 0 | AK29: =Assumptions!G233/12 -> 0 | AL29: =Assumptions!G233/12 -> 0 | AM29: =Assumptions!G233/12 -> 0 | AN29: =Assumptions!G233/12 -> 0 | AO29: =Assumptions!H233/12 -> 0 | AP29: =Assumptions!H233/12 -> 0 | AQ29: =Assumptions!H233/12 -> 0 | AR29: =Assumptions!H233/12 -> 0 | AS29: =Assumptions!H233/12 -> 0 | AT29: =Assumptions!H233/12 -> 0 | AU29: =Assumptions!H233/12 -> 0 | AV29: =Assumptions!H233/12 -> 0 | AW29: =Assumptions!H233/12 -> 0 | AX29: =Assumptions!H233/12 -> 0 | AY29: =Assumptions!H233/12 -> 0 | AZ29: =Assumptions!H233/12 -> 0 | BA29: =Assumptions!I233/12 -> 0 | BB29: =Assumptions!I233/12 -> 0 | BC29: =Assumptions!I233/12 -> 0 | BD29: =Assumptions!I233/12 -> 0 | BE29: =Assumptions!I233/12 -> 0 | BF29: =Assumptions!I233/12 -> 0 | BG29: =Assumptions!I233/12 -> 0 | BH29: =Assumptions!I233/12 -> 0 | BI29: =Assumptions!I233/12 -> 0 | BJ29: =Assumptions!I233/12 -> 0 | BK29: =Assumptions!I233/12 -> 0 | BL29: =Assumptions!I233/12 -> 0
C30: Adidas cash versus revenue adjustment | E30: =Assumptions!E33/12-E9 -> 0 | F30: =Assumptions!E33/12-F9 -> 0 | G30: =Assumptions!E33/12-G9 -> 0 | H30: =Assumptions!E33/12-H9 -> 0 | I30: =Assumptions!E33/12-I9 -> 0 | J30: =Assumptions!E33/12-J9 -> 0 | K30: =Assumptions!E33/12-K9 -> 0 | L30: =Assumptions!E33/12-L9 -> 0 | M30: =Assumptions!E33/12-M9 -> 0 | N30: =Assumptions!E33/12-N9 -> 0 | O30: =Assumptions!E33/12-O9 -> 0 | P30: =Assumptions!E33/12-P9 -> 0 | Q30: =Assumptions!F33/12-Q9 -> 0.76666667 | R30: =Assumptions!F33/12-R9 -> 0.76666667 | S30: =Assumptions!F33/12-S9 -> 0.76666667 | T30: =Assumptions!F33/12-T9 -> 0.76666667 | U30: =Assumptions!F33/12-U9 -> 0.76666667 | V30: =Assumptions!F33/12-V9 -> 0.76666667 | W30: =Assumptions!F33/12-W9 -> 0.76666667 | X30: =Assumptions!F33/12-X9 -> 0.76666667 | Y30: =Assumptions!F33/12-Y9 -> 0.76666667 | Z30: =Assumptions!F33/12-Z9 -> 0.76666667 | AA30: =Assumptions!F33/12-AA9 -> 0.76666667 | AB30: =Assumptions!F33/12-AB9 -> 0.76666667 | AC30: =Assumptions!G33/12-AC9 -> -0.066666667 | AD30: =Assumptions!G33/12-AD9 -> -0.066666667 | AE30: =Assumptions!G33/12-AE9 -> -0.066666667 | AF30: =Assumptions!G33/12-AF9 -> -0.066666667 | AG30: =Assumptions!G33/12-AG9 -> -0.066666667 | AH30: =Assumptions!G33/12-AH9 -> -0.066666667 | AI30: =Assumptions!G33/12-AI9 -> -0.066666667 | AJ30: =Assumptions!G33/12-AJ9 -> -0.066666667 | AK30: =Assumptions!G33/12-AK9 -> -0.066666667 | AL30: =Assumptions!G33/12-AL9 -> -0.066666667 | AM30: =Assumptions!G33/12-AM9 -> -0.066666667 | AN30: =Assumptions!G33/12-AN9 -> -0.066666667 | AO30: =Assumptions!H33/12-AO9 -> -0.066666667 | AP30: =Assumptions!H33/12-AP9 -> -0.066666667 | AQ30: =Assumptions!H33/12-AQ9 -> -0.066666667 | AR30: =Assumptions!H33/12-AR9 -> -0.066666667 | AS30: =Assumptions!H33/12-AS9 -> -0.066666667 | AT30: =Assumptions!H33/12-AT9 -> -0.066666667 | AU30: =Assumptions!H33/12-AU9 -> -0.066666667 | AV30: =Assumptions!H33/12-AV9 -> -0.066666667 | AW30: =Assumptions!H33/12-AW9 -> -0.066666667 | AX30: =Assumptions!H33/12-AX9 -> -0.066666667 | AY30: =Assumptions!H33/12-AY9 -> -0.066666667 | AZ30: =Assumptions!H33/12-AZ9 -> -0.066666667 | BA30: =Assumptions!I33/12-BA9 -> -0.066666667 | BB30: =Assumptions!I33/12-BB9 -> -0.066666667 | BC30: =Assumptions!I33/12-BC9 -> -0.066666667 | BD30: =Assumptions!I33/12-BD9 -> -0.066666667 | BE30: =Assumptions!I33/12-BE9 -> -0.066666667 | BF30: =Assumptions!I33/12-BF9 -> -0.066666667 | BG30: =Assumptions!I33/12-BG9 -> -0.066666667 | BH30: =Assumptions!I33/12-BH9 -> -0.066666667 | BI30: =Assumptions!I33/12-BI9 -> -0.066666667 | BJ30: =Assumptions!I33/12-BJ9 -> -0.066666667 | BK30: =Assumptions!I33/12-BK9 -> -0.066666667 | BL30: =Assumptions!I33/12-BL9 -> -0.066666667

Sheet Registrations
C2: Registrations
C3: £m unless stated. Evidence cut-off: 8 October 2026.
C4: Case selected | E4: =CHOOSE(Assumptions!$E$5,"Base","Downside","Upside") -> Base
C7: Month | E7: 46204 | F7: 46235 | G7: 46266 | H7: 46296 | I7: 46327 | J7: 46357 | K7: 46388 | L7: 46419 | M7: 46447 | N7: 46478 | O7: 46508 | P7: 46539 | Q7: 46569 | R7: 46600 | S7: 46631 | T7: 46661 | U7: 46692 | V7: 46722 | W7: 46753 | X7: 46784 | Y7: 46813 | Z7: 46844 | AA7: 46874 | AB7: 46905 | AC7: 46935 | AD7: 46966 | AE7: 46997 | AF7: 47027 | AG7: 47058 | AH7: 47088 | AI7: 47119 | AJ7: 47150 | AK7: 47178 | AL7: 47209 | AM7: 47239 | AN7: 47270 | AO7: 47300 | AP7: 47331 | AQ7: 47362 | AR7: 47392 | AS7: 47423 | AT7: 47453 | AU7: 47484 | AV7: 47515 | AW7: 47543 | AX7: 47574 | AY7: 47604 | AZ7: 47635 | BA7: 47665 | BB7: 47696 | BC7: 47727 | BD7: 47757 | BE7: 47788 | BF7: 47818 | BG7: 47849 | BH7: 47880 | BI7: 47908 | BJ7: 47939 | BK7: 47969 | BL7: 48000
C8: Opening remaining life 1 years
C9: Opening NBV | E9: =(1)*(Assumptions!E143-Assumptions!F143) -> 31.1 | F9: =E14 -> 28.508333 | G9: =F14 -> 25.387476 | H9: =G14 -> 22.821603 | I9: =H14 -> 20.285869 | J9: =I14 -> 17.750136 | K9: =J14 -> 15.214402 | L9: =K14 -> 12.678668 | M9: =L14 -> 10.142935 | ... BL9: =BK14 -> 0
C10: Additions | E10: =0 -> 0 | F10: =0 -> 0 | G10: =0 -> 0 | H10: =0 -> 0 | I10: =0 -> 0 | J10: =0 -> 0 | K10: =0 -> 0 | L10: =0 -> 0 | ... BL10: =0 -> 0
C11: Amortisation | E11: =IF(0<0,0,IF(12-(0-0)>0,MIN(E9+E10,(E9+E10)/MAX(1,12-(0-0))),E9+E10)) -> 2.5916667 | F11: =IF(1<0,0,IF(12-(1-0)>0,MIN(F9+F10,(F9+F10)/MAX(1,12-(1-0))),F9+F10)) -> 2.5916667 | G11: =IF(2<0,0,IF(12-(2-0)>0,MIN(G9+G10,(G9+G10)/MAX(1,12-(2-0))),G9+G10)) -> 2.5387476 | H11: =IF(3<0,0,IF(12-(3-0)>0,MIN(H9+H10,(H9+H10)/MAX(1,12-(3-0))),H9+H10)) -> 2.5357336 | I11: =IF(4<0,0,IF(12-(4-0)>0,MIN(I9+I10,(I9+I10)/MAX(1,12-(4-0))),I9+I10)) -> 2.5357336 | J11: =IF(5<0,0,IF(12-(5-0)>0,MIN(J9+J10,(J9+J10)/MAX(1,12-(5-0))),J9+J10)) -> 2.5357336 | K11: =IF(6<0,0,IF(12-(6-0)>0,MIN(K9+K10,(K9+K10)/MAX(1,12-(6-0))),K9+K10)) -> 2.5357336 | L11: =IF(7<0,0,IF(12-(7-0)>0,MIN(L9+L10,(L9+L10)/MAX(1,12-(7-0))),L9+L10)) -> 2.5357336 | M11: =IF(8<0,0,IF(12-(8-0)>0,MIN(M9+M10,(M9+M10)/MAX(1,12-(8-0))),M9+M10)) -> 2.5357336 | N11: =IF(9<0,0,IF(12-(9-0)>0,MIN(N9+N10,(N9+N10)/MAX(1,12-(9-0))),N9+N10)) -> 2.5357336 | O11: =IF(10<0,0,IF(12-(10-0)>0,MIN(O9+O10,(O9+O10)/MAX(1,12-(10-0))),O9+O10)) -> 2.5357336 | P11: =IF(11<0,0,IF(12-(11-0)>0,MIN(P9+P10,(P9+P10)/MAX(1,12-(11-0))),P9+P10)) -> 2.5357336 | Q11: =IF(12<0,0,IF(12-(12-0)>0,MIN(Q9+Q10,(Q9+Q10)/MAX(1,12-(12-0))),Q9+Q10)) -> 0 | R11: =IF(13<0,0,IF(12-(13-0)>0,MIN(R9+R10,(R9+R10)/MAX(1,12-(13-0))),R9+R10)) -> 0 | S11: =IF(14<0,0,IF(12-(14-0)>0,MIN(S9+S10,(S9+S10)/MAX(1,12-(14-0))),S9+S10)) -> 0 | T11: =IF(15<0,0,IF(12-(15-0)>0,MIN(T9+T10,(T9+T10)/MAX(1,12-(15-0))),T9+T10)) -> 0 | U11: =IF(16<0,0,IF(12-(16-0)>0,MIN(U9+U10,(U9+U10)/MAX(1,12-(16-0))),U9+U10)) -> 0 | V11: =IF(17<0,0,IF(12-(17-0)>0,MIN(V9+V10,(V9+V10)/MAX(1,12-(17-0))),V9+V10)) -> 0 | W11: =IF(18<0,0,IF(12-(18-0)>0,MIN(W9+W10,(W9+W10)/MAX(1,12-(18-0))),W9+W10)) -> 0 | X11: =IF(19<0,0,IF(12-(19-0)>0,MIN(X9+X10,(X9+X10)/MAX(1,12-(19-0))),X9+X10)) -> 0 | Y11: =IF(20<0,0,IF(12-(20-0)>0,MIN(Y9+Y10,(Y9+Y10)/MAX(1,12-(20-0))),Y9+Y10)) -> 0 | Z11: =IF(21<0,0,IF(12-(21-0)>0,MIN(Z9+Z10,(Z9+Z10)/MAX(1,12-(21-0))),Z9+Z10)) -> 0 | AA11: =IF(22<0,0,IF(12-(22-0)>0,MIN(AA9+AA10,(AA9+AA10)/MAX(1,12-(22-0))),AA9+AA10)) -> 0 | AB11: =IF(23<0,0,IF(12-(23-0)>0,MIN(AB9+AB10,(AB9+AB10)/MAX(1,12-(23-0))),AB9+AB10)) -> 0 | AC11: =IF(24<0,0,IF(12-(24-0)>0,MIN(AC9+AC10,(AC9+AC10)/MAX(1,12-(24-0))),AC9+AC10)) -> 0 | AD11: =IF(25<0,0,IF(12-(25-0)>0,MIN(AD9+AD10,(AD9+AD10)/MAX(1,12-(25-0))),AD9+AD10)) -> 0 | AE11: =IF(26<0,0,IF(12-(26-0)>0,MIN(AE9+AE10,(AE9+AE10)/MAX(1,12-(26-0))),AE9+AE10)) -> 0 | AF11: =IF(27<0,0,IF(12-(27-0)>0,MIN(AF9+AF10,(AF9+AF10)/MAX(1,12-(27-0))),AF9+AF10)) -> 0 | AG11: =IF(28<0,0,IF(12-(28-0)>0,MIN(AG9+AG10,(AG9+AG10)/MAX(1,12-(28-0))),AG9+AG10)) -> 0 | AH11: =IF(29<0,0,IF(12-(29-0)>0,MIN(AH9+AH10,(AH9+AH10)/MAX(1,12-(29-0))),AH9+AH10)) -> 0 | AI11: =IF(30<0,0,IF(12-(30-0)>0,MIN(AI9+AI10,(AI9+AI10)/MAX(1,12-(30-0))),AI9+AI10)) -> 0 | AJ11: =IF(31<0,0,IF(12-(31-0)>0,MIN(AJ9+AJ10,(AJ9+AJ10)/MAX(1,12-(31-0))),AJ9+AJ10)) -> 0 | AK11: =IF(32<0,0,IF(12-(32-0)>0,MIN(AK9+AK10,(AK9+AK10)/MAX(1,12-(32-0))),AK9+AK10)) -> 0 | AL11: =IF(33<0,0,IF(12-(33-0)>0,MIN(AL9+AL10,(AL9+AL10)/MAX(1,12-(33-0))),AL9+AL10)) -> 0 | AM11: =IF(34<0,0,IF(12-(34-0)>0,MIN(AM9+AM10,(AM9+AM10)/MAX(1,12-(34-0))),AM9+AM10)) -> 0 | AN11: =IF(35<0,0,IF(12-(35-0)>0,MIN(AN9+AN10,(AN9+AN10)/MAX(1,12-(35-0))),AN9+AN10)) -> 0 | AO11: =IF(36<0,0,IF(12-(36-0)>0,MIN(AO9+AO10,(AO9+AO10)/MAX(1,12-(36-0))),AO9+AO10)) -> 0 | AP11: =IF(37<0,0,IF(12-(37-0)>0,MIN(AP9+AP10,(AP9+AP10)/MAX(1,12-(37-0))),AP9+AP10)) -> 0 | AQ11: =IF(38<0,0,IF(12-(38-0)>0,MIN(AQ9+AQ10,(AQ9+AQ10)/MAX(1,12-(38-0))),AQ9+AQ10)) -> 0 | AR11: =IF(39<0,0,IF(12-(39-0)>0,MIN(AR9+AR10,(AR9+AR10)/MAX(1,12-(39-0))),AR9+AR10)) -> 0 | AS11: =IF(40<0,0,IF(12-(40-0)>0,MIN(AS9+AS10,(AS9+AS10)/MAX(1,12-(40-0))),AS9+AS10)) -> 0 | AT11: =IF(41<0,0,IF(12-(41-0)>0,MIN(AT9+AT10,(AT9+AT10)/MAX(1,12-(41-0))),AT9+AT10)) -> 0 | AU11: =IF(42<0,0,IF(12-(42-0)>0,MIN(AU9+AU10,(AU9+AU10)/MAX(1,12-(42-0))),AU9+AU10)) -> 0 | AV11: =IF(43<0,0,IF(12-(43-0)>0,MIN(AV9+AV10,(AV9+AV10)/MAX(1,12-(43-0))),AV9+AV10)) -> 0 | AW11: =IF(44<0,0,IF(12-(44-0)>0,MIN(AW9+AW10,(AW9+AW10)/MAX(1,12-(44-0))),AW9+AW10)) -> 0 | AX11: =IF(45<0,0,IF(12-(45-0)>0,MIN(AX9+AX10,(AX9+AX10)/MAX(1,12-(45-0))),AX9+AX10)) -> 0 | AY11: =IF(46<0,0,IF(12-(46-0)>0,MIN(AY9+AY10,(AY9+AY10)/MAX(1,12-(46-0))),AY9+AY10)) -> 0 | AZ11: =IF(47<0,0,IF(12-(47-0)>0,MIN(AZ9+AZ10,(AZ9+AZ10)/MAX(1,12-(47-0))),AZ9+AZ10)) -> 0 | BA11: =IF(48<0,0,IF(12-(48-0)>0,MIN(BA9+BA10,(BA9+BA10)/MAX(1,12-(48-0))),BA9+BA10)) -> 0 | BB11: =IF(49<0,0,IF(12-(49-0)>0,MIN(BB9+BB10,(BB9+BB10)/MAX(1,12-(49-0))),BB9+BB10)) -> 0 | BC11: =IF(50<0,0,IF(12-(50-0)>0,MIN(BC9+BC10,(BC9+BC10)/MAX(1,12-(50-0))),BC9+BC10)) -> 0 | BD11: =IF(51<0,0,IF(12-(51-0)>0,MIN(BD9+BD10,(BD9+BD10)/MAX(1,12-(51-0))),BD9+BD10)) -> 0 | BE11: =IF(52<0,0,IF(12-(52-0)>0,MIN(BE9+BE10,(BE9+BE10)/MAX(1,12-(52-0))),BE9+BE10)) -> 0 | BF11: =IF(53<0,0,IF(12-(53-0)>0,MIN(BF9+BF10,(BF9+BF10)/MAX(1,12-(53-0))),BF9+BF10)) -> 0 | BG11: =IF(54<0,0,IF(12-(54-0)>0,MIN(BG9+BG10,(BG9+BG10)/MAX(1,12-(54-0))),BG9+BG10)) -> 0 | BH11: =IF(55<0,0,IF(12-(55-0)>0,MIN(BH9+BH10,(BH9+BH10)/MAX(1,12-(55-0))),BH9+BH10)) -> 0 | BI11: =IF(56<0,0,IF(12-(56-0)>0,MIN(BI9+BI10,(BI9+BI10)/MAX(1,12-(56-0))),BI9+BI10)) -> 0 | BJ11: =IF(57<0,0,IF(12-(57-0)>0,MIN(BJ9+BJ10,(BJ9+BJ10)/MAX(1,12-(57-0))),BJ9+BJ10)) -> 0 | BK11: =IF(58<0,0,IF(12-(58-0)>0,MIN(BK9+BK10,(BK9+BK10)/MAX(1,12-(58-0))),BK9+BK10)) -> 0 | BL11: =IF(59<0,0,IF(12-(59-0)>0,MIN(BL9+BL10,(BL9+BL10)/MAX(1,12-(59-0))),BL9+BL10)) -> 0
C12: Pre-sale NBV | E12: =E9+E10-E11 -> 28.508333 | F12: =F9+F10-F11 -> 25.916667 | G12: =G9+G10-G11 -> 22.848729 | H12: =H9+H10-H11 -> 20.285869 | I12: =I9+I10-I11 -> 17.750136 | J12: =J9+J10-J11 -> 15.214402 | K12: =K9+K10-K11 -> 12.678668 | L12: =L9+L10-L11 -> 10.142935 | ... BL12: =BL9+BL10-BL11 -> 0
C13: Allocated disposal NBV | E13: =IF(E91>0,E12/E91*Transfers!E24,0) -> 0 | F13: =IF(F91>0,F12/F91*Transfers!F24,0) -> 0.52919033 | G13: =IF(G91>0,G12/G91*Transfers!G24,0) -> 0.0271259 | H13: =IF(H91>0,H12/H91*Transfers!H24,0) -> 0 | I13: =IF(I91>0,I12/I91*Transfers!I24,0) -> 0 | J13: =IF(J91>0,J12/J91*Transfers!J24,0) -> 0 | K13: =IF(K91>0,K12/K91*Transfers!K24,0) -> 0 | L13: =IF(L91>0,L12/L91*Transfers!L24,0) -> 0 | ... BL13: =IF(BL91>0,BL12/BL91*Transfers!BL24,0) -> 0
C14: Closing NBV | E14: =E12-E13 -> 28.508333 | F14: =F12-F13 -> 25.387476 | G14: =G12-G13 -> 22.821603 | H14: =H12-H13 -> 20.285869 | I14: =I12-I13 -> 17.750136 | J14: =J12-J13 -> 15.214402 | K14: =K12-K13 -> 12.678668 | L14: =L12-L13 -> 10.142935 | ... BL14: =BL12-BL13 -> 0
C15: Opening remaining life 2 years
C16: Opening NBV | E16: =(2)*(Assumptions!F143-Assumptions!G143) -> 70 | F16: =E21 -> 67.083333 | G16: =F21 -> 62.856453 | H16: =G21 -> 59.92811 | I16: =H21 -> 57.074391 | J16: =I21 -> 54.220671 | K16: =J21 -> 51.366952 | L16: =K21 -> 48.513232 | M16: =L21 -> 45.659513 | ... BL16: =BK21 -> 0
C17: Additions | E17: =0 -> 0 | F17: =0 -> 0 | G17: =0 -> 0 | H17: =0 -> 0 | I17: =0 -> 0 | J17: =0 -> 0 | K17: =0 -> 0 | L17: =0 -> 0 | ... BL17: =0 -> 0
C18: Amortisation | E18: =IF(0<0,0,IF(24-(0-0)>0,MIN(E16+E17,(E16+E17)/MAX(1,24-(0-0))),E16+E17)) -> 2.9166667 | F18: =IF(1<0,0,IF(24-(1-0)>0,MIN(F16+F17,(F16+F17)/MAX(1,24-(1-0))),F16+F17)) -> 2.9166667 | G18: =IF(2<0,0,IF(24-(2-0)>0,MIN(G16+G17,(G16+G17)/MAX(1,24-(2-0))),G16+G17)) -> 2.8571115 | H18: =IF(3<0,0,IF(24-(3-0)>0,MIN(H16+H17,(H16+H17)/MAX(1,24-(3-0))),H16+H17)) -> 2.8537195 | I18: =IF(4<0,0,IF(24-(4-0)>0,MIN(I16+I17,(I16+I17)/MAX(1,24-(4-0))),I16+I17)) -> 2.8537195 | J18: =IF(5<0,0,IF(24-(5-0)>0,MIN(J16+J17,(J16+J17)/MAX(1,24-(5-0))),J16+J17)) -> 2.8537195 | K18: =IF(6<0,0,IF(24-(6-0)>0,MIN(K16+K17,(K16+K17)/MAX(1,24-(6-0))),K16+K17)) -> 2.8537195 | L18: =IF(7<0,0,IF(24-(7-0)>0,MIN(L16+L17,(L16+L17)/MAX(1,24-(7-0))),L16+L17)) -> 2.8537195 | M18: =IF(8<0,0,IF(24-(8-0)>0,MIN(M16+M17,(M16+M17)/MAX(1,24-(8-0))),M16+M17)) -> 2.8537195 | N18: =IF(9<0,0,IF(24-(9-0)>0,MIN(N16+N17,(N16+N17)/MAX(1,24-(9-0))),N16+N17)) -> 2.8537195 | O18: =IF(10<0,0,IF(24-(10-0)>0,MIN(O16+O17,(O16+O17)/MAX(1,24-(10-0))),O16+O17)) -> 2.8537195 | P18: =IF(11<0,0,IF(24-(11-0)>0,MIN(P16+P17,(P16+P17)/MAX(1,24-(11-0))),P16+P17)) -> 2.8537195 | Q18: =IF(12<0,0,IF(24-(12-0)>0,MIN(Q16+Q17,(Q16+Q17)/MAX(1,24-(12-0))),Q16+Q17)) -> 2.8537195 | R18: =IF(13<0,0,IF(24-(13-0)>0,MIN(R16+R17,(R16+R17)/MAX(1,24-(13-0))),R16+R17)) -> 2.8537195 | S18: =IF(14<0,0,IF(24-(14-0)>0,MIN(S16+S17,(S16+S17)/MAX(1,24-(14-0))),S16+S17)) -> 2.7672161 | T18: =IF(15<0,0,IF(24-(15-0)>0,MIN(T16+T17,(T16+T17)/MAX(1,24-(15-0))),T16+T17)) -> 2.7672161 | U18: =IF(16<0,0,IF(24-(16-0)>0,MIN(U16+U17,(U16+U17)/MAX(1,24-(16-0))),U16+U17)) -> 2.7672161 | V18: =IF(17<0,0,IF(24-(17-0)>0,MIN(V16+V17,(V16+V17)/MAX(1,24-(17-0))),V16+V17)) -> 2.7672161 | W18: =IF(18<0,0,IF(24-(18-0)>0,MIN(W16+W17,(W16+W17)/MAX(1,24-(18-0))),W16+W17)) -> 2.7672161 | X18: =IF(19<0,0,IF(24-(19-0)>0,MIN(X16+X17,(X16+X17)/MAX(1,24-(19-0))),X16+X17)) -> 2.7672161 | Y18: =IF(20<0,0,IF(24-(20-0)>0,MIN(Y16+Y17,(Y16+Y17)/MAX(1,24-(20-0))),Y16+Y17)) -> 2.7672161 | Z18: =IF(21<0,0,IF(24-(21-0)>0,MIN(Z16+Z17,(Z16+Z17)/MAX(1,24-(21-0))),Z16+Z17)) -> 2.7672161 | AA18: =IF(22<0,0,IF(24-(22-0)>0,MIN(AA16+AA17,(AA16+AA17)/MAX(1,24-(22-0))),AA16+AA17)) -> 2.7672161 | AB18: =IF(23<0,0,IF(24-(23-0)>0,MIN(AB16+AB17,(AB16+AB17)/MAX(1,24-(23-0))),AB16+AB17)) -> 2.7672161 | AC18: =IF(24<0,0,IF(24-(24-0)>0,MIN(AC16+AC17,(AC16+AC17)/MAX(1,24-(24-0))),AC16+AC17)) -> 0 | AD18: =IF(25<0,0,IF(24-(25-0)>0,MIN(AD16+AD17,(AD16+AD17)/MAX(1,24-(25-0))),AD16+AD17)) -> 0 | AE18: =IF(26<0,0,IF(24-(26-0)>0,MIN(AE16+AE17,(AE16+AE17)/MAX(1,24-(26-0))),AE16+AE17)) -> 0 | AF18: =IF(27<0,0,IF(24-(27-0)>0,MIN(AF16+AF17,(AF16+AF17)/MAX(1,24-(27-0))),AF16+AF17)) -> 0 | AG18: =IF(28<0,0,IF(24-(28-0)>0,MIN(AG16+AG17,(AG16+AG17)/MAX(1,24-(28-0))),AG16+AG17)) -> 0 | AH18: =IF(29<0,0,IF(24-(29-0)>0,MIN(AH16+AH17,(AH16+AH17)/MAX(1,24-(29-0))),AH16+AH17)) -> 0 | AI18: =IF(30<0,0,IF(24-(30-0)>0,MIN(AI16+AI17,(AI16+AI17)/MAX(1,24-(30-0))),AI16+AI17)) -> 0 | AJ18: =IF(31<0,0,IF(24-(31-0)>0,MIN(AJ16+AJ17,(AJ16+AJ17)/MAX(1,24-(31-0))),AJ16+AJ17)) -> 0 | AK18: =IF(32<0,0,IF(24-(32-0)>0,MIN(AK16+AK17,(AK16+AK17)/MAX(1,24-(32-0))),AK16+AK17)) -> 0 | AL18: =IF(33<0,0,IF(24-(33-0)>0,MIN(AL16+AL17,(AL16+AL17)/MAX(1,24-(33-0))),AL16+AL17)) -> 0 | AM18: =IF(34<0,0,IF(24-(34-0)>0,MIN(AM16+AM17,(AM16+AM17)/MAX(1,24-(34-0))),AM16+AM17)) -> 0 | AN18: =IF(35<0,0,IF(24-(35-0)>0,MIN(AN16+AN17,(AN16+AN17)/MAX(1,24-(35-0))),AN16+AN17)) -> 0 | AO18: =IF(36<0,0,IF(24-(36-0)>0,MIN(AO16+AO17,(AO16+AO17)/MAX(1,24-(36-0))),AO16+AO17)) -> 0 | AP18: =IF(37<0,0,IF(24-(37-0)>0,MIN(AP16+AP17,(AP16+AP17)/MAX(1,24-(37-0))),AP16+AP17)) -> 0 | AQ18: =IF(38<0,0,IF(24-(38-0)>0,MIN(AQ16+AQ17,(AQ16+AQ17)/MAX(1,24-(38-0))),AQ16+AQ17)) -> 0 | AR18: =IF(39<0,0,IF(24-(39-0)>0,MIN(AR16+AR17,(AR16+AR17)/MAX(1,24-(39-0))),AR16+AR17)) -> 0 | AS18: =IF(40<0,0,IF(24-(40-0)>0,MIN(AS16+AS17,(AS16+AS17)/MAX(1,24-(40-0))),AS16+AS17)) -> 0 | AT18: =IF(41<0,0,IF(24-(41-0)>0,MIN(AT16+AT17,(AT16+AT17)/MAX(1,24-(41-0))),AT16+AT17)) -> 0 | AU18: =IF(42<0,0,IF(24-(42-0)>0,MIN(AU16+AU17,(AU16+AU17)/MAX(1,24-(42-0))),AU16+AU17)) -> 0 | AV18: =IF(43<0,0,IF(24-(43-0)>0,MIN(AV16+AV17,(AV16+AV17)/MAX(1,24-(43-0))),AV16+AV17)) -> 0 | AW18: =IF(44<0,0,IF(24-(44-0)>0,MIN(AW16+AW17,(AW16+AW17)/MAX(1,24-(44-0))),AW16+AW17)) -> 0 | AX18: =IF(45<0,0,IF(24-(45-0)>0,MIN(AX16+AX17,(AX16+AX17)/MAX(1,24-(45-0))),AX16+AX17)) -> 0 | AY18: =IF(46<0,0,IF(24-(46-0)>0,MIN(AY16+AY17,(AY16+AY17)/MAX(1,24-(46-0))),AY16+AY17)) -> 0 | AZ18: =IF(47<0,0,IF(24-(47-0)>0,MIN(AZ16+AZ17,(AZ16+AZ17)/MAX(1,24-(47-0))),AZ16+AZ17)) -> 0 | BA18: =IF(48<0,0,IF(24-(48-0)>0,MIN(BA16+BA17,(BA16+BA17)/MAX(1,24-(48-0))),BA16+BA17)) -> 0 | BB18: =IF(49<0,0,IF(24-(49-0)>0,MIN(BB16+BB17,(BB16+BB17)/MAX(1,24-(49-0))),BB16+BB17)) -> 0 | BC18: =IF(50<0,0,IF(24-(50-0)>0,MIN(BC16+BC17,(BC16+BC17)/MAX(1,24-(50-0))),BC16+BC17)) -> 0 | BD18: =IF(51<0,0,IF(24-(51-0)>0,MIN(BD16+BD17,(BD16+BD17)/MAX(1,24-(51-0))),BD16+BD17)) -> 0 | BE18: =IF(52<0,0,IF(24-(52-0)>0,MIN(BE16+BE17,(BE16+BE17)/MAX(1,24-(52-0))),BE16+BE17)) -> 0 | BF18: =IF(53<0,0,IF(24-(53-0)>0,MIN(BF16+BF17,(BF16+BF17)/MAX(1,24-(53-0))),BF16+BF17)) -> 0 | BG18: =IF(54<0,0,IF(24-(54-0)>0,MIN(BG16+BG17,(BG16+BG17)/MAX(1,24-(54-0))),BG16+BG17)) -> 0 | BH18: =IF(55<0,0,IF(24-(55-0)>0,MIN(BH16+BH17,(BH16+BH17)/MAX(1,24-(55-0))),BH16+BH17)) -> 0 | BI18: =IF(56<0,0,IF(24-(56-0)>0,MIN(BI16+BI17,(BI16+BI17)/MAX(1,24-(56-0))),BI16+BI17)) -> 0 | BJ18: =IF(57<0,0,IF(24-(57-0)>0,MIN(BJ16+BJ17,(BJ16+BJ17)/MAX(1,24-(57-0))),BJ16+BJ17)) -> 0 | BK18: =IF(58<0,0,IF(24-(58-0)>0,MIN(BK16+BK17,(BK16+BK17)/MAX(1,24-(58-0))),BK16+BK17)) -> 0 | BL18: =IF(59<0,0,IF(24-(59-0)>0,MIN(BL16+BL17,(BL16+BL17)/MAX(1,24-(59-0))),BL16+BL17)) -> 0
C19: Pre-sale NBV | E19: =E16+E17-E18 -> 67.083333 | F19: =F16+F17-F18 -> 64.166667 | G19: =G16+G17-G18 -> 59.999341 | H19: =H16+H17-H18 -> 57.074391 | I19: =I16+I17-I18 -> 54.220671 | J19: =J16+J17-J18 -> 51.366952 | K19: =K16+K17-K18 -> 48.513232 | L19: =L16+L17-L18 -> 45.659513 | ... BL19: =BL16+BL17-BL18 -> 0
C20: Allocated disposal NBV | E20: =IF(E91>0,E19/E91*Transfers!E24,0) -> 0 | F20: =IF(F91>0,F19/F91*Transfers!F24,0) -> 1.310214 | G20: =IF(G91>0,G19/G91*Transfers!G24,0) -> 0.071230928 | H20: =IF(H91>0,H19/H91*Transfers!H24,0) -> 0 | I20: =IF(I91>0,I19/I91*Transfers!I24,0) -> 0 | J20: =IF(J91>0,J19/J91*Transfers!J24,0) -> 0 | K20: =IF(K91>0,K19/K91*Transfers!K24,0) -> 0 | L20: =IF(L91>0,L19/L91*Transfers!L24,0) -> 0 | ... BL20: =IF(BL91>0,BL19/BL91*Transfers!BL24,0) -> 0
C21: Closing NBV | E21: =E19-E20 -> 67.083333 | F21: =F19-F20 -> 62.856453 | G21: =G19-G20 -> 59.92811 | H21: =H19-H20 -> 57.074391 | I21: =I19-I20 -> 54.220671 | J21: =J19-J20 -> 51.366952 | K21: =K19-K20 -> 48.513232 | L21: =L19-L20 -> 45.659513 | ... BL21: =BL19-BL20 -> 0
C22: Opening remaining life 3 years
C23: Opening NBV | E23: =(3)*(Assumptions!G143-Assumptions!H143) -> 105 | F23: =E28 -> 102.08333 | G23: =F28 -> 97.141791 | H23: =G28 -> 94.172745 | I23: =H28 -> 91.319025 | J23: =I28 -> 88.465306 | K23: =J28 -> 85.611586 | L23: =K28 -> 82.757867 | M23: =L28 -> 79.904147 | ... BL23: =BK28 -> 0
C24: Additions | E24: =0 -> 0 | F24: =0 -> 0 | G24: =0 -> 0 | H24: =0 -> 0 | I24: =0 -> 0 | J24: =0 -> 0 | K24: =0 -> 0 | L24: =0 -> 0 | ... BL24: =0 -> 0
C25: Amortisation | E25: =IF(0<0,0,IF(36-(0-0)>0,MIN(E23+E24,(E23+E24)/MAX(1,36-(0-0))),E23+E24)) -> 2.9166667 | F25: =IF(1<0,0,IF(36-(1-0)>0,MIN(F23+F24,(F23+F24)/MAX(1,36-(1-0))),F23+F24)) -> 2.9166667 | G25: =IF(2<0,0,IF(36-(2-0)>0,MIN(G23+G24,(G23+G24)/MAX(1,36-(2-0))),G23+G24)) -> 2.8571115 | H25: =IF(3<0,0,IF(36-(3-0)>0,MIN(H23+H24,(H23+H24)/MAX(1,36-(3-0))),H23+H24)) -> 2.8537195 | I25: =IF(4<0,0,IF(36-(4-0)>0,MIN(I23+I24,(I23+I24)/MAX(1,36-(4-0))),I23+I24)) -> 2.8537195 | J25: =IF(5<0,0,IF(36-(5-0)>0,MIN(J23+J24,(J23+J24)/MAX(1,36-(5-0))),J23+J24)) -> 2.8537195 | K25: =IF(6<0,0,IF(36-(6-0)>0,MIN(K23+K24,(K23+K24)/MAX(1,36-(6-0))),K23+K24)) -> 2.8537195 | L25: =IF(7<0,0,IF(36-(7-0)>0,MIN(L23+L24,(L23+L24)/MAX(1,36-(7-0))),L23+L24)) -> 2.8537195 | M25: =IF(8<0,0,IF(36-(8-0)>0,MIN(M23+M24,(M23+M24)/MAX(1,36-(8-0))),M23+M24)) -> 2.8537195 | N25: =IF(9<0,0,IF(36-(9-0)>0,MIN(N23+N24,(N23+N24)/MAX(1,36-(9-0))),N23+N24)) -> 2.8537195 | O25: =IF(10<0,0,IF(36-(10-0)>0,MIN(O23+O24,(O23+O24)/MAX(1,36-(10-0))),O23+O24)) -> 2.8537195 | P25: =IF(11<0,0,IF(36-(11-0)>0,MIN(P23+P24,(P23+P24)/MAX(1,36-(11-0))),P23+P24)) -> 2.8537195 | Q25: =IF(12<0,0,IF(36-(12-0)>0,MIN(Q23+Q24,(Q23+Q24)/MAX(1,36-(12-0))),Q23+Q24)) -> 2.8537195 | R25: =IF(13<0,0,IF(36-(13-0)>0,MIN(R23+R24,(R23+R24)/MAX(1,36-(13-0))),R23+R24)) -> 2.8537195 | S25: =IF(14<0,0,IF(36-(14-0)>0,MIN(S23+S24,(S23+S24)/MAX(1,36-(14-0))),S23+S24)) -> 2.7672161 | T25: =IF(15<0,0,IF(36-(15-0)>0,MIN(T23+T24,(T23+T24)/MAX(1,36-(15-0))),T23+T24)) -> 2.7672161 | U25: =IF(16<0,0,IF(36-(16-0)>0,MIN(U23+U24,(U23+U24)/MAX(1,36-(16-0))),U23+U24)) -> 2.7672161 | V25: =IF(17<0,0,IF(36-(17-0)>0,MIN(V23+V24,(V23+V24)/MAX(1,36-(17-0))),V23+V24)) -> 2.7672161 | W25: =IF(18<0,0,IF(36-(18-0)>0,MIN(W23+W24,(W23+W24)/MAX(1,36-(18-0))),W23+W24)) -> 2.7672161 | X25: =IF(19<0,0,IF(36-(19-0)>0,MIN(X23+X24,(X23+X24)/MAX(1,36-(19-0))),X23+X24)) -> 2.7672161 | Y25: =IF(20<0,0,IF(36-(20-0)>0,MIN(Y23+Y24,(Y23+Y24)/MAX(1,36-(20-0))),Y23+Y24)) -> 2.7672161 | Z25: =IF(21<0,0,IF(36-(21-0)>0,MIN(Z23+Z24,(Z23+Z24)/MAX(1,36-(21-0))),Z23+Z24)) -> 2.7672161 | AA25: =IF(22<0,0,IF(36-(22-0)>0,MIN(AA23+AA24,(AA23+AA24)/MAX(1,36-(22-0))),AA23+AA24)) -> 2.7672161 | AB25: =IF(23<0,0,IF(36-(23-0)>0,MIN(AB23+AB24,(AB23+AB24)/MAX(1,36-(23-0))),AB23+AB24)) -> 2.7672161 | AC25: =IF(24<0,0,IF(36-(24-0)>0,MIN(AC23+AC24,(AC23+AC24)/MAX(1,36-(24-0))),AC23+AC24)) -> 2.7672161 | AD25: =IF(25<0,0,IF(36-(25-0)>0,MIN(AD23+AD24,(AD23+AD24)/MAX(1,36-(25-0))),AD23+AD24)) -> 2.7672161 | AE25: =IF(26<0,0,IF(36-(26-0)>0,MIN(AE23+AE24,(AE23+AE24)/MAX(1,36-(26-0))),AE23+AE24)) -> 2.6566382 | AF25: =IF(27<0,0,IF(36-(27-0)>0,MIN(AF23+AF24,(AF23+AF24)/MAX(1,36-(27-0))),AF23+AF24)) -> 2.6566382 | AG25: =IF(28<0,0,IF(36-(28-0)>0,MIN(AG23+AG24,(AG23+AG24)/MAX(1,36-(28-0))),AG23+AG24)) -> 2.6566382 | AH25: =IF(29<0,0,IF(36-(29-0)>0,MIN(AH23+AH24,(AH23+AH24)/MAX(1,36-(29-0))),AH23+AH24)) -> 2.6566382 | AI25: =IF(30<0,0,IF(36-(30-0)>0,MIN(AI23+AI24,(AI23+AI24)/MAX(1,36-(30-0))),AI23+AI24)) -> 2.6566382 | AJ25: =IF(31<0,0,IF(36-(31-0)>0,MIN(AJ23+AJ24,(AJ23+AJ24)/MAX(1,36-(31-0))),AJ23+AJ24)) -> 2.6566382 | AK25: =IF(32<0,0,IF(36-(32-0)>0,MIN(AK23+AK24,(AK23+AK24)/MAX(1,36-(32-0))),AK23+AK24)) -> 2.6566382 | AL25: =IF(33<0,0,IF(36-(33-0)>0,MIN(AL23+AL24,(AL23+AL24)/MAX(1,36-(33-0))),AL23+AL24)) -> 2.6566382 | AM25: =IF(34<0,0,IF(36-(34-0)>0,MIN(AM23+AM24,(AM23+AM24)/MAX(1,36-(34-0))),AM23+AM24)) -> 2.6566382 | AN25: =IF(35<0,0,IF(36-(35-0)>0,MIN(AN23+AN24,(AN23+AN24)/MAX(1,36-(35-0))),AN23+AN24)) -> 2.6566382 | AO25: =IF(36<0,0,IF(36-(36-0)>0,MIN(AO23+AO24,(AO23+AO24)/MAX(1,36-(36-0))),AO23+AO24)) -> 0 | AP25: =IF(37<0,0,IF(36-(37-0)>0,MIN(AP23+AP24,(AP23+AP24)/MAX(1,36-(37-0))),AP23+AP24)) -> 0 | AQ25: =IF(38<0,0,IF(36-(38-0)>0,MIN(AQ23+AQ24,(AQ23+AQ24)/MAX(1,36-(38-0))),AQ23+AQ24)) -> 0 | AR25: =IF(39<0,0,IF(36-(39-0)>0,MIN(AR23+AR24,(AR23+AR24)/MAX(1,36-(39-0))),AR23+AR24)) -> 0 | AS25: =IF(40<0,0,IF(36-(40-0)>0,MIN(AS23+AS24,(AS23+AS24)/MAX(1,36-(40-0))),AS23+AS24)) -> 0 | AT25: =IF(41<0,0,IF(36-(41-0)>0,MIN(AT23+AT24,(AT23+AT24)/MAX(1,36-(41-0))),AT23+AT24)) -> 0 | AU25: =IF(42<0,0,IF(36-(42-0)>0,MIN(AU23+AU24,(AU23+AU24)/MAX(1,36-(42-0))),AU23+AU24)) -> 0 | AV25: =IF(43<0,0,IF(36-(43-0)>0,MIN(AV23+AV24,(AV23+AV24)/MAX(1,36-(43-0))),AV23+AV24)) -> 0 | AW25: =IF(44<0,0,IF(36-(44-0)>0,MIN(AW23+AW24,(AW23+AW24)/MAX(1,36-(44-0))),AW23+AW24)) -> 0 | AX25: =IF(45<0,0,IF(36-(45-0)>0,MIN(AX23+AX24,(AX23+AX24)/MAX(1,36-(45-0))),AX23+AX24)) -> 0 | AY25: =IF(46<0,0,IF(36-(46-0)>0,MIN(AY23+AY24,(AY23+AY24)/MAX(1,36-(46-0))),AY23+AY24)) -> 0 | AZ25: =IF(47<0,0,IF(36-(47-0)>0,MIN(AZ23+AZ24,(AZ23+AZ24)/MAX(1,36-(47-0))),AZ23+AZ24)) -> 0 | BA25: =IF(48<0,0,IF(36-(48-0)>0,MIN(BA23+BA24,(BA23+BA24)/MAX(1,36-(48-0))),BA23+BA24)) -> 0 | BB25: =IF(49<0,0,IF(36-(49-0)>0,MIN(BB23+BB24,(BB23+BB24)/MAX(1,36-(49-0))),BB23+BB24)) -> 0 | BC25: =IF(50<0,0,IF(36-(50-0)>0,MIN(BC23+BC24,(BC23+BC24)/MAX(1,36-(50-0))),BC23+BC24)) -> 0 | BD25: =IF(51<0,0,IF(36-(51-0)>0,MIN(BD23+BD24,(BD23+BD24)/MAX(1,36-(51-0))),BD23+BD24)) -> 0 | BE25: =IF(52<0,0,IF(36-(52-0)>0,MIN(BE23+BE24,(BE23+BE24)/MAX(1,36-(52-0))),BE23+BE24)) -> 0 | BF25: =IF(53<0,0,IF(36-(53-0)>0,MIN(BF23+BF24,(BF23+BF24)/MAX(1,36-(53-0))),BF23+BF24)) -> 0 | BG25: =IF(54<0,0,IF(36-(54-0)>0,MIN(BG23+BG24,(BG23+BG24)/MAX(1,36-(54-0))),BG23+BG24)) -> 0 | BH25: =IF(55<0,0,IF(36-(55-0)>0,MIN(BH23+BH24,(BH23+BH24)/MAX(1,36-(55-0))),BH23+BH24)) -> 0 | BI25: =IF(56<0,0,IF(36-(56-0)>0,MIN(BI23+BI24,(BI23+BI24)/MAX(1,36-(56-0))),BI23+BI24)) -> 0 | BJ25: =IF(57<0,0,IF(36-(57-0)>0,MIN(BJ23+BJ24,(BJ23+BJ24)/MAX(1,36-(57-0))),BJ23+BJ24)) -> 0 | BK25: =IF(58<0,0,IF(36-(58-0)>0,MIN(BK23+BK24,(BK23+BK24)/MAX(1,36-(58-0))),BK23+BK24)) -> 0 | BL25: =IF(59<0,0,IF(36-(59-0)>0,MIN(BL23+BL24,(BL23+BL24)/MAX(1,36-(59-0))),BL23+BL24)) -> 0
C26: Pre-sale NBV | E26: =E23+E24-E25 -> 102.08333 | F26: =F23+F24-F25 -> 99.166667 | G26: =G23+G24-G25 -> 94.284679 | H26: =H23+H24-H25 -> 91.319025 | I26: =I23+I24-I25 -> 88.465306 | J26: =J23+J24-J25 -> 85.611586 | K26: =K23+K24-K25 -> 82.757867 | L26: =L23+L24-L25 -> 79.904147 | ... BL26: =BL23+BL24-BL25 -> 0
C27: Allocated disposal NBV | E27: =IF(E91>0,E26/E91*Transfers!E24,0) -> 0 | F27: =IF(F91>0,F26/F91*Transfers!F24,0) -> 2.0248762 | G27: =IF(G91>0,G26/G91*Transfers!G24,0) -> 0.11193432 | H27: =IF(H91>0,H26/H91*Transfers!H24,0) -> 0 | I27: =IF(I91>0,I26/I91*Transfers!I24,0) -> 0 | J27: =IF(J91>0,J26/J91*Transfers!J24,0) -> 0 | K27: =IF(K91>0,K26/K91*Transfers!K24,0) -> 0 | L27: =IF(L91>0,L26/L91*Transfers!L24,0) -> 0 | ... BL27: =IF(BL91>0,BL26/BL91*Transfers!BL24,0) -> 0
C28: Closing NBV | E28: =E26-E27 -> 102.08333 | F28: =F26-F27 -> 97.141791 | G28: =G26-G27 -> 94.172745 | H28: =H26-H27 -> 91.319025 | I28: =I26-I27 -> 88.465306 | J28: =J26-J27 -> 85.611586 | K28: =K26-K27 -> 82.757867 | L28: =L26-L27 -> 79.904147 | ... BL28: =BL26-BL27 -> 0
C29: Opening remaining life 4 years
C30: Opening NBV | E30: =(4)*(Assumptions!H143-Assumptions!I143) -> 115.232 | F30: =E35 -> 112.83133 | G30: =F35 -> 108.17579 | H30: =G35 -> 105.69851 | I30: =H35 -> 103.34965 | J30: =I35 -> 101.0008 | K30: =J35 -> 98.651943 | L30: =K35 -> 96.303087 | M30: =L35 -> 93.954231 | ... BL30: =BK35 -> 0
C31: Additions | E31: =0 -> 0 | F31: =0 -> 0 | G31: =0 -> 0 | H31: =0 -> 0 | I31: =0 -> 0 | J31: =0 -> 0 | K31: =0 -> 0 | L31: =0 -> 0 | ... BL31: =0 -> 0
C32: Amortisation | E32: =IF(0<0,0,IF(48-(0-0)>0,MIN(E30+E31,(E30+E31)/MAX(1,48-(0-0))),E30+E31)) -> 2.4006667 | F32: =IF(1<0,0,IF(48-(1-0)>0,MIN(F30+F31,(F30+F31)/MAX(1,48-(1-0))),F30+F31)) -> 2.4006667 | G32: =IF(2<0,0,IF(48-(2-0)>0,MIN(G30+G31,(G30+G31)/MAX(1,48-(2-0))),G30+G31)) -> 2.3516476 | H32: =IF(3<0,0,IF(48-(3-0)>0,MIN(H30+H31,(H30+H31)/MAX(1,48-(3-0))),H30+H31)) -> 2.3488558 | I32: =IF(4<0,0,IF(48-(4-0)>0,MIN(I30+I31,(I30+I31)/MAX(1,48-(4-0))),I30+I31)) -> 2.3488558 | J32: =IF(5<0,0,IF(48-(5-0)>0,MIN(J30+J31,(J30+J31)/MAX(1,48-(5-0))),J30+J31)) -> 2.3488558 | K32: =IF(6<0,0,IF(48-(6-0)>0,MIN(K30+K31,(K30+K31)/MAX(1,48-(6-0))),K30+K31)) -> 2.3488558 | L32: =IF(7<0,0,IF(48-(7-0)>0,MIN(L30+L31,(L30+L31)/MAX(1,48-(7-0))),L30+L31)) -> 2.3488558 | M32: =IF(8<0,0,IF(48-(8-0)>0,MIN(M30+M31,(M30+M31)/MAX(1,48-(8-0))),M30+M31)) -> 2.3488558 | N32: =IF(9<0,0,IF(48-(9-0)>0,MIN(N30+N31,(N30+N31)/MAX(1,48-(9-0))),N30+N31)) -> 2.3488558 | O32: =IF(10<0,0,IF(48-(10-0)>0,MIN(O30+O31,(O30+O31)/MAX(1,48-(10-0))),O30+O31)) -> 2.3488558 | P32: =IF(11<0,0,IF(48-(11-0)>0,MIN(P30+P31,(P30+P31)/MAX(1,48-(11-0))),P30+P31)) -> 2.3488558 | Q32: =IF(12<0,0,IF(48-(12-0)>0,MIN(Q30+Q31,(Q30+Q31)/MAX(1,48-(12-0))),Q30+Q31)) -> 2.3488558 | R32: =IF(13<0,0,IF(48-(13-0)>0,MIN(R30+R31,(R30+R31)/MAX(1,48-(13-0))),R30+R31)) -> 2.3488558 | S32: =IF(14<0,0,IF(48-(14-0)>0,MIN(S30+S31,(S30+S31)/MAX(1,48-(14-0))),S30+S31)) -> 2.277656 | T32: =IF(15<0,0,IF(48-(15-0)>0,MIN(T30+T31,(T30+T31)/MAX(1,48-(15-0))),T30+T31)) -> 2.277656 | U32: =IF(16<0,0,IF(48-(16-0)>0,MIN(U30+U31,(U30+U31)/MAX(1,48-(16-0))),U30+U31)) -> 2.277656 | V32: =IF(17<0,0,IF(48-(17-0)>0,MIN(V30+V31,(V30+V31)/MAX(1,48-(17-0))),V30+V31)) -> 2.277656 | W32: =IF(18<0,0,IF(48-(18-0)>0,MIN(W30+W31,(W30+W31)/MAX(1,48-(18-0))),W30+W31)) -> 2.277656 | X32: =IF(19<0,0,IF(48-(19-0)>0,MIN(X30+X31,(X30+X31)/MAX(1,48-(19-0))),X30+X31)) -> 2.277656 | Y32: =IF(20<0,0,IF(48-(20-0)>0,MIN(Y30+Y31,(Y30+Y31)/MAX(1,48-(20-0))),Y30+Y31)) -> 2.277656 | Z32: =IF(21<0,0,IF(48-(21-0)>0,MIN(Z30+Z31,(Z30+Z31)/MAX(1,48-(21-0))),Z30+Z31)) -> 2.277656 | AA32: =IF(22<0,0,IF(48-(22-0)>0,MIN(AA30+AA31,(AA30+AA31)/MAX(1,48-(22-0))),AA30+AA31)) -> 2.277656 | AB32: =IF(23<0,0,IF(48-(23-0)>0,MIN(AB30+AB31,(AB30+AB31)/MAX(1,48-(23-0))),AB30+AB31)) -> 2.277656 | AC32: =IF(24<0,0,IF(48-(24-0)>0,MIN(AC30+AC31,(AC30+AC31)/MAX(1,48-(24-0))),AC30+AC31)) -> 2.277656 | AD32: =IF(25<0,0,IF(48-(25-0)>0,MIN(AD30+AD31,(AD30+AD31)/MAX(1,48-(25-0))),AD30+AD31)) -> 2.277656 | AE32: =IF(26<0,0,IF(48-(26-0)>0,MIN(AE30+AE31,(AE30+AE31)/MAX(1,48-(26-0))),AE30+AE31)) -> 2.186641 | AF32: =IF(27<0,0,IF(48-(27-0)>0,MIN(AF30+AF31,(AF30+AF31)/MAX(1,48-(27-0))),AF30+AF31)) -> 2.186641 | AG32: =IF(28<0,0,IF(48-(28-0)>0,MIN(AG30+AG31,(AG30+AG31)/MAX(1,48-(28-0))),AG30+AG31)) -> 2.186641 | AH32: =IF(29<0,0,IF(48-(29-0)>0,MIN(AH30+AH31,(AH30+AH31)/MAX(1,48-(29-0))),AH30+AH31)) -> 2.186641 | AI32: =IF(30<0,0,IF(48-(30-0)>0,MIN(AI30+AI31,(AI30+AI31)/MAX(1,48-(30-0))),AI30+AI31)) -> 2.186641 | AJ32: =IF(31<0,0,IF(48-(31-0)>0,MIN(AJ30+AJ31,(AJ30+AJ31)/MAX(1,48-(31-0))),AJ30+AJ31)) -> 2.186641 | AK32: =IF(32<0,0,IF(48-(32-0)>0,MIN(AK30+AK31,(AK30+AK31)/MAX(1,48-(32-0))),AK30+AK31)) -> 2.186641 | AL32: =IF(33<0,0,IF(48-(33-0)>0,MIN(AL30+AL31,(AL30+AL31)/MAX(1,48-(33-0))),AL30+AL31)) -> 2.186641 | AM32: =IF(34<0,0,IF(48-(34-0)>0,MIN(AM30+AM31,(AM30+AM31)/MAX(1,48-(34-0))),AM30+AM31)) -> 2.186641 | AN32: =IF(35<0,0,IF(48-(35-0)>0,MIN(AN30+AN31,(AN30+AN31)/MAX(1,48-(35-0))),AN30+AN31)) -> 2.186641 | AO32: =IF(36<0,0,IF(48-(36-0)>0,MIN(AO30+AO31,(AO30+AO31)/MAX(1,48-(36-0))),AO30+AO31)) -> 2.186641 | AP32: =IF(37<0,0,IF(48-(37-0)>0,MIN(AP30+AP31,(AP30+AP31)/MAX(1,48-(37-0))),AP30+AP31)) -> 2.186641 | AQ32: =IF(38<0,0,IF(48-(38-0)>0,MIN(AQ30+AQ31,(AQ30+AQ31)/MAX(1,48-(38-0))),AQ30+AQ31)) -> 2.0708143 | AR32: =IF(39<0,0,IF(48-(39-0)>0,MIN(AR30+AR31,(AR30+AR31)/MAX(1,48-(39-0))),AR30+AR31)) -> 2.0708143 | AS32: =IF(40<0,0,IF(48-(40-0)>0,MIN(AS30+AS31,(AS30+AS31)/MAX(1,48-(40-0))),AS30+AS31)) -> 2.0708143 | AT32: =IF(41<0,0,IF(48-(41-0)>0,MIN(AT30+AT31,(AT30+AT31)/MAX(1,48-(41-0))),AT30+AT31)) -> 2.0708143 | AU32: =IF(42<0,0,IF(48-(42-0)>0,MIN(AU30+AU31,(AU30+AU31)/MAX(1,48-(42-0))),AU30+AU31)) -> 2.0708143 | AV32: =IF(43<0,0,IF(48-(43-0)>0,MIN(AV30+AV31,(AV30+AV31)/MAX(1,48-(43-0))),AV30+AV31)) -> 2.0708143 | AW32: =IF(44<0,0,IF(48-(44-0)>0,MIN(AW30+AW31,(AW30+AW31)/MAX(1,48-(44-0))),AW30+AW31)) -> 2.0708143 | AX32: =IF(45<0,0,IF(48-(45-0)>0,MIN(AX30+AX31,(AX30+AX31)/MAX(1,48-(45-0))),AX30+AX31)) -> 2.0708143 | AY32: =IF(46<0,0,IF(48-(46-0)>0,MIN(AY30+AY31,(AY30+AY31)/MAX(1,48-(46-0))),AY30+AY31)) -> 2.0708143 | AZ32: =IF(47<0,0,IF(48-(47-0)>0,MIN(AZ30+AZ31,(AZ30+AZ31)/MAX(1,48-(47-0))),AZ30+AZ31)) -> 2.0708143 | BA32: =IF(48<0,0,IF(48-(48-0)>0,MIN(BA30+BA31,(BA30+BA31)/MAX(1,48-(48-0))),BA30+BA31)) -> 0 | BB32: =IF(49<0,0,IF(48-(49-0)>0,MIN(BB30+BB31,(BB30+BB31)/MAX(1,48-(49-0))),BB30+BB31)) -> 0 | BC32: =IF(50<0,0,IF(48-(50-0)>0,MIN(BC30+BC31,(BC30+BC31)/MAX(1,48-(50-0))),BC30+BC31)) -> 0 | BD32: =IF(51<0,0,IF(48-(51-0)>0,MIN(BD30+BD31,(BD30+BD31)/MAX(1,48-(51-0))),BD30+BD31)) -> 0 | BE32: =IF(52<0,0,IF(48-(52-0)>0,MIN(BE30+BE31,(BE30+BE31)/MAX(1,48-(52-0))),BE30+BE31)) -> 0 | BF32: =IF(53<0,0,IF(48-(53-0)>0,MIN(BF30+BF31,(BF30+BF31)/MAX(1,48-(53-0))),BF30+BF31)) -> 0 | BG32: =IF(54<0,0,IF(48-(54-0)>0,MIN(BG30+BG31,(BG30+BG31)/MAX(1,48-(54-0))),BG30+BG31)) -> 0 | BH32: =IF(55<0,0,IF(48-(55-0)>0,MIN(BH30+BH31,(BH30+BH31)/MAX(1,48-(55-0))),BH30+BH31)) -> 0 | BI32: =IF(56<0,0,IF(48-(56-0)>0,MIN(BI30+BI31,(BI30+BI31)/MAX(1,48-(56-0))),BI30+BI31)) -> 0 | BJ32: =IF(57<0,0,IF(48-(57-0)>0,MIN(BJ30+BJ31,(BJ30+BJ31)/MAX(1,48-(57-0))),BJ30+BJ31)) -> 0 | BK32: =IF(58<0,0,IF(48-(58-0)>0,MIN(BK30+BK31,(BK30+BK31)/MAX(1,48-(58-0))),BK30+BK31)) -> 0 | BL32: =IF(59<0,0,IF(48-(59-0)>0,MIN(BL30+BL31,(BL30+BL31)/MAX(1,48-(59-0))),BL30+BL31)) -> 0
C33: Pre-sale NBV | E33: =E30+E31-E32 -> 112.83133 | F33: =F30+F31-F32 -> 110.43067 | G33: =G30+G31-G32 -> 105.82414 | H33: =H30+H31-H32 -> 103.34965 | I33: =I30+I31-I32 -> 101.0008 | J33: =J30+J31-J32 -> 98.651943 | K33: =K30+K31-K32 -> 96.303087 | L33: =L30+L31-L32 -> 93.954231 | ... BL33: =BL30+BL31-BL32 -> 0
C34: Allocated disposal NBV | E34: =IF(E91>0,E33/E91*Transfers!E24,0) -> 0 | F34: =IF(F91>0,F33/F91*Transfers!F24,0) -> 2.2548749 | G34: =IF(G91>0,G33/G91*Transfers!G24,0) -> 0.12563391 | H34: =IF(H91>0,H33/H91*Transfers!H24,0) -> 0 | I34: =IF(I91>0,I33/I91*Transfers!I24,0) -> 0 | J34: =IF(J91>0,J33/J91*Transfers!J24,0) -> 0 | K34: =IF(K91>0,K33/K91*Transfers!K24,0) -> 0 | L34: =IF(L91>0,L33/L91*Transfers!L24,0) -> 0 | ... BL34: =IF(BL91>0,BL33/BL91*Transfers!BL24,0) -> 0
C35: Closing NBV | E35: =E33-E34 -> 112.83133 | F35: =F33-F34 -> 108.17579 | G35: =G33-G34 -> 105.69851 | H35: =H33-H34 -> 103.34965 | I35: =I33-I34 -> 101.0008 | J35: =J33-J34 -> 98.651943 | K35: =K33-K34 -> 96.303087 | L35: =L33-L34 -> 93.954231 | ... BL35: =BL33-BL34 -> 0
C36: Opening remaining life 5 years
C37: Opening NBV | E37: =(5)*(Assumptions!I143-0) -> 130.96 | F37: =E42 -> 128.77733 | G37: =F42 -> 124.00974 | H37: =G42 -> 121.72696 | I37: =H42 -> 119.5914 | J37: =I42 -> 117.45583 | K37: =J42 -> 115.32027 | L37: =K42 -> 113.18471 | M37: =L42 -> 111.04915 | ... BL37: =BK42 -> 1.7523081
C38: Additions | E38: =0 -> 0 | F38: =0 -> 0 | G38: =0 -> 0 | H38: =0 -> 0 | I38: =0 -> 0 | J38: =0 -> 0 | K38: =0 -> 0 | L38: =0 -> 0 | ... BL38: =0 -> 0
C39: Amortisation | E39: =IF(0<0,0,IF(60-(0-0)>0,MIN(E37+E38,(E37+E38)/MAX(1,60-(0-0))),E37+E38)) -> 2.1826667 | F39: =IF(1<0,0,IF(60-(1-0)>0,MIN(F37+F38,(F37+F38)/MAX(1,60-(1-0))),F37+F38)) -> 2.1826667 | G39: =IF(2<0,0,IF(60-(2-0)>0,MIN(G37+G38,(G37+G38)/MAX(1,60-(2-0))),G37+G38)) -> 2.138099 | H39: =IF(3<0,0,IF(60-(3-0)>0,MIN(H37+H38,(H37+H38)/MAX(1,60-(3-0))),H37+H38)) -> 2.1355606 | I39: =IF(4<0,0,IF(60-(4-0)>0,MIN(I37+I38,(I37+I38)/MAX(1,60-(4-0))),I37+I38)) -> 2.1355606 | J39: =IF(5<0,0,IF(60-(5-0)>0,MIN(J37+J38,(J37+J38)/MAX(1,60-(5-0))),J37+J38)) -> 2.1355606 | K39: =IF(6<0,0,IF(60-(6-0)>0,MIN(K37+K38,(K37+K38)/MAX(1,60-(6-0))),K37+K38)) -> 2.1355606 | L39: =IF(7<0,0,IF(60-(7-0)>0,MIN(L37+L38,(L37+L38)/MAX(1,60-(7-0))),L37+L38)) -> 2.1355606 | M39: =IF(8<0,0,IF(60-(8-0)>0,MIN(M37+M38,(M37+M38)/MAX(1,60-(8-0))),M37+M38)) -> 2.1355606 | N39: =IF(9<0,0,IF(60-(9-0)>0,MIN(N37+N38,(N37+N38)/MAX(1,60-(9-0))),N37+N38)) -> 2.1355606 | O39: =IF(10<0,0,IF(60-(10-0)>0,MIN(O37+O38,(O37+O38)/MAX(1,60-(10-0))),O37+O38)) -> 2.1355606 | P39: =IF(11<0,0,IF(60-(11-0)>0,MIN(P37+P38,(P37+P38)/MAX(1,60-(11-0))),P37+P38)) -> 2.1355606 | Q39: =IF(12<0,0,IF(60-(12-0)>0,MIN(Q37+Q38,(Q37+Q38)/MAX(1,60-(12-0))),Q37+Q38)) -> 2.1355606 | R39: =IF(13<0,0,IF(60-(13-0)>0,MIN(R37+R38,(R37+R38)/MAX(1,60-(13-0))),R37+R38)) -> 2.1355606 | S39: =IF(14<0,0,IF(60-(14-0)>0,MIN(S37+S38,(S37+S38)/MAX(1,60-(14-0))),S37+S38)) -> 2.0708264 | T39: =IF(15<0,0,IF(60-(15-0)>0,MIN(T37+T38,(T37+T38)/MAX(1,60-(15-0))),T37+T38)) -> 2.0708264 | U39: =IF(16<0,0,IF(60-(16-0)>0,MIN(U37+U38,(U37+U38)/MAX(1,60-(16-0))),U37+U38)) -> 2.0708264 | V39: =IF(17<0,0,IF(60-(17-0)>0,MIN(V37+V38,(V37+V38)/MAX(1,60-(17-0))),V37+V38)) -> 2.0708264 | W39: =IF(18<0,0,IF(60-(18-0)>0,MIN(W37+W38,(W37+W38)/MAX(1,60-(18-0))),W37+W38)) -> 2.0708264 | X39: =IF(19<0,0,IF(60-(19-0)>0,MIN(X37+X38,(X37+X38)/MAX(1,60-(19-0))),X37+X38)) -> 2.0708264 | Y39: =IF(20<0,0,IF(60-(20-0)>0,MIN(Y37+Y38,(Y37+Y38)/MAX(1,60-(20-0))),Y37+Y38)) -> 2.0708264 | Z39: =IF(21<0,0,IF(60-(21-0)>0,MIN(Z37+Z38,(Z37+Z38)/MAX(1,60-(21-0))),Z37+Z38)) -> 2.0708264 | AA39: =IF(22<0,0,IF(60-(22-0)>0,MIN(AA37+AA38,(AA37+AA38)/MAX(1,60-(22-0))),AA37+AA38)) -> 2.0708264 | AB39: =IF(23<0,0,IF(60-(23-0)>0,MIN(AB37+AB38,(AB37+AB38)/MAX(1,60-(23-0))),AB37+AB38)) -> 2.0708264 | AC39: =IF(24<0,0,IF(60-(24-0)>0,MIN(AC37+AC38,(AC37+AC38)/MAX(1,60-(24-0))),AC37+AC38)) -> 2.0708264 | AD39: =IF(25<0,0,IF(60-(25-0)>0,MIN(AD37+AD38,(AD37+AD38)/MAX(1,60-(25-0))),AD37+AD38)) -> 2.0708264 | AE39: =IF(26<0,0,IF(60-(26-0)>0,MIN(AE37+AE38,(AE37+AE38)/MAX(1,60-(26-0))),AE37+AE38)) -> 1.9880762 | AF39: =IF(27<0,0,IF(60-(27-0)>0,MIN(AF37+AF38,(AF37+AF38)/MAX(1,60-(27-0))),AF37+AF38)) -> 1.9880762 | AG39: =IF(28<0,0,IF(60-(28-0)>0,MIN(AG37+AG38,(AG37+AG38)/MAX(1,60-(28-0))),AG37+AG38)) -> 1.9880762 | AH39: =IF(29<0,0,IF(60-(29-0)>0,MIN(AH37+AH38,(AH37+AH38)/MAX(1,60-(29-0))),AH37+AH38)) -> 1.9880762 | AI39: =IF(30<0,0,IF(60-(30-0)>0,MIN(AI37+AI38,(AI37+AI38)/MAX(1,60-(30-0))),AI37+AI38)) -> 1.9880762 | AJ39: =IF(31<0,0,IF(60-(31-0)>0,MIN(AJ37+AJ38,(AJ37+AJ38)/MAX(1,60-(31-0))),AJ37+AJ38)) -> 1.9880762 | AK39: =IF(32<0,0,IF(60-(32-0)>0,MIN(AK37+AK38,(AK37+AK38)/MAX(1,60-(32-0))),AK37+AK38)) -> 1.9880762 | AL39: =IF(33<0,0,IF(60-(33-0)>0,MIN(AL37+AL38,(AL37+AL38)/MAX(1,60-(33-0))),AL37+AL38)) -> 1.9880762 | AM39: =IF(34<0,0,IF(60-(34-0)>0,MIN(AM37+AM38,(AM37+AM38)/MAX(1,60-(34-0))),AM37+AM38)) -> 1.9880762 | AN39: =IF(35<0,0,IF(60-(35-0)>0,MIN(AN37+AN38,(AN37+AN38)/MAX(1,60-(35-0))),AN37+AN38)) -> 1.9880762 | AO39: =IF(36<0,0,IF(60-(36-0)>0,MIN(AO37+AO38,(AO37+AO38)/MAX(1,60-(36-0))),AO37+AO38)) -> 1.9880762 | AP39: =IF(37<0,0,IF(60-(37-0)>0,MIN(AP37+AP38,(AP37+AP38)/MAX(1,60-(37-0))),AP37+AP38)) -> 1.9880762 | AQ39: =IF(38<0,0,IF(60-(38-0)>0,MIN(AQ37+AQ38,(AQ37+AQ38)/MAX(1,60-(38-0))),AQ37+AQ38)) -> 1.8827676 | AR39: =IF(39<0,0,IF(60-(39-0)>0,MIN(AR37+AR38,(AR37+AR38)/MAX(1,60-(39-0))),AR37+AR38)) -> 1.8827676 | AS39: =IF(40<0,0,IF(60-(40-0)>0,MIN(AS37+AS38,(AS37+AS38)/MAX(1,60-(40-0))),AS37+AS38)) -> 1.8827676 | AT39: =IF(41<0,0,IF(60-(41-0)>0,MIN(AT37+AT38,(AT37+AT38)/MAX(1,60-(41-0))),AT37+AT38)) -> 1.8827676 | AU39: =IF(42<0,0,IF(60-(42-0)>0,MIN(AU37+AU38,(AU37+AU38)/MAX(1,60-(42-0))),AU37+AU38)) -> 1.8827676 | AV39: =IF(43<0,0,IF(60-(43-0)>0,MIN(AV37+AV38,(AV37+AV38)/MAX(1,60-(43-0))),AV37+AV38)) -> 1.8827676 | AW39: =IF(44<0,0,IF(60-(44-0)>0,MIN(AW37+AW38,(AW37+AW38)/MAX(1,60-(44-0))),AW37+AW38)) -> 1.8827676 | AX39: =IF(45<0,0,IF(60-(45-0)>0,MIN(AX37+AX38,(AX37+AX38)/MAX(1,60-(45-0))),AX37+AX38)) -> 1.8827676 | AY39: =IF(46<0,0,IF(60-(46-0)>0,MIN(AY37+AY38,(AY37+AY38)/MAX(1,60-(46-0))),AY37+AY38)) -> 1.8827676 | AZ39: =IF(47<0,0,IF(60-(47-0)>0,MIN(AZ37+AZ38,(AZ37+AZ38)/MAX(1,60-(47-0))),AZ37+AZ38)) -> 1.8827676 | BA39: =IF(48<0,0,IF(60-(48-0)>0,MIN(BA37+BA38,(BA37+BA38)/MAX(1,60-(48-0))),BA37+BA38)) -> 1.8827676 | BB39: =IF(49<0,0,IF(60-(49-0)>0,MIN(BB37+BB38,(BB37+BB38)/MAX(1,60-(49-0))),BB37+BB38)) -> 1.8827676 | BC39: =IF(50<0,0,IF(60-(50-0)>0,MIN(BC37+BC38,(BC37+BC38)/MAX(1,60-(50-0))),BC37+BC38)) -> 1.7523081 | BD39: =IF(51<0,0,IF(60-(51-0)>0,MIN(BD37+BD38,(BD37+BD38)/MAX(1,60-(51-0))),BD37+BD38)) -> 1.7523081 | BE39: =IF(52<0,0,IF(60-(52-0)>0,MIN(BE37+BE38,(BE37+BE38)/MAX(1,60-(52-0))),BE37+BE38)) -> 1.7523081 | BF39: =IF(53<0,0,IF(60-(53-0)>0,MIN(BF37+BF38,(BF37+BF38)/MAX(1,60-(53-0))),BF37+BF38)) -> 1.7523081 | BG39: =IF(54<0,0,IF(60-(54-0)>0,MIN(BG37+BG38,(BG37+BG38)/MAX(1,60-(54-0))),BG37+BG38)) -> 1.7523081 | BH39: =IF(55<0,0,IF(60-(55-0)>0,MIN(BH37+BH38,(BH37+BH38)/MAX(1,60-(55-0))),BH37+BH38)) -> 1.7523081 | BI39: =IF(56<0,0,IF(60-(56-0)>0,MIN(BI37+BI38,(BI37+BI38)/MAX(1,60-(56-0))),BI37+BI38)) -> 1.7523081 | BJ39: =IF(57<0,0,IF(60-(57-0)>0,MIN(BJ37+BJ38,(BJ37+BJ38)/MAX(1,60-(57-0))),BJ37+BJ38)) -> 1.7523081 | BK39: =IF(58<0,0,IF(60-(58-0)>0,MIN(BK37+BK38,(BK37+BK38)/MAX(1,60-(58-0))),BK37+BK38)) -> 1.7523081 | BL39: =IF(59<0,0,IF(60-(59-0)>0,MIN(BL37+BL38,(BL37+BL38)/MAX(1,60-(59-0))),BL37+BL38)) -> 1.7523081
C40: Pre-sale NBV | E40: =E37+E38-E39 -> 128.77733 | F40: =F37+F38-F39 -> 126.59467 | G40: =G37+G38-G39 -> 121.87164 | H40: =H37+H38-H39 -> 119.5914 | I40: =I37+I38-I39 -> 117.45583 | J40: =J37+J38-J39 -> 115.32027 | K40: =K37+K38-K39 -> 113.18471 | L40: =L37+L38-L39 -> 111.04915 | ... BL40: =BL37+BL38-BL39 -> 0
C41: Allocated disposal NBV | E41: =IF(E91>0,E40/E91*Transfers!E24,0) -> 0 | F41: =IF(F91>0,F40/F91*Transfers!F24,0) -> 2.5849263 | G41: =IF(G91>0,G40/G91*Transfers!G24,0) -> 0.14468542 | H41: =IF(H91>0,H40/H91*Transfers!H24,0) -> 0 | I41: =IF(I91>0,I40/I91*Transfers!I24,0) -> 0 | J41: =IF(J91>0,J40/J91*Transfers!J24,0) -> 0 | K41: =IF(K91>0,K40/K91*Transfers!K24,0) -> 0 | L41: =IF(L91>0,L40/L91*Transfers!L24,0) -> 0 | ... BL41: =IF(BL91>0,BL40/BL91*Transfers!BL24,0) -> 0
C42: Closing NBV | E42: =E40-E41 -> 128.77733 | F42: =F40-F41 -> 124.00974 | G42: =G40-G41 -> 121.72696 | H42: =H40-H41 -> 119.5914 | I42: =I40-I41 -> 117.45583 | J42: =J40-J41 -> 115.32027 | K42: =K40-K41 -> 113.18471 | L42: =L40-L41 -> 111.04915 | ... BL42: =BL40-BL41 -> 0
C43: Known summer additions / extensions
C44: Opening NBV | E44: =0 -> 0 | F44: =E49 -> 0 | G44: =F49 -> 0 | H44: =G49 -> 177.84654 | I44: =H49 -> 174.8322 | J44: =I49 -> 171.81785 | K44: =J49 -> 168.8035 | L44: =K49 -> 165.78915 | M44: =L49 -> 162.7748 | ... BL44: =BK49 -> 7.4201594
C45: Additions | E45: =Transfers!E11 -> 0 | F45: =Transfers!F11 -> 0 | G45: =Transfers!G11 -> 181.07586 | H45: =Transfers!H11 -> 0 | I45: =Transfers!I11 -> 0 | J45: =Transfers!J11 -> 0 | K45: =Transfers!K11 -> 0 | L45: =Transfers!L11 -> 0 | ... BL45: =Transfers!BL11 -> 0
C46: Amortisation | E46: =IF(0<2,0,IF((Assumptions!E88*12)-(0-2)>0,MIN(E44+E45,(E44+E45)/MAX(1,(Assumptions!E88*12)-(0-2))),E44+E45)) -> 0 | F46: =IF(1<2,0,IF((Assumptions!E88*12)-(1-2)>0,MIN(F44+F45,(F44+F45)/MAX(1,(Assumptions!E88*12)-(1-2))),F44+F45)) -> 0 | G46: =IF(2<2,0,IF((Assumptions!E88*12)-(2-2)>0,MIN(G44+G45,(G44+G45)/MAX(1,(Assumptions!E88*12)-(2-2))),G44+G45)) -> 3.0179311 | H46: =IF(3<2,0,IF((Assumptions!E88*12)-(3-2)>0,MIN(H44+H45,(H44+H45)/MAX(1,(Assumptions!E88*12)-(3-2))),H44+H45)) -> 3.0143482 | I46: =IF(4<2,0,IF((Assumptions!E88*12)-(4-2)>0,MIN(I44+I45,(I44+I45)/MAX(1,(Assumptions!E88*12)-(4-2))),I44+I45)) -> 3.0143482 | J46: =IF(5<2,0,IF((Assumptions!E88*12)-(5-2)>0,MIN(J44+J45,(J44+J45)/MAX(1,(Assumptions!E88*12)-(5-2))),J44+J45)) -> 3.0143482 | K46: =IF(6<2,0,IF((Assumptions!E88*12)-(6-2)>0,MIN(K44+K45,(K44+K45)/MAX(1,(Assumptions!E88*12)-(6-2))),K44+K45)) -> 3.0143482 | L46: =IF(7<2,0,IF((Assumptions!E88*12)-(7-2)>0,MIN(L44+L45,(L44+L45)/MAX(1,(Assumptions!E88*12)-(7-2))),L44+L45)) -> 3.0143482 | M46: =IF(8<2,0,IF((Assumptions!E88*12)-(8-2)>0,MIN(M44+M45,(M44+M45)/MAX(1,(Assumptions!E88*12)-(8-2))),M44+M45)) -> 3.0143482 | N46: =IF(9<2,0,IF((Assumptions!E88*12)-(9-2)>0,MIN(N44+N45,(N44+N45)/MAX(1,(Assumptions!E88*12)-(9-2))),N44+N45)) -> 3.0143482 | O46: =IF(10<2,0,IF((Assumptions!E88*12)-(10-2)>0,MIN(O44+O45,(O44+O45)/MAX(1,(Assumptions!E88*12)-(10-2))),O44+O45)) -> 3.0143482 | P46: =IF(11<2,0,IF((Assumptions!E88*12)-(11-2)>0,MIN(P44+P45,(P44+P45)/MAX(1,(Assumptions!E88*12)-(11-2))),P44+P45)) -> 3.0143482 | Q46: =IF(12<2,0,IF((Assumptions!E88*12)-(12-2)>0,MIN(Q44+Q45,(Q44+Q45)/MAX(1,(Assumptions!E88*12)-(12-2))),Q44+Q45)) -> 3.0143482 | R46: =IF(13<2,0,IF((Assumptions!E88*12)-(13-2)>0,MIN(R44+R45,(R44+R45)/MAX(1,(Assumptions!E88*12)-(13-2))),R44+R45)) -> 3.0143482 | S46: =IF(14<2,0,IF((Assumptions!E88*12)-(14-2)>0,MIN(S44+S45,(S44+S45)/MAX(1,(Assumptions!E88*12)-(14-2))),S44+S45)) -> 2.9229757 | T46: =IF(15<2,0,IF((Assumptions!E88*12)-(15-2)>0,MIN(T44+T45,(T44+T45)/MAX(1,(Assumptions!E88*12)-(15-2))),T44+T45)) -> 2.9229757 | U46: =IF(16<2,0,IF((Assumptions!E88*12)-(16-2)>0,MIN(U44+U45,(U44+U45)/MAX(1,(Assumptions!E88*12)-(16-2))),U44+U45)) -> 2.9229757 | V46: =IF(17<2,0,IF((Assumptions!E88*12)-(17-2)>0,MIN(V44+V45,(V44+V45)/MAX(1,(Assumptions!E88*12)-(17-2))),V44+V45)) -> 2.9229757 | W46: =IF(18<2,0,IF((Assumptions!E88*12)-(18-2)>0,MIN(W44+W45,(W44+W45)/MAX(1,(Assumptions!E88*12)-(18-2))),W44+W45)) -> 2.9229757 | X46: =IF(19<2,0,IF((Assumptions!E88*12)-(19-2)>0,MIN(X44+X45,(X44+X45)/MAX(1,(Assumptions!E88*12)-(19-2))),X44+X45)) -> 2.9229757 | Y46: =IF(20<2,0,IF((Assumptions!E88*12)-(20-2)>0,MIN(Y44+Y45,(Y44+Y45)/MAX(1,(Assumptions!E88*12)-(20-2))),Y44+Y45)) -> 2.9229757 | Z46: =IF(21<2,0,IF((Assumptions!E88*12)-(21-2)>0,MIN(Z44+Z45,(Z44+Z45)/MAX(1,(Assumptions!E88*12)-(21-2))),Z44+Z45)) -> 2.9229757 | AA46: =IF(22<2,0,IF((Assumptions!E88*12)-(22-2)>0,MIN(AA44+AA45,(AA44+AA45)/MAX(1,(Assumptions!E88*12)-(22-2))),AA44+AA45)) -> 2.9229757 | AB46: =IF(23<2,0,IF((Assumptions!E88*12)-(23-2)>0,MIN(AB44+AB45,(AB44+AB45)/MAX(1,(Assumptions!E88*12)-(23-2))),AB44+AB45)) -> 2.9229757 | AC46: =IF(24<2,0,IF((Assumptions!E88*12)-(24-2)>0,MIN(AC44+AC45,(AC44+AC45)/MAX(1,(Assumptions!E88*12)-(24-2))),AC44+AC45)) -> 2.9229757 | AD46: =IF(25<2,0,IF((Assumptions!E88*12)-(25-2)>0,MIN(AD44+AD45,(AD44+AD45)/MAX(1,(Assumptions!E88*12)-(25-2))),AD44+AD45)) -> 2.9229757 | AE46: =IF(26<2,0,IF((Assumptions!E88*12)-(26-2)>0,MIN(AE44+AE45,(AE44+AE45)/MAX(1,(Assumptions!E88*12)-(26-2))),AE44+AE45)) -> 2.8061737 | AF46: =IF(27<2,0,IF((Assumptions!E88*12)-(27-2)>0,MIN(AF44+AF45,(AF44+AF45)/MAX(1,(Assumptions!E88*12)-(27-2))),AF44+AF45)) -> 2.8061737 | AG46: =IF(28<2,0,IF((Assumptions!E88*12)-(28-2)>0,MIN(AG44+AG45,(AG44+AG45)/MAX(1,(Assumptions!E88*12)-(28-2))),AG44+AG45)) -> 2.8061737 | AH46: =IF(29<2,0,IF((Assumptions!E88*12)-(29-2)>0,MIN(AH44+AH45,(AH44+AH45)/MAX(1,(Assumptions!E88*12)-(29-2))),AH44+AH45)) -> 2.8061737 | AI46: =IF(30<2,0,IF((Assumptions!E88*12)-(30-2)>0,MIN(AI44+AI45,(AI44+AI45)/MAX(1,(Assumptions!E88*12)-(30-2))),AI44+AI45)) -> 2.8061737 | AJ46: =IF(31<2,0,IF((Assumptions!E88*12)-(31-2)>0,MIN(AJ44+AJ45,(AJ44+AJ45)/MAX(1,(Assumptions!E88*12)-(31-2))),AJ44+AJ45)) -> 2.8061737 | AK46: =IF(32<2,0,IF((Assumptions!E88*12)-(32-2)>0,MIN(AK44+AK45,(AK44+AK45)/MAX(1,(Assumptions!E88*12)-(32-2))),AK44+AK45)) -> 2.8061737 | AL46: =IF(33<2,0,IF((Assumptions!E88*12)-(33-2)>0,MIN(AL44+AL45,(AL44+AL45)/MAX(1,(Assumptions!E88*12)-(33-2))),AL44+AL45)) -> 2.8061737 | AM46: =IF(34<2,0,IF((Assumptions!E88*12)-(34-2)>0,MIN(AM44+AM45,(AM44+AM45)/MAX(1,(Assumptions!E88*12)-(34-2))),AM44+AM45)) -> 2.8061737 | AN46: =IF(35<2,0,IF((Assumptions!E88*12)-(35-2)>0,MIN(AN44+AN45,(AN44+AN45)/MAX(1,(Assumptions!E88*12)-(35-2))),AN44+AN45)) -> 2.8061737 | AO46: =IF(36<2,0,IF((Assumptions!E88*12)-(36-2)>0,MIN(AO44+AO45,(AO44+AO45)/MAX(1,(Assumptions!E88*12)-(36-2))),AO44+AO45)) -> 2.8061737 | AP46: =IF(37<2,0,IF((Assumptions!E88*12)-(37-2)>0,MIN(AP44+AP45,(AP44+AP45)/MAX(1,(Assumptions!E88*12)-(37-2))),AP44+AP45)) -> 2.8061737 | AQ46: =IF(38<2,0,IF((Assumptions!E88*12)-(38-2)>0,MIN(AQ44+AQ45,(AQ44+AQ45)/MAX(1,(Assumptions!E88*12)-(38-2))),AQ44+AQ45)) -> 2.6575303 | AR46: =IF(39<2,0,IF((Assumptions!E88*12)-(39-2)>0,MIN(AR44+AR45,(AR44+AR45)/MAX(1,(Assumptions!E88*12)-(39-2))),AR44+AR45)) -> 2.6575303 | AS46: =IF(40<2,0,IF((Assumptions!E88*12)-(40-2)>0,MIN(AS44+AS45,(AS44+AS45)/MAX(1,(Assumptions!E88*12)-(40-2))),AS44+AS45)) -> 2.6575303 | AT46: =IF(41<2,0,IF((Assumptions!E88*12)-(41-2)>0,MIN(AT44+AT45,(AT44+AT45)/MAX(1,(Assumptions!E88*12)-(41-2))),AT44+AT45)) -> 2.6575303 | AU46: =IF(42<2,0,IF((Assumptions!E88*12)-(42-2)>0,MIN(AU44+AU45,(AU44+AU45)/MAX(1,(Assumptions!E88*12)-(42-2))),AU44+AU45)) -> 2.6575303 | AV46: =IF(43<2,0,IF((Assumptions!E88*12)-(43-2)>0,MIN(AV44+AV45,(AV44+AV45)/MAX(1,(Assumptions!E88*12)-(43-2))),AV44+AV45)) -> 2.6575303 | AW46: =IF(44<2,0,IF((Assumptions!E88*12)-(44-2)>0,MIN(AW44+AW45,(AW44+AW45)/MAX(1,(Assumptions!E88*12)-(44-2))),AW44+AW45)) -> 2.6575303 | AX46: =IF(45<2,0,IF((Assumptions!E88*12)-(45-2)>0,MIN(AX44+AX45,(AX44+AX45)/MAX(1,(Assumptions!E88*12)-(45-2))),AX44+AX45)) -> 2.6575303 | AY46: =IF(46<2,0,IF((Assumptions!E88*12)-(46-2)>0,MIN(AY44+AY45,(AY44+AY45)/MAX(1,(Assumptions!E88*12)-(46-2))),AY44+AY45)) -> 2.6575303 | AZ46: =IF(47<2,0,IF((Assumptions!E88*12)-(47-2)>0,MIN(AZ44+AZ45,(AZ44+AZ45)/MAX(1,(Assumptions!E88*12)-(47-2))),AZ44+AZ45)) -> 2.6575303 | BA46: =IF(48<2,0,IF((Assumptions!E88*12)-(48-2)>0,MIN(BA44+BA45,(BA44+BA45)/MAX(1,(Assumptions!E88*12)-(48-2))),BA44+BA45)) -> 2.6575303 | BB46: =IF(49<2,0,IF((Assumptions!E88*12)-(49-2)>0,MIN(BB44+BB45,(BB44+BB45)/MAX(1,(Assumptions!E88*12)-(49-2))),BB44+BB45)) -> 2.6575303 | BC46: =IF(50<2,0,IF((Assumptions!E88*12)-(50-2)>0,MIN(BC44+BC45,(BC44+BC45)/MAX(1,(Assumptions!E88*12)-(50-2))),BC44+BC45)) -> 2.4733865 | BD46: =IF(51<2,0,IF((Assumptions!E88*12)-(51-2)>0,MIN(BD44+BD45,(BD44+BD45)/MAX(1,(Assumptions!E88*12)-(51-2))),BD44+BD45)) -> 2.4733865 | BE46: =IF(52<2,0,IF((Assumptions!E88*12)-(52-2)>0,MIN(BE44+BE45,(BE44+BE45)/MAX(1,(Assumptions!E88*12)-(52-2))),BE44+BE45)) -> 2.4733865 | BF46: =IF(53<2,0,IF((Assumptions!E88*12)-(53-2)>0,MIN(BF44+BF45,(BF44+BF45)/MAX(1,(Assumptions!E88*12)-(53-2))),BF44+BF45)) -> 2.4733865 | BG46: =IF(54<2,0,IF((Assumptions!E88*12)-(54-2)>0,MIN(BG44+BG45,(BG44+BG45)/MAX(1,(Assumptions!E88*12)-(54-2))),BG44+BG45)) -> 2.4733865 | BH46: =IF(55<2,0,IF((Assumptions!E88*12)-(55-2)>0,MIN(BH44+BH45,(BH44+BH45)/MAX(1,(Assumptions!E88*12)-(55-2))),BH44+BH45)) -> 2.4733865 | BI46: =IF(56<2,0,IF((Assumptions!E88*12)-(56-2)>0,MIN(BI44+BI45,(BI44+BI45)/MAX(1,(Assumptions!E88*12)-(56-2))),BI44+BI45)) -> 2.4733865 | BJ46: =IF(57<2,0,IF((Assumptions!E88*12)-(57-2)>0,MIN(BJ44+BJ45,(BJ44+BJ45)/MAX(1,(Assumptions!E88*12)-(57-2))),BJ44+BJ45)) -> 2.4733865 | BK46: =IF(58<2,0,IF((Assumptions!E88*12)-(58-2)>0,MIN(BK44+BK45,(BK44+BK45)/MAX(1,(Assumptions!E88*12)-(58-2))),BK44+BK45)) -> 2.4733865 | BL46: =IF(59<2,0,IF((Assumptions!E88*12)-(59-2)>0,MIN(BL44+BL45,(BL44+BL45)/MAX(1,(Assumptions!E88*12)-(59-2))),BL44+BL45)) -> 2.4733865
C47: Pre-sale NBV | E47: =E44+E45-E46 -> 0 | F47: =F44+F45-F46 -> 0 | G47: =G44+G45-G46 -> 178.05793 | H47: =H44+H45-H46 -> 174.8322 | I47: =I44+I45-I46 -> 171.81785 | J47: =J44+J45-J46 -> 168.8035 | K47: =K44+K45-K46 -> 165.78915 | L47: =L44+L45-L46 -> 162.7748 | ... BL47: =BL44+BL45-BL46 -> 4.946773
C48: Allocated disposal NBV | E48: =IF(E91>0,E47/E91*Transfers!E24,0) -> 0 | F48: =IF(F91>0,F47/F91*Transfers!F24,0) -> 0 | G48: =IF(G91>0,G47/G91*Transfers!G24,0) -> 0.21138952 | H48: =IF(H91>0,H47/H91*Transfers!H24,0) -> 0 | I48: =IF(I91>0,I47/I91*Transfers!I24,0) -> 0 | J48: =IF(J91>0,J47/J91*Transfers!J24,0) -> 0 | K48: =IF(K91>0,K47/K91*Transfers!K24,0) -> 0 | L48: =IF(L91>0,L47/L91*Transfers!L24,0) -> 0 | ... BL48: =IF(BL91>0,BL47/BL91*Transfers!BL24,0) -> 0
C49: Closing NBV | E49: =E47-E48 -> 0 | F49: =F47-F48 -> 0 | G49: =G47-G48 -> 177.84654 | H49: =H47-H48 -> 174.8322 | I49: =I47-I48 -> 171.81785 | J49: =J47-J48 -> 168.8035 | K49: =K47-K48 -> 165.78915 | L49: =L47-L48 -> 162.7748 | ... BL49: =BL47-BL48 -> 4.946773
C50: FY2027 new investment
C51: Opening NBV | E51: =0 -> 0 | F51: =E56 -> 0 | G51: =F56 -> 0 | H51: =G56 -> 0 | I51: =H56 -> 0 | J51: =I56 -> 0 | K51: =J56 -> 0 | L51: =K56 -> 4.9166667 | M51: =L56 -> 4.8333333 | ... BL51: =BK56 -> 0.47864702
C52: Additions | E52: =Transfers!E10+Transfers!E12 -> 0 | F52: =Transfers!F10+Transfers!F12 -> 0 | G52: =Transfers!G10+Transfers!G12 -> 0 | H52: =Transfers!H10+Transfers!H12 -> 0 | I52: =Transfers!I10+Transfers!I12 -> 0 | J52: =Transfers!J10+Transfers!J12 -> 0 | K52: =Transfers!K10+Transfers!K12 -> 5 | L52: =Transfers!L10+Transfers!L12 -> 0 | ... P52: =Transfers!P10+Transfers!P12 -> 0 | Q52: =0 -> 0 | R52: =0 -> 0 | S52: =0 -> 0 | T52: =0 -> 0 | U52: =0 -> 0 | V52: =0 -> 0 | W52: =0 -> 0 | X52: =0 -> 0 | ... BL52: =0 -> 0
C53: Amortisation | E53: =IF(0<6,0,IF((Assumptions!E83*12)-(0-6)>0,MIN(E51+E52,(E51+E52)/MAX(1,(Assumptions!E83*12)-(0-6))),E51+E52)) -> 0 | F53: =IF(1<6,0,IF((Assumptions!E83*12)-(1-6)>0,MIN(F51+F52,(F51+F52)/MAX(1,(Assumptions!E83*12)-(1-6))),F51+F52)) -> 0 | G53: =IF(2<6,0,IF((Assumptions!E83*12)-(2-6)>0,MIN(G51+G52,(G51+G52)/MAX(1,(Assumptions!E83*12)-(2-6))),G51+G52)) -> 0 | H53: =IF(3<6,0,IF((Assumptions!E83*12)-(3-6)>0,MIN(H51+H52,(H51+H52)/MAX(1,(Assumptions!E83*12)-(3-6))),H51+H52)) -> 0 | I53: =IF(4<6,0,IF((Assumptions!E83*12)-(4-6)>0,MIN(I51+I52,(I51+I52)/MAX(1,(Assumptions!E83*12)-(4-6))),I51+I52)) -> 0 | J53: =IF(5<6,0,IF((Assumptions!E83*12)-(5-6)>0,MIN(J51+J52,(J51+J52)/MAX(1,(Assumptions!E83*12)-(5-6))),J51+J52)) -> 0 | K53: =IF(6<6,0,IF((Assumptions!E83*12)-(6-6)>0,MIN(K51+K52,(K51+K52)/MAX(1,(Assumptions!E83*12)-(6-6))),K51+K52)) -> 0.083333333 | L53: =IF(7<6,0,IF((Assumptions!E83*12)-(7-6)>0,MIN(L51+L52,(L51+L52)/MAX(1,(Assumptions!E83*12)-(7-6))),L51+L52)) -> 0.083333333 | M53: =IF(8<6,0,IF((Assumptions!E83*12)-(8-6)>0,MIN(M51+M52,(M51+M52)/MAX(1,(Assumptions!E83*12)-(8-6))),M51+M52)) -> 0.083333333 | N53: =IF(9<6,0,IF((Assumptions!E83*12)-(9-6)>0,MIN(N51+N52,(N51+N52)/MAX(1,(Assumptions!E83*12)-(9-6))),N51+N52)) -> 0.083333333 | O53: =IF(10<6,0,IF((Assumptions!E83*12)-(10-6)>0,MIN(O51+O52,(O51+O52)/MAX(1,(Assumptions!E83*12)-(10-6))),O51+O52)) -> 0.083333333 | P53: =IF(11<6,0,IF((Assumptions!E83*12)-(11-6)>0,MIN(P51+P52,(P51+P52)/MAX(1,(Assumptions!E83*12)-(11-6))),P51+P52)) -> 0.083333333 | Q53: =IF(12<6,0,IF((Assumptions!E83*12)-(12-6)>0,MIN(Q51+Q52,(Q51+Q52)/MAX(1,(Assumptions!E83*12)-(12-6))),Q51+Q52)) -> 0.083333333 | R53: =IF(13<6,0,IF((Assumptions!E83*12)-(13-6)>0,MIN(R51+R52,(R51+R52)/MAX(1,(Assumptions!E83*12)-(13-6))),R51+R52)) -> 0.083333333 | S53: =IF(14<6,0,IF((Assumptions!E83*12)-(14-6)>0,MIN(S51+S52,(S51+S52)/MAX(1,(Assumptions!E83*12)-(14-6))),S51+S52)) -> 0.080807289 | T53: =IF(15<6,0,IF((Assumptions!E83*12)-(15-6)>0,MIN(T51+T52,(T51+T52)/MAX(1,(Assumptions!E83*12)-(15-6))),T51+T52)) -> 0.080807289 | U53: =IF(16<6,0,IF((Assumptions!E83*12)-(16-6)>0,MIN(U51+U52,(U51+U52)/MAX(1,(Assumptions!E83*12)-(16-6))),U51+U52)) -> 0.080807289 | V53: =IF(17<6,0,IF((Assumptions!E83*12)-(17-6)>0,MIN(V51+V52,(V51+V52)/MAX(1,(Assumptions!E83*12)-(17-6))),V51+V52)) -> 0.080807289 | W53: =IF(18<6,0,IF((Assumptions!E83*12)-(18-6)>0,MIN(W51+W52,(W51+W52)/MAX(1,(Assumptions!E83*12)-(18-6))),W51+W52)) -> 0.080807289 | X53: =IF(19<6,0,IF((Assumptions!E83*12)-(19-6)>0,MIN(X51+X52,(X51+X52)/MAX(1,(Assumptions!E83*12)-(19-6))),X51+X52)) -> 0.080807289 | Y53: =IF(20<6,0,IF((Assumptions!E83*12)-(20-6)>0,MIN(Y51+Y52,(Y51+Y52)/MAX(1,(Assumptions!E83*12)-(20-6))),Y51+Y52)) -> 0.080807289 | Z53: =IF(21<6,0,IF((Assumptions!E83*12)-(21-6)>0,MIN(Z51+Z52,(Z51+Z52)/MAX(1,(Assumptions!E83*12)-(21-6))),Z51+Z52)) -> 0.080807289 | AA53: =IF(22<6,0,IF((Assumptions!E83*12)-(22-6)>0,MIN(AA51+AA52,(AA51+AA52)/MAX(1,(Assumptions!E83*12)-(22-6))),AA51+AA52)) -> 0.080807289 | AB53: =IF(23<6,0,IF((Assumptions!E83*12)-(23-6)>0,MIN(AB51+AB52,(AB51+AB52)/MAX(1,(Assumptions!E83*12)-(23-6))),AB51+AB52)) -> 0.080807289 | AC53: =IF(24<6,0,IF((Assumptions!E83*12)-(24-6)>0,MIN(AC51+AC52,(AC51+AC52)/MAX(1,(Assumptions!E83*12)-(24-6))),AC51+AC52)) -> 0.080807289 | AD53: =IF(25<6,0,IF((Assumptions!E83*12)-(25-6)>0,MIN(AD51+AD52,(AD51+AD52)/MAX(1,(Assumptions!E83*12)-(25-6))),AD51+AD52)) -> 0.080807289 | AE53: =IF(26<6,0,IF((Assumptions!E83*12)-(26-6)>0,MIN(AE51+AE52,(AE51+AE52)/MAX(1,(Assumptions!E83*12)-(26-6))),AE51+AE52)) -> 0.077578233 | AF53: =IF(27<6,0,IF((Assumptions!E83*12)-(27-6)>0,MIN(AF51+AF52,(AF51+AF52)/MAX(1,(Assumptions!E83*12)-(27-6))),AF51+AF52)) -> 0.077578233 | AG53: =IF(28<6,0,IF((Assumptions!E83*12)-(28-6)>0,MIN(AG51+AG52,(AG51+AG52)/MAX(1,(Assumptions!E83*12)-(28-6))),AG51+AG52)) -> 0.077578233 | AH53: =IF(29<6,0,IF((Assumptions!E83*12)-(29-6)>0,MIN(AH51+AH52,(AH51+AH52)/MAX(1,(Assumptions!E83*12)-(29-6))),AH51+AH52)) -> 0.077578233 | AI53: =IF(30<6,0,IF((Assumptions!E83*12)-(30-6)>0,MIN(AI51+AI52,(AI51+AI52)/MAX(1,(Assumptions!E83*12)-(30-6))),AI51+AI52)) -> 0.077578233 | AJ53: =IF(31<6,0,IF((Assumptions!E83*12)-(31-6)>0,MIN(AJ51+AJ52,(AJ51+AJ52)/MAX(1,(Assumptions!E83*12)-(31-6))),AJ51+AJ52)) -> 0.077578233 | AK53: =IF(32<6,0,IF((Assumptions!E83*12)-(32-6)>0,MIN(AK51+AK52,(AK51+AK52)/MAX(1,(Assumptions!E83*12)-(32-6))),AK51+AK52)) -> 0.077578233 | AL53: =IF(33<6,0,IF((Assumptions!E83*12)-(33-6)>0,MIN(AL51+AL52,(AL51+AL52)/MAX(1,(Assumptions!E83*12)-(33-6))),AL51+AL52)) -> 0.077578233 | AM53: =IF(34<6,0,IF((Assumptions!E83*12)-(34-6)>0,MIN(AM51+AM52,(AM51+AM52)/MAX(1,(Assumptions!E83*12)-(34-6))),AM51+AM52)) -> 0.077578233 | AN53: =IF(35<6,0,IF((Assumptions!E83*12)-(35-6)>0,MIN(AN51+AN52,(AN51+AN52)/MAX(1,(Assumptions!E83*12)-(35-6))),AN51+AN52)) -> 0.077578233 | AO53: =IF(36<6,0,IF((Assumptions!E83*12)-(36-6)>0,MIN(AO51+AO52,(AO51+AO52)/MAX(1,(Assumptions!E83*12)-(36-6))),AO51+AO52)) -> 0.077578233 | AP53: =IF(37<6,0,IF((Assumptions!E83*12)-(37-6)>0,MIN(AP51+AP52,(AP51+AP52)/MAX(1,(Assumptions!E83*12)-(37-6))),AP51+AP52)) -> 0.077578233 | AQ53: =IF(38<6,0,IF((Assumptions!E83*12)-(38-6)>0,MIN(AQ51+AQ52,(AQ51+AQ52)/MAX(1,(Assumptions!E83*12)-(38-6))),AQ51+AQ52)) -> 0.073468903 | AR53: =IF(39<6,0,IF((Assumptions!E83*12)-(39-6)>0,MIN(AR51+AR52,(AR51+AR52)/MAX(1,(Assumptions!E83*12)-(39-6))),AR51+AR52)) -> 0.073468903 | AS53: =IF(40<6,0,IF((Assumptions!E83*12)-(40-6)>0,MIN(AS51+AS52,(AS51+AS52)/MAX(1,(Assumptions!E83*12)-(40-6))),AS51+AS52)) -> 0.073468903 | AT53: =IF(41<6,0,IF((Assumptions!E83*12)-(41-6)>0,MIN(AT51+AT52,(AT51+AT52)/MAX(1,(Assumptions!E83*12)-(41-6))),AT51+AT52)) -> 0.073468903 | AU53: =IF(42<6,0,IF((Assumptions!E83*12)-(42-6)>0,MIN(AU51+AU52,(AU51+AU52)/MAX(1,(Assumptions!E83*12)-(42-6))),AU51+AU52)) -> 0.073468903 | AV53: =IF(43<6,0,IF((Assumptions!E83*12)-(43-6)>0,MIN(AV51+AV52,(AV51+AV52)/MAX(1,(Assumptions!E83*12)-(43-6))),AV51+AV52)) -> 0.073468903 | AW53: =IF(44<6,0,IF((Assumptions!E83*12)-(44-6)>0,MIN(AW51+AW52,(AW51+AW52)/MAX(1,(Assumptions!E83*12)-(44-6))),AW51+AW52)) -> 0.073468903 | AX53: =IF(45<6,0,IF((Assumptions!E83*12)-(45-6)>0,MIN(AX51+AX52,(AX51+AX52)/MAX(1,(Assumptions!E83*12)-(45-6))),AX51+AX52)) -> 0.073468903 | AY53: =IF(46<6,0,IF((Assumptions!E83*12)-(46-6)>0,MIN(AY51+AY52,(AY51+AY52)/MAX(1,(Assumptions!E83*12)-(46-6))),AY51+AY52)) -> 0.073468903 | AZ53: =IF(47<6,0,IF((Assumptions!E83*12)-(47-6)>0,MIN(AZ51+AZ52,(AZ51+AZ52)/MAX(1,(Assumptions!E83*12)-(47-6))),AZ51+AZ52)) -> 0.073468903 | BA53: =IF(48<6,0,IF((Assumptions!E83*12)-(48-6)>0,MIN(BA51+BA52,(BA51+BA52)/MAX(1,(Assumptions!E83*12)-(48-6))),BA51+BA52)) -> 0.073468903 | BB53: =IF(49<6,0,IF((Assumptions!E83*12)-(49-6)>0,MIN(BB51+BB52,(BB51+BB52)/MAX(1,(Assumptions!E83*12)-(49-6))),BB51+BB52)) -> 0.073468903 | BC53: =IF(50<6,0,IF((Assumptions!E83*12)-(50-6)>0,MIN(BC51+BC52,(BC51+BC52)/MAX(1,(Assumptions!E83*12)-(50-6))),BC51+BC52)) -> 0.068378146 | BD53: =IF(51<6,0,IF((Assumptions!E83*12)-(51-6)>0,MIN(BD51+BD52,(BD51+BD52)/MAX(1,(Assumptions!E83*12)-(51-6))),BD51+BD52)) -> 0.068378146 | BE53: =IF(52<6,0,IF((Assumptions!E83*12)-(52-6)>0,MIN(BE51+BE52,(BE51+BE52)/MAX(1,(Assumptions!E83*12)-(52-6))),BE51+BE52)) -> 0.068378146 | BF53: =IF(53<6,0,IF((Assumptions!E83*12)-(53-6)>0,MIN(BF51+BF52,(BF51+BF52)/MAX(1,(Assumptions!E83*12)-(53-6))),BF51+BF52)) -> 0.068378146 | BG53: =IF(54<6,0,IF((Assumptions!E83*12)-(54-6)>0,MIN(BG51+BG52,(BG51+BG52)/MAX(1,(Assumptions!E83*12)-(54-6))),BG51+BG52)) -> 0.068378146 | BH53: =IF(55<6,0,IF((Assumptions!E83*12)-(55-6)>0,MIN(BH51+BH52,(BH51+BH52)/MAX(1,(Assumptions!E83*12)-(55-6))),BH51+BH52)) -> 0.068378146 | BI53: =IF(56<6,0,IF((Assumptions!E83*12)-(56-6)>0,MIN(BI51+BI52,(BI51+BI52)/MAX(1,(Assumptions!E83*12)-(56-6))),BI51+BI52)) -> 0.068378146 | BJ53: =IF(57<6,0,IF((Assumptions!E83*12)-(57-6)>0,MIN(BJ51+BJ52,(BJ51+BJ52)/MAX(1,(Assumptions!E83*12)-(57-6))),BJ51+BJ52)) -> 0.068378146 | BK53: =IF(58<6,0,IF((Assumptions!E83*12)-(58-6)>0,MIN(BK51+BK52,(BK51+BK52)/MAX(1,(Assumptions!E83*12)-(58-6))),BK51+BK52)) -> 0.068378146 | BL53: =IF(59<6,0,IF((Assumptions!E83*12)-(59-6)>0,MIN(BL51+BL52,(BL51+BL52)/MAX(1,(Assumptions!E83*12)-(59-6))),BL51+BL52)) -> 0.068378146
C54: Pre-sale NBV | E54: =E51+E52-E53 -> 0 | F54: =F51+F52-F53 -> 0 | G54: =G51+G52-G53 -> 0 | H54: =H51+H52-H53 -> 0 | I54: =I51+I52-I53 -> 0 | J54: =J51+J52-J53 -> 0 | K54: =K51+K52-K53 -> 4.9166667 | L54: =L51+L52-L53 -> 4.8333333 | ... BL54: =BL51+BL52-BL53 -> 0.41026887
C55: Allocated disposal NBV | E55: =IF(E91>0,E54/E91*Transfers!E24,0) -> 0 | F55: =IF(F91>0,F54/F91*Transfers!F24,0) -> 0 | G55: =IF(G91>0,G54/G91*Transfers!G24,0) -> 0 | H55: =IF(H91>0,H54/H91*Transfers!H24,0) -> 0 | I55: =IF(I91>0,I54/I91*Transfers!I24,0) -> 0 | J55: =IF(J91>0,J54/J91*Transfers!J24,0) -> 0 | K55: =IF(K91>0,K54/K91*Transfers!K24,0) -> 0 | L55: =IF(L91>0,L54/L91*Transfers!L24,0) -> 0 | ... BL55: =IF(BL91>0,BL54/BL91*Transfers!BL24,0) -> 0
C56: Closing NBV | E56: =E54-E55 -> 0 | F56: =F54-F55 -> 0 | G56: =G54-G55 -> 0 | H56: =H54-H55 -> 0 | I56: =I54-I55 -> 0 | J56: =J54-J55 -> 0 | K56: =K54-K55 -> 4.9166667 | L56: =L54-L55 -> 4.8333333 | ... BL56: =BL54-BL55 -> 0.41026887
C57: FY2028 new investment
C58: Opening NBV | E58: =0 -> 0 | F58: =E63 -> 0 | G58: =F63 -> 0 | H58: =G63 -> 0 | I58: =H63 -> 0 | J58: =I63 -> 0 | K58: =J63 -> 0 | L58: =K63 -> 0 | M58: =L63 -> 0 | ... BL58: =BK63 -> 11.059934
C59: Additions | E59: =0 -> 0 | F59: =0 -> 0 | G59: =0 -> 0 | H59: =0 -> 0 | I59: =0 -> 0 | J59: =0 -> 0 | K59: =0 -> 0 | L59: =0 -> 0 | ... P59: =0 -> 0 | Q59: =Transfers!Q10+Transfers!Q12 -> 62.210236 | R59: =Transfers!R10+Transfers!R12 -> 0 | S59: =Transfers!S10+Transfers!S12 -> 0 | T59: =Transfers!T10+Transfers!T12 -> 0 | U59: =Transfers!U10+Transfers!U12 -> 0 | V59: =Transfers!V10+Transfers!V12 -> 0 | W59: =Transfers!W10+Transfers!W12 -> 0 | X59: =Transfers!X10+Transfers!X12 -> 0 | ... AB59: =Transfers!AB10+Transfers!AB12 -> 0 | AC59: =0 -> 0 | AD59: =0 -> 0 | AE59: =0 -> 0 | AF59: =0 -> 0 | AG59: =0 -> 0 | AH59: =0 -> 0 | AI59: =0 -> 0 | AJ59: =0 -> 0 | ... BL59: =0 -> 0
C60: Amortisation | E60: =IF(0<12,0,IF((Assumptions!F83*12)-(0-12)>0,MIN(E58+E59,(E58+E59)/MAX(1,(Assumptions!F83*12)-(0-12))),E58+E59)) -> 0 | F60: =IF(1<12,0,IF((Assumptions!F83*12)-(1-12)>0,MIN(F58+F59,(F58+F59)/MAX(1,(Assumptions!F83*12)-(1-12))),F58+F59)) -> 0 | G60: =IF(2<12,0,IF((Assumptions!F83*12)-(2-12)>0,MIN(G58+G59,(G58+G59)/MAX(1,(Assumptions!F83*12)-(2-12))),G58+G59)) -> 0 | H60: =IF(3<12,0,IF((Assumptions!F83*12)-(3-12)>0,MIN(H58+H59,(H58+H59)/MAX(1,(Assumptions!F83*12)-(3-12))),H58+H59)) -> 0 | I60: =IF(4<12,0,IF((Assumptions!F83*12)-(4-12)>0,MIN(I58+I59,(I58+I59)/MAX(1,(Assumptions!F83*12)-(4-12))),I58+I59)) -> 0 | J60: =IF(5<12,0,IF((Assumptions!F83*12)-(5-12)>0,MIN(J58+J59,(J58+J59)/MAX(1,(Assumptions!F83*12)-(5-12))),J58+J59)) -> 0 | K60: =IF(6<12,0,IF((Assumptions!F83*12)-(6-12)>0,MIN(K58+K59,(K58+K59)/MAX(1,(Assumptions!F83*12)-(6-12))),K58+K59)) -> 0 | L60: =IF(7<12,0,IF((Assumptions!F83*12)-(7-12)>0,MIN(L58+L59,(L58+L59)/MAX(1,(Assumptions!F83*12)-(7-12))),L58+L59)) -> 0 | M60: =IF(8<12,0,IF((Assumptions!F83*12)-(8-12)>0,MIN(M58+M59,(M58+M59)/MAX(1,(Assumptions!F83*12)-(8-12))),M58+M59)) -> 0 | N60: =IF(9<12,0,IF((Assumptions!F83*12)-(9-12)>0,MIN(N58+N59,(N58+N59)/MAX(1,(Assumptions!F83*12)-(9-12))),N58+N59)) -> 0 | O60: =IF(10<12,0,IF((Assumptions!F83*12)-(10-12)>0,MIN(O58+O59,(O58+O59)/MAX(1,(Assumptions!F83*12)-(10-12))),O58+O59)) -> 0 | P60: =IF(11<12,0,IF((Assumptions!F83*12)-(11-12)>0,MIN(P58+P59,(P58+P59)/MAX(1,(Assumptions!F83*12)-(11-12))),P58+P59)) -> 0 | Q60: =IF(12<12,0,IF((Assumptions!F83*12)-(12-12)>0,MIN(Q58+Q59,(Q58+Q59)/MAX(1,(Assumptions!F83*12)-(12-12))),Q58+Q59)) -> 1.0368373 | R60: =IF(13<12,0,IF((Assumptions!F83*12)-(13-12)>0,MIN(R58+R59,(R58+R59)/MAX(1,(Assumptions!F83*12)-(13-12))),R58+R59)) -> 1.0368373 | S60: =IF(14<12,0,IF((Assumptions!F83*12)-(14-12)>0,MIN(S58+S59,(S58+S59)/MAX(1,(Assumptions!F83*12)-(14-12))),S58+S59)) -> 1.0054081 | T60: =IF(15<12,0,IF((Assumptions!F83*12)-(15-12)>0,MIN(T58+T59,(T58+T59)/MAX(1,(Assumptions!F83*12)-(15-12))),T58+T59)) -> 1.0054081 | U60: =IF(16<12,0,IF((Assumptions!F83*12)-(16-12)>0,MIN(U58+U59,(U58+U59)/MAX(1,(Assumptions!F83*12)-(16-12))),U58+U59)) -> 1.0054081 | V60: =IF(17<12,0,IF((Assumptions!F83*12)-(17-12)>0,MIN(V58+V59,(V58+V59)/MAX(1,(Assumptions!F83*12)-(17-12))),V58+V59)) -> 1.0054081 | W60: =IF(18<12,0,IF((Assumptions!F83*12)-(18-12)>0,MIN(W58+W59,(W58+W59)/MAX(1,(Assumptions!F83*12)-(18-12))),W58+W59)) -> 1.0054081 | X60: =IF(19<12,0,IF((Assumptions!F83*12)-(19-12)>0,MIN(X58+X59,(X58+X59)/MAX(1,(Assumptions!F83*12)-(19-12))),X58+X59)) -> 1.0054081 | Y60: =IF(20<12,0,IF((Assumptions!F83*12)-(20-12)>0,MIN(Y58+Y59,(Y58+Y59)/MAX(1,(Assumptions!F83*12)-(20-12))),Y58+Y59)) -> 1.0054081 | Z60: =IF(21<12,0,IF((Assumptions!F83*12)-(21-12)>0,MIN(Z58+Z59,(Z58+Z59)/MAX(1,(Assumptions!F83*12)-(21-12))),Z58+Z59)) -> 1.0054081 | AA60: =IF(22<12,0,IF((Assumptions!F83*12)-(22-12)>0,MIN(AA58+AA59,(AA58+AA59)/MAX(1,(Assumptions!F83*12)-(22-12))),AA58+AA59)) -> 1.0054081 | AB60: =IF(23<12,0,IF((Assumptions!F83*12)-(23-12)>0,MIN(AB58+AB59,(AB58+AB59)/MAX(1,(Assumptions!F83*12)-(23-12))),AB58+AB59)) -> 1.0054081 | AC60: =IF(24<12,0,IF((Assumptions!F83*12)-(24-12)>0,MIN(AC58+AC59,(AC58+AC59)/MAX(1,(Assumptions!F83*12)-(24-12))),AC58+AC59)) -> 1.0054081 | AD60: =IF(25<12,0,IF((Assumptions!F83*12)-(25-12)>0,MIN(AD58+AD59,(AD58+AD59)/MAX(1,(Assumptions!F83*12)-(25-12))),AD58+AD59)) -> 1.0054081 | AE60: =IF(26<12,0,IF((Assumptions!F83*12)-(26-12)>0,MIN(AE58+AE59,(AE58+AE59)/MAX(1,(Assumptions!F83*12)-(26-12))),AE58+AE59)) -> 0.96523205 | AF60: =IF(27<12,0,IF((Assumptions!F83*12)-(27-12)>0,MIN(AF58+AF59,(AF58+AF59)/MAX(1,(Assumptions!F83*12)-(27-12))),AF58+AF59)) -> 0.96523205 | AG60: =IF(28<12,0,IF((Assumptions!F83*12)-(28-12)>0,MIN(AG58+AG59,(AG58+AG59)/MAX(1,(Assumptions!F83*12)-(28-12))),AG58+AG59)) -> 0.96523205 | AH60: =IF(29<12,0,IF((Assumptions!F83*12)-(29-12)>0,MIN(AH58+AH59,(AH58+AH59)/MAX(1,(Assumptions!F83*12)-(29-12))),AH58+AH59)) -> 0.96523205 | AI60: =IF(30<12,0,IF((Assumptions!F83*12)-(30-12)>0,MIN(AI58+AI59,(AI58+AI59)/MAX(1,(Assumptions!F83*12)-(30-12))),AI58+AI59)) -> 0.96523205 | AJ60: =IF(31<12,0,IF((Assumptions!F83*12)-(31-12)>0,MIN(AJ58+AJ59,(AJ58+AJ59)/MAX(1,(Assumptions!F83*12)-(31-12))),AJ58+AJ59)) -> 0.96523205 | AK60: =IF(32<12,0,IF((Assumptions!F83*12)-(32-12)>0,MIN(AK58+AK59,(AK58+AK59)/MAX(1,(Assumptions!F83*12)-(32-12))),AK58+AK59)) -> 0.96523205 | AL60: =IF(33<12,0,IF((Assumptions!F83*12)-(33-12)>0,MIN(AL58+AL59,(AL58+AL59)/MAX(1,(Assumptions!F83*12)-(33-12))),AL58+AL59)) -> 0.96523205 | AM60: =IF(34<12,0,IF((Assumptions!F83*12)-(34-12)>0,MIN(AM58+AM59,(AM58+AM59)/MAX(1,(Assumptions!F83*12)-(34-12))),AM58+AM59)) -> 0.96523205 | AN60: =IF(35<12,0,IF((Assumptions!F83*12)-(35-12)>0,MIN(AN58+AN59,(AN58+AN59)/MAX(1,(Assumptions!F83*12)-(35-12))),AN58+AN59)) -> 0.96523205 | AO60: =IF(36<12,0,IF((Assumptions!F83*12)-(36-12)>0,MIN(AO58+AO59,(AO58+AO59)/MAX(1,(Assumptions!F83*12)-(36-12))),AO58+AO59)) -> 0.96523205 | AP60: =IF(37<12,0,IF((Assumptions!F83*12)-(37-12)>0,MIN(AP58+AP59,(AP58+AP59)/MAX(1,(Assumptions!F83*12)-(37-12))),AP58+AP59)) -> 0.96523205 | AQ60: =IF(38<12,0,IF((Assumptions!F83*12)-(38-12)>0,MIN(AQ58+AQ59,(AQ58+AQ59)/MAX(1,(Assumptions!F83*12)-(38-12))),AQ58+AQ59)) -> 0.91410357 | AR60: =IF(39<12,0,IF((Assumptions!F83*12)-(39-12)>0,MIN(AR58+AR59,(AR58+AR59)/MAX(1,(Assumptions!F83*12)-(39-12))),AR58+AR59)) -> 0.91410357 | AS60: =IF(40<12,0,IF((Assumptions!F83*12)-(40-12)>0,MIN(AS58+AS59,(AS58+AS59)/MAX(1,(Assumptions!F83*12)-(40-12))),AS58+AS59)) -> 0.91410357 | AT60: =IF(41<12,0,IF((Assumptions!F83*12)-(41-12)>0,MIN(AT58+AT59,(AT58+AT59)/MAX(1,(Assumptions!F83*12)-(41-12))),AT58+AT59)) -> 0.91410357 | AU60: =IF(42<12,0,IF((Assumptions!F83*12)-(42-12)>0,MIN(AU58+AU59,(AU58+AU59)/MAX(1,(Assumptions!F83*12)-(42-12))),AU58+AU59)) -> 0.91410357 | AV60: =IF(43<12,0,IF((Assumptions!F83*12)-(43-12)>0,MIN(AV58+AV59,(AV58+AV59)/MAX(1,(Assumptions!F83*12)-(43-12))),AV58+AV59)) -> 0.91410357 | AW60: =IF(44<12,0,IF((Assumptions!F83*12)-(44-12)>0,MIN(AW58+AW59,(AW58+AW59)/MAX(1,(Assumptions!F83*12)-(44-12))),AW58+AW59)) -> 0.91410357 | AX60: =IF(45<12,0,IF((Assumptions!F83*12)-(45-12)>0,MIN(AX58+AX59,(AX58+AX59)/MAX(1,(Assumptions!F83*12)-(45-12))),AX58+AX59)) -> 0.91410357 | AY60: =IF(46<12,0,IF((Assumptions!F83*12)-(46-12)>0,MIN(AY58+AY59,(AY58+AY59)/MAX(1,(Assumptions!F83*12)-(46-12))),AY58+AY59)) -> 0.91410357 | AZ60: =IF(47<12,0,IF((Assumptions!F83*12)-(47-12)>0,MIN(AZ58+AZ59,(AZ58+AZ59)/MAX(1,(Assumptions!F83*12)-(47-12))),AZ58+AZ59)) -> 0.91410357 | BA60: =IF(48<12,0,IF((Assumptions!F83*12)-(48-12)>0,MIN(BA58+BA59,(BA58+BA59)/MAX(1,(Assumptions!F83*12)-(48-12))),BA58+BA59)) -> 0.91410357 | BB60: =IF(49<12,0,IF((Assumptions!F83*12)-(49-12)>0,MIN(BB58+BB59,(BB58+BB59)/MAX(1,(Assumptions!F83*12)-(49-12))),BB58+BB59)) -> 0.91410357 | BC60: =IF(50<12,0,IF((Assumptions!F83*12)-(50-12)>0,MIN(BC58+BC59,(BC58+BC59)/MAX(1,(Assumptions!F83*12)-(50-12))),BC58+BC59)) -> 0.85076412 | BD60: =IF(51<12,0,IF((Assumptions!F83*12)-(51-12)>0,MIN(BD58+BD59,(BD58+BD59)/MAX(1,(Assumptions!F83*12)-(51-12))),BD58+BD59)) -> 0.85076412 | BE60: =IF(52<12,0,IF((Assumptions!F83*12)-(52-12)>0,MIN(BE58+BE59,(BE58+BE59)/MAX(1,(Assumptions!F83*12)-(52-12))),BE58+BE59)) -> 0.85076412 | BF60: =IF(53<12,0,IF((Assumptions!F83*12)-(53-12)>0,MIN(BF58+BF59,(BF58+BF59)/MAX(1,(Assumptions!F83*12)-(53-12))),BF58+BF59)) -> 0.85076412 | BG60: =IF(54<12,0,IF((Assumptions!F83*12)-(54-12)>0,MIN(BG58+BG59,(BG58+BG59)/MAX(1,(Assumptions!F83*12)-(54-12))),BG58+BG59)) -> 0.85076412 | BH60: =IF(55<12,0,IF((Assumptions!F83*12)-(55-12)>0,MIN(BH58+BH59,(BH58+BH59)/MAX(1,(Assumptions!F83*12)-(55-12))),BH58+BH59)) -> 0.85076412 | BI60: =IF(56<12,0,IF((Assumptions!F83*12)-(56-12)>0,MIN(BI58+BI59,(BI58+BI59)/MAX(1,(Assumptions!F83*12)-(56-12))),BI58+BI59)) -> 0.85076412 | BJ60: =IF(57<12,0,IF((Assumptions!F83*12)-(57-12)>0,MIN(BJ58+BJ59,(BJ58+BJ59)/MAX(1,(Assumptions!F83*12)-(57-12))),BJ58+BJ59)) -> 0.85076412 | BK60: =IF(58<12,0,IF((Assumptions!F83*12)-(58-12)>0,MIN(BK58+BK59,(BK58+BK59)/MAX(1,(Assumptions!F83*12)-(58-12))),BK58+BK59)) -> 0.85076412 | BL60: =IF(59<12,0,IF((Assumptions!F83*12)-(59-12)>0,MIN(BL58+BL59,(BL58+BL59)/MAX(1,(Assumptions!F83*12)-(59-12))),BL58+BL59)) -> 0.85076412
C61: Pre-sale NBV | E61: =E58+E59-E60 -> 0 | F61: =F58+F59-F60 -> 0 | G61: =G58+G59-G60 -> 0 | H61: =H58+H59-H60 -> 0 | I61: =I58+I59-I60 -> 0 | J61: =J58+J59-J60 -> 0 | K61: =K58+K59-K60 -> 0 | L61: =L58+L59-L60 -> 0 | ... BL61: =BL58+BL59-BL60 -> 10.209169
C62: Allocated disposal NBV | E62: =IF(E91>0,E61/E91*Transfers!E24,0) -> 0 | F62: =IF(F91>0,F61/F91*Transfers!F24,0) -> 0 | G62: =IF(G91>0,G61/G91*Transfers!G24,0) -> 0 | H62: =IF(H91>0,H61/H91*Transfers!H24,0) -> 0 | I62: =IF(I91>0,I61/I91*Transfers!I24,0) -> 0 | J62: =IF(J91>0,J61/J91*Transfers!J24,0) -> 0 | K62: =IF(K91>0,K61/K91*Transfers!K24,0) -> 0 | L62: =IF(L91>0,L61/L91*Transfers!L24,0) -> 0 | ... BL62: =IF(BL91>0,BL61/BL91*Transfers!BL24,0) -> 0
C63: Closing NBV | E63: =E61-E62 -> 0 | F63: =F61-F62 -> 0 | G63: =G61-G62 -> 0 | H63: =H61-H62 -> 0 | I63: =I61-I62 -> 0 | J63: =J61-J62 -> 0 | K63: =K61-K62 -> 0 | L63: =L61-L62 -> 0 | ... BL63: =BL61-BL62 -> 10.209169
C64: FY2029 new investment
C65: Opening NBV | E65: =0 -> 0 | F65: =E70 -> 0 | G65: =F70 -> 0 | H65: =G70 -> 0 | I65: =H70 -> 0 | J65: =I70 -> 0 | K65: =J70 -> 0 | L65: =K70 -> 0 | M65: =L70 -> 0 | ... BL65: =BK70 -> 21.933977
C66: Additions | E66: =0 -> 0 | F66: =0 -> 0 | G66: =0 -> 0 | H66: =0 -> 0 | I66: =0 -> 0 | J66: =0 -> 0 | K66: =0 -> 0 | L66: =0 -> 0 | ... AB66: =0 -> 0 | AC66: =Transfers!AC10+Transfers!AC12 -> 62.210236 | AD66: =Transfers!AD10+Transfers!AD12 -> 0 | AE66: =Transfers!AE10+Transfers!AE12 -> 0 | AF66: =Transfers!AF10+Transfers!AF12 -> 0 | AG66: =Transfers!AG10+Transfers!AG12 -> 0 | AH66: =Transfers!AH10+Transfers!AH12 -> 0 | AI66: =Transfers!AI10+Transfers!AI12 -> 0 | AJ66: =Transfers!AJ10+Transfers!AJ12 -> 0 | ... AN66: =Transfers!AN10+Transfers!AN12 -> 0 | AO66: =0 -> 0 | AP66: =0 -> 0 | AQ66: =0 -> 0 | AR66: =0 -> 0 | AS66: =0 -> 0 | AT66: =0 -> 0 | AU66: =0 -> 0 | AV66: =0 -> 0 | ... BL66: =0 -> 0
C67: Amortisation | E67: =IF(0<24,0,IF((Assumptions!G83*12)-(0-24)>0,MIN(E65+E66,(E65+E66)/MAX(1,(Assumptions!G83*12)-(0-24))),E65+E66)) -> 0 | F67: =IF(1<24,0,IF((Assumptions!G83*12)-(1-24)>0,MIN(F65+F66,(F65+F66)/MAX(1,(Assumptions!G83*12)-(1-24))),F65+F66)) -> 0 | G67: =IF(2<24,0,IF((Assumptions!G83*12)-(2-24)>0,MIN(G65+G66,(G65+G66)/MAX(1,(Assumptions!G83*12)-(2-24))),G65+G66)) -> 0 | H67: =IF(3<24,0,IF((Assumptions!G83*12)-(3-24)>0,MIN(H65+H66,(H65+H66)/MAX(1,(Assumptions!G83*12)-(3-24))),H65+H66)) -> 0 | I67: =IF(4<24,0,IF((Assumptions!G83*12)-(4-24)>0,MIN(I65+I66,(I65+I66)/MAX(1,(Assumptions!G83*12)-(4-24))),I65+I66)) -> 0 | J67: =IF(5<24,0,IF((Assumptions!G83*12)-(5-24)>0,MIN(J65+J66,(J65+J66)/MAX(1,(Assumptions!G83*12)-(5-24))),J65+J66)) -> 0 | K67: =IF(6<24,0,IF((Assumptions!G83*12)-(6-24)>0,MIN(K65+K66,(K65+K66)/MAX(1,(Assumptions!G83*12)-(6-24))),K65+K66)) -> 0 | L67: =IF(7<24,0,IF((Assumptions!G83*12)-(7-24)>0,MIN(L65+L66,(L65+L66)/MAX(1,(Assumptions!G83*12)-(7-24))),L65+L66)) -> 0 | M67: =IF(8<24,0,IF((Assumptions!G83*12)-(8-24)>0,MIN(M65+M66,(M65+M66)/MAX(1,(Assumptions!G83*12)-(8-24))),M65+M66)) -> 0 | N67: =IF(9<24,0,IF((Assumptions!G83*12)-(9-24)>0,MIN(N65+N66,(N65+N66)/MAX(1,(Assumptions!G83*12)-(9-24))),N65+N66)) -> 0 | O67: =IF(10<24,0,IF((Assumptions!G83*12)-(10-24)>0,MIN(O65+O66,(O65+O66)/MAX(1,(Assumptions!G83*12)-(10-24))),O65+O66)) -> 0 | P67: =IF(11<24,0,IF((Assumptions!G83*12)-(11-24)>0,MIN(P65+P66,(P65+P66)/MAX(1,(Assumptions!G83*12)-(11-24))),P65+P66)) -> 0 | Q67: =IF(12<24,0,IF((Assumptions!G83*12)-(12-24)>0,MIN(Q65+Q66,(Q65+Q66)/MAX(1,(Assumptions!G83*12)-(12-24))),Q65+Q66)) -> 0 | R67: =IF(13<24,0,IF((Assumptions!G83*12)-(13-24)>0,MIN(R65+R66,(R65+R66)/MAX(1,(Assumptions!G83*12)-(13-24))),R65+R66)) -> 0 | S67: =IF(14<24,0,IF((Assumptions!G83*12)-(14-24)>0,MIN(S65+S66,(S65+S66)/MAX(1,(Assumptions!G83*12)-(14-24))),S65+S66)) -> 0 | T67: =IF(15<24,0,IF((Assumptions!G83*12)-(15-24)>0,MIN(T65+T66,(T65+T66)/MAX(1,(Assumptions!G83*12)-(15-24))),T65+T66)) -> 0 | U67: =IF(16<24,0,IF((Assumptions!G83*12)-(16-24)>0,MIN(U65+U66,(U65+U66)/MAX(1,(Assumptions!G83*12)-(16-24))),U65+U66)) -> 0 | V67: =IF(17<24,0,IF((Assumptions!G83*12)-(17-24)>0,MIN(V65+V66,(V65+V66)/MAX(1,(Assumptions!G83*12)-(17-24))),V65+V66)) -> 0 | W67: =IF(18<24,0,IF((Assumptions!G83*12)-(18-24)>0,MIN(W65+W66,(W65+W66)/MAX(1,(Assumptions!G83*12)-(18-24))),W65+W66)) -> 0 | X67: =IF(19<24,0,IF((Assumptions!G83*12)-(19-24)>0,MIN(X65+X66,(X65+X66)/MAX(1,(Assumptions!G83*12)-(19-24))),X65+X66)) -> 0 | Y67: =IF(20<24,0,IF((Assumptions!G83*12)-(20-24)>0,MIN(Y65+Y66,(Y65+Y66)/MAX(1,(Assumptions!G83*12)-(20-24))),Y65+Y66)) -> 0 | Z67: =IF(21<24,0,IF((Assumptions!G83*12)-(21-24)>0,MIN(Z65+Z66,(Z65+Z66)/MAX(1,(Assumptions!G83*12)-(21-24))),Z65+Z66)) -> 0 | AA67: =IF(22<24,0,IF((Assumptions!G83*12)-(22-24)>0,MIN(AA65+AA66,(AA65+AA66)/MAX(1,(Assumptions!G83*12)-(22-24))),AA65+AA66)) -> 0 | AB67: =IF(23<24,0,IF((Assumptions!G83*12)-(23-24)>0,MIN(AB65+AB66,(AB65+AB66)/MAX(1,(Assumptions!G83*12)-(23-24))),AB65+AB66)) -> 0 | AC67: =IF(24<24,0,IF((Assumptions!G83*12)-(24-24)>0,MIN(AC65+AC66,(AC65+AC66)/MAX(1,(Assumptions!G83*12)-(24-24))),AC65+AC66)) -> 1.0368373 | AD67: =IF(25<24,0,IF((Assumptions!G83*12)-(25-24)>0,MIN(AD65+AD66,(AD65+AD66)/MAX(1,(Assumptions!G83*12)-(25-24))),AD65+AD66)) -> 1.0368373 | AE67: =IF(26<24,0,IF((Assumptions!G83*12)-(26-24)>0,MIN(AE65+AE66,(AE65+AE66)/MAX(1,(Assumptions!G83*12)-(26-24))),AE65+AE66)) -> 0.9954053 | AF67: =IF(27<24,0,IF((Assumptions!G83*12)-(27-24)>0,MIN(AF65+AF66,(AF65+AF66)/MAX(1,(Assumptions!G83*12)-(27-24))),AF65+AF66)) -> 0.9954053 | AG67: =IF(28<24,0,IF((Assumptions!G83*12)-(28-24)>0,MIN(AG65+AG66,(AG65+AG66)/MAX(1,(Assumptions!G83*12)-(28-24))),AG65+AG66)) -> 0.9954053 | AH67: =IF(29<24,0,IF((Assumptions!G83*12)-(29-24)>0,MIN(AH65+AH66,(AH65+AH66)/MAX(1,(Assumptions!G83*12)-(29-24))),AH65+AH66)) -> 0.9954053 | AI67: =IF(30<24,0,IF((Assumptions!G83*12)-(30-24)>0,MIN(AI65+AI66,(AI65+AI66)/MAX(1,(Assumptions!G83*12)-(30-24))),AI65+AI66)) -> 0.9954053 | AJ67: =IF(31<24,0,IF((Assumptions!G83*12)-(31-24)>0,MIN(AJ65+AJ66,(AJ65+AJ66)/MAX(1,(Assumptions!G83*12)-(31-24))),AJ65+AJ66)) -> 0.9954053 | AK67: =IF(32<24,0,IF((Assumptions!G83*12)-(32-24)>0,MIN(AK65+AK66,(AK65+AK66)/MAX(1,(Assumptions!G83*12)-(32-24))),AK65+AK66)) -> 0.9954053 | AL67: =IF(33<24,0,IF((Assumptions!G83*12)-(33-24)>0,MIN(AL65+AL66,(AL65+AL66)/MAX(1,(Assumptions!G83*12)-(33-24))),AL65+AL66)) -> 0.9954053 | AM67: =IF(34<24,0,IF((Assumptions!G83*12)-(34-24)>0,MIN(AM65+AM66,(AM65+AM66)/MAX(1,(Assumptions!G83*12)-(34-24))),AM65+AM66)) -> 0.9954053 | AN67: =IF(35<24,0,IF((Assumptions!G83*12)-(35-24)>0,MIN(AN65+AN66,(AN65+AN66)/MAX(1,(Assumptions!G83*12)-(35-24))),AN65+AN66)) -> 0.9954053 | AO67: =IF(36<24,0,IF((Assumptions!G83*12)-(36-24)>0,MIN(AO65+AO66,(AO65+AO66)/MAX(1,(Assumptions!G83*12)-(36-24))),AO65+AO66)) -> 0.9954053 | AP67: =IF(37<24,0,IF((Assumptions!G83*12)-(37-24)>0,MIN(AP65+AP66,(AP65+AP66)/MAX(1,(Assumptions!G83*12)-(37-24))),AP65+AP66)) -> 0.9954053 | AQ67: =IF(38<24,0,IF((Assumptions!G83*12)-(38-24)>0,MIN(AQ65+AQ66,(AQ65+AQ66)/MAX(1,(Assumptions!G83*12)-(38-24))),AQ65+AQ66)) -> 0.94267854 | AR67: =IF(39<24,0,IF((Assumptions!G83*12)-(39-24)>0,MIN(AR65+AR66,(AR65+AR66)/MAX(1,(Assumptions!G83*12)-(39-24))),AR65+AR66)) -> 0.94267854 | AS67: =IF(40<24,0,IF((Assumptions!G83*12)-(40-24)>0,MIN(AS65+AS66,(AS65+AS66)/MAX(1,(Assumptions!G83*12)-(40-24))),AS65+AS66)) -> 0.94267854 | AT67: =IF(41<24,0,IF((Assumptions!G83*12)-(41-24)>0,MIN(AT65+AT66,(AT65+AT66)/MAX(1,(Assumptions!G83*12)-(41-24))),AT65+AT66)) -> 0.94267854 | AU67: =IF(42<24,0,IF((Assumptions!G83*12)-(42-24)>0,MIN(AU65+AU66,(AU65+AU66)/MAX(1,(Assumptions!G83*12)-(42-24))),AU65+AU66)) -> 0.94267854 | AV67: =IF(43<24,0,IF((Assumptions!G83*12)-(43-24)>0,MIN(AV65+AV66,(AV65+AV66)/MAX(1,(Assumptions!G83*12)-(43-24))),AV65+AV66)) -> 0.94267854 | AW67: =IF(44<24,0,IF((Assumptions!G83*12)-(44-24)>0,MIN(AW65+AW66,(AW65+AW66)/MAX(1,(Assumptions!G83*12)-(44-24))),AW65+AW66)) -> 0.94267854 | AX67: =IF(45<24,0,IF((Assumptions!G83*12)-(45-24)>0,MIN(AX65+AX66,(AX65+AX66)/MAX(1,(Assumptions!G83*12)-(45-24))),AX65+AX66)) -> 0.94267854 | AY67: =IF(46<24,0,IF((Assumptions!G83*12)-(46-24)>0,MIN(AY65+AY66,(AY65+AY66)/MAX(1,(Assumptions!G83*12)-(46-24))),AY65+AY66)) -> 0.94267854 | AZ67: =IF(47<24,0,IF((Assumptions!G83*12)-(47-24)>0,MIN(AZ65+AZ66,(AZ65+AZ66)/MAX(1,(Assumptions!G83*12)-(47-24))),AZ65+AZ66)) -> 0.94267854 | BA67: =IF(48<24,0,IF((Assumptions!G83*12)-(48-24)>0,MIN(BA65+BA66,(BA65+BA66)/MAX(1,(Assumptions!G83*12)-(48-24))),BA65+BA66)) -> 0.94267854 | BB67: =IF(49<24,0,IF((Assumptions!G83*12)-(49-24)>0,MIN(BB65+BB66,(BB65+BB66)/MAX(1,(Assumptions!G83*12)-(49-24))),BB65+BB66)) -> 0.94267854 | BC67: =IF(50<24,0,IF((Assumptions!G83*12)-(50-24)>0,MIN(BC65+BC66,(BC65+BC66)/MAX(1,(Assumptions!G83*12)-(50-24))),BC65+BC66)) -> 0.87735909 | BD67: =IF(51<24,0,IF((Assumptions!G83*12)-(51-24)>0,MIN(BD65+BD66,(BD65+BD66)/MAX(1,(Assumptions!G83*12)-(51-24))),BD65+BD66)) -> 0.87735909 | BE67: =IF(52<24,0,IF((Assumptions!G83*12)-(52-24)>0,MIN(BE65+BE66,(BE65+BE66)/MAX(1,(Assumptions!G83*12)-(52-24))),BE65+BE66)) -> 0.87735909 | BF67: =IF(53<24,0,IF((Assumptions!G83*12)-(53-24)>0,MIN(BF65+BF66,(BF65+BF66)/MAX(1,(Assumptions!G83*12)-(53-24))),BF65+BF66)) -> 0.87735909 | BG67: =IF(54<24,0,IF((Assumptions!G83*12)-(54-24)>0,MIN(BG65+BG66,(BG65+BG66)/MAX(1,(Assumptions!G83*12)-(54-24))),BG65+BG66)) -> 0.87735909 | BH67: =IF(55<24,0,IF((Assumptions!G83*12)-(55-24)>0,MIN(BH65+BH66,(BH65+BH66)/MAX(1,(Assumptions!G83*12)-(55-24))),BH65+BH66)) -> 0.87735909 | BI67: =IF(56<24,0,IF((Assumptions!G83*12)-(56-24)>0,MIN(BI65+BI66,(BI65+BI66)/MAX(1,(Assumptions!G83*12)-(56-24))),BI65+BI66)) -> 0.87735909 | BJ67: =IF(57<24,0,IF((Assumptions!G83*12)-(57-24)>0,MIN(BJ65+BJ66,(BJ65+BJ66)/MAX(1,(Assumptions!G83*12)-(57-24))),BJ65+BJ66)) -> 0.87735909 | BK67: =IF(58<24,0,IF((Assumptions!G83*12)-(58-24)>0,MIN(BK65+BK66,(BK65+BK66)/MAX(1,(Assumptions!G83*12)-(58-24))),BK65+BK66)) -> 0.87735909 | BL67: =IF(59<24,0,IF((Assumptions!G83*12)-(59-24)>0,MIN(BL65+BL66,(BL65+BL66)/MAX(1,(Assumptions!G83*12)-(59-24))),BL65+BL66)) -> 0.87735909
C68: Pre-sale NBV | E68: =E65+E66-E67 -> 0 | F68: =F65+F66-F67 -> 0 | G68: =G65+G66-G67 -> 0 | H68: =H65+H66-H67 -> 0 | I68: =I65+I66-I67 -> 0 | J68: =J65+J66-J67 -> 0 | K68: =K65+K66-K67 -> 0 | L68: =L65+L66-L67 -> 0 | ... BL68: =BL65+BL66-BL67 -> 21.056618
C69: Allocated disposal NBV | E69: =IF(E91>0,E68/E91*Transfers!E24,0) -> 0 | F69: =IF(F91>0,F68/F91*Transfers!F24,0) -> 0 | G69: =IF(G91>0,G68/G91*Transfers!G24,0) -> 0 | H69: =IF(H91>0,H68/H91*Transfers!H24,0) -> 0 | I69: =IF(I91>0,I68/I91*Transfers!I24,0) -> 0 | J69: =IF(J91>0,J68/J91*Transfers!J24,0) -> 0 | K69: =IF(K91>0,K68/K91*Transfers!K24,0) -> 0 | L69: =IF(L91>0,L68/L91*Transfers!L24,0) -> 0 | ... BL69: =IF(BL91>0,BL68/BL91*Transfers!BL24,0) -> 0
C70: Closing NBV | E70: =E68-E69 -> 0 | F70: =F68-F69 -> 0 | G70: =G68-G69 -> 0 | H70: =H68-H69 -> 0 | I70: =I68-I69 -> 0 | J70: =J68-J69 -> 0 | K70: =K68-K69 -> 0 | L70: =L68-L69 -> 0 | ... BL70: =BL68-BL69 -> 21.056618
C71: FY2030 new investment
C72: Opening NBV | E72: =0 -> 0 | F72: =E77 -> 0 | G72: =F77 -> 0 | H72: =G77 -> 0 | I72: =H77 -> 0 | J72: =I77 -> 0 | K72: =J77 -> 0 | L72: =K77 -> 0 | M72: =L77 -> 0 | ... BL72: =BK77 -> 33.813471
C73: Additions | E73: =0 -> 0 | F73: =0 -> 0 | G73: =0 -> 0 | H73: =0 -> 0 | I73: =0 -> 0 | J73: =0 -> 0 | K73: =0 -> 0 | L73: =0 -> 0 | ... AN73: =0 -> 0 | AO73: =Transfers!AO10+Transfers!AO12 -> 62.210236 | AP73: =Transfers!AP10+Transfers!AP12 -> 0 | AQ73: =Transfers!AQ10+Transfers!AQ12 -> 0 | AR73: =Transfers!AR10+Transfers!AR12 -> 0 | AS73: =Transfers!AS10+Transfers!AS12 -> 0 | AT73: =Transfers!AT10+Transfers!AT12 -> 0 | AU73: =Transfers!AU10+Transfers!AU12 -> 0 | AV73: =Transfers!AV10+Transfers!AV12 -> 0 | ... AZ73: =Transfers!AZ10+Transfers!AZ12 -> 0 | BA73: =0 -> 0 | BB73: =0 -> 0 | BC73: =0 -> 0 | BD73: =0 -> 0 | BE73: =0 -> 0 | BF73: =0 -> 0 | BG73: =0 -> 0 | BH73: =0 -> 0 | ... BL73: =0 -> 0
C74: Amortisation | E74: =IF(0<36,0,IF((Assumptions!H83*12)-(0-36)>0,MIN(E72+E73,(E72+E73)/MAX(1,(Assumptions!H83*12)-(0-36))),E72+E73)) -> 0 | F74: =IF(1<36,0,IF((Assumptions!H83*12)-(1-36)>0,MIN(F72+F73,(F72+F73)/MAX(1,(Assumptions!H83*12)-(1-36))),F72+F73)) -> 0 | G74: =IF(2<36,0,IF((Assumptions!H83*12)-(2-36)>0,MIN(G72+G73,(G72+G73)/MAX(1,(Assumptions!H83*12)-(2-36))),G72+G73)) -> 0 | H74: =IF(3<36,0,IF((Assumptions!H83*12)-(3-36)>0,MIN(H72+H73,(H72+H73)/MAX(1,(Assumptions!H83*12)-(3-36))),H72+H73)) -> 0 | I74: =IF(4<36,0,IF((Assumptions!H83*12)-(4-36)>0,MIN(I72+I73,(I72+I73)/MAX(1,(Assumptions!H83*12)-(4-36))),I72+I73)) -> 0 | J74: =IF(5<36,0,IF((Assumptions!H83*12)-(5-36)>0,MIN(J72+J73,(J72+J73)/MAX(1,(Assumptions!H83*12)-(5-36))),J72+J73)) -> 0 | K74: =IF(6<36,0,IF((Assumptions!H83*12)-(6-36)>0,MIN(K72+K73,(K72+K73)/MAX(1,(Assumptions!H83*12)-(6-36))),K72+K73)) -> 0 | L74: =IF(7<36,0,IF((Assumptions!H83*12)-(7-36)>0,MIN(L72+L73,(L72+L73)/MAX(1,(Assumptions!H83*12)-(7-36))),L72+L73)) -> 0 | M74: =IF(8<36,0,IF((Assumptions!H83*12)-(8-36)>0,MIN(M72+M73,(M72+M73)/MAX(1,(Assumptions!H83*12)-(8-36))),M72+M73)) -> 0 | N74: =IF(9<36,0,IF((Assumptions!H83*12)-(9-36)>0,MIN(N72+N73,(N72+N73)/MAX(1,(Assumptions!H83*12)-(9-36))),N72+N73)) -> 0 | O74: =IF(10<36,0,IF((Assumptions!H83*12)-(10-36)>0,MIN(O72+O73,(O72+O73)/MAX(1,(Assumptions!H83*12)-(10-36))),O72+O73)) -> 0 | P74: =IF(11<36,0,IF((Assumptions!H83*12)-(11-36)>0,MIN(P72+P73,(P72+P73)/MAX(1,(Assumptions!H83*12)-(11-36))),P72+P73)) -> 0 | Q74: =IF(12<36,0,IF((Assumptions!H83*12)-(12-36)>0,MIN(Q72+Q73,(Q72+Q73)/MAX(1,(Assumptions!H83*12)-(12-36))),Q72+Q73)) -> 0 | R74: =IF(13<36,0,IF((Assumptions!H83*12)-(13-36)>0,MIN(R72+R73,(R72+R73)/MAX(1,(Assumptions!H83*12)-(13-36))),R72+R73)) -> 0 | S74: =IF(14<36,0,IF((Assumptions!H83*12)-(14-36)>0,MIN(S72+S73,(S72+S73)/MAX(1,(Assumptions!H83*12)-(14-36))),S72+S73)) -> 0 | T74: =IF(15<36,0,IF((Assumptions!H83*12)-(15-36)>0,MIN(T72+T73,(T72+T73)/MAX(1,(Assumptions!H83*12)-(15-36))),T72+T73)) -> 0 | U74: =IF(16<36,0,IF((Assumptions!H83*12)-(16-36)>0,MIN(U72+U73,(U72+U73)/MAX(1,(Assumptions!H83*12)-(16-36))),U72+U73)) -> 0 | V74: =IF(17<36,0,IF((Assumptions!H83*12)-(17-36)>0,MIN(V72+V73,(V72+V73)/MAX(1,(Assumptions!H83*12)-(17-36))),V72+V73)) -> 0 | W74: =IF(18<36,0,IF((Assumptions!H83*12)-(18-36)>0,MIN(W72+W73,(W72+W73)/MAX(1,(Assumptions!H83*12)-(18-36))),W72+W73)) -> 0 | X74: =IF(19<36,0,IF((Assumptions!H83*12)-(19-36)>0,MIN(X72+X73,(X72+X73)/MAX(1,(Assumptions!H83*12)-(19-36))),X72+X73)) -> 0 | Y74: =IF(20<36,0,IF((Assumptions!H83*12)-(20-36)>0,MIN(Y72+Y73,(Y72+Y73)/MAX(1,(Assumptions!H83*12)-(20-36))),Y72+Y73)) -> 0 | Z74: =IF(21<36,0,IF((Assumptions!H83*12)-(21-36)>0,MIN(Z72+Z73,(Z72+Z73)/MAX(1,(Assumptions!H83*12)-(21-36))),Z72+Z73)) -> 0 | AA74: =IF(22<36,0,IF((Assumptions!H83*12)-(22-36)>0,MIN(AA72+AA73,(AA72+AA73)/MAX(1,(Assumptions!H83*12)-(22-36))),AA72+AA73)) -> 0 | AB74: =IF(23<36,0,IF((Assumptions!H83*12)-(23-36)>0,MIN(AB72+AB73,(AB72+AB73)/MAX(1,(Assumptions!H83*12)-(23-36))),AB72+AB73)) -> 0 | AC74: =IF(24<36,0,IF((Assumptions!H83*12)-(24-36)>0,MIN(AC72+AC73,(AC72+AC73)/MAX(1,(Assumptions!H83*12)-(24-36))),AC72+AC73)) -> 0 | AD74: =IF(25<36,0,IF((Assumptions!H83*12)-(25-36)>0,MIN(AD72+AD73,(AD72+AD73)/MAX(1,(Assumptions!H83*12)-(25-36))),AD72+AD73)) -> 0 | AE74: =IF(26<36,0,IF((Assumptions!H83*12)-(26-36)>0,MIN(AE72+AE73,(AE72+AE73)/MAX(1,(Assumptions!H83*12)-(26-36))),AE72+AE73)) -> 0 | AF74: =IF(27<36,0,IF((Assumptions!H83*12)-(27-36)>0,MIN(AF72+AF73,(AF72+AF73)/MAX(1,(Assumptions!H83*12)-(27-36))),AF72+AF73)) -> 0 | AG74: =IF(28<36,0,IF((Assumptions!H83*12)-(28-36)>0,MIN(AG72+AG73,(AG72+AG73)/MAX(1,(Assumptions!H83*12)-(28-36))),AG72+AG73)) -> 0 | AH74: =IF(29<36,0,IF((Assumptions!H83*12)-(29-36)>0,MIN(AH72+AH73,(AH72+AH73)/MAX(1,(Assumptions!H83*12)-(29-36))),AH72+AH73)) -> 0 | AI74: =IF(30<36,0,IF((Assumptions!H83*12)-(30-36)>0,MIN(AI72+AI73,(AI72+AI73)/MAX(1,(Assumptions!H83*12)-(30-36))),AI72+AI73)) -> 0 | AJ74: =IF(31<36,0,IF((Assumptions!H83*12)-(31-36)>0,MIN(AJ72+AJ73,(AJ72+AJ73)/MAX(1,(Assumptions!H83*12)-(31-36))),AJ72+AJ73)) -> 0 | AK74: =IF(32<36,0,IF((Assumptions!H83*12)-(32-36)>0,MIN(AK72+AK73,(AK72+AK73)/MAX(1,(Assumptions!H83*12)-(32-36))),AK72+AK73)) -> 0 | AL74: =IF(33<36,0,IF((Assumptions!H83*12)-(33-36)>0,MIN(AL72+AL73,(AL72+AL73)/MAX(1,(Assumptions!H83*12)-(33-36))),AL72+AL73)) -> 0 | AM74: =IF(34<36,0,IF((Assumptions!H83*12)-(34-36)>0,MIN(AM72+AM73,(AM72+AM73)/MAX(1,(Assumptions!H83*12)-(34-36))),AM72+AM73)) -> 0 | AN74: =IF(35<36,0,IF((Assumptions!H83*12)-(35-36)>0,MIN(AN72+AN73,(AN72+AN73)/MAX(1,(Assumptions!H83*12)-(35-36))),AN72+AN73)) -> 0 | AO74: =IF(36<36,0,IF((Assumptions!H83*12)-(36-36)>0,MIN(AO72+AO73,(AO72+AO73)/MAX(1,(Assumptions!H83*12)-(36-36))),AO72+AO73)) -> 1.0368373 | AP74: =IF(37<36,0,IF((Assumptions!H83*12)-(37-36)>0,MIN(AP72+AP73,(AP72+AP73)/MAX(1,(Assumptions!H83*12)-(37-36))),AP72+AP73)) -> 1.0368373 | AQ74: =IF(38<36,0,IF((Assumptions!H83*12)-(38-36)>0,MIN(AQ72+AQ73,(AQ72+AQ73)/MAX(1,(Assumptions!H83*12)-(38-36))),AQ72+AQ73)) -> 0.98191586 | AR74: =IF(39<36,0,IF((Assumptions!H83*12)-(39-36)>0,MIN(AR72+AR73,(AR72+AR73)/MAX(1,(Assumptions!H83*12)-(39-36))),AR72+AR73)) -> 0.98191586 | AS74: =IF(40<36,0,IF((Assumptions!H83*12)-(40-36)>0,MIN(AS72+AS73,(AS72+AS73)/MAX(1,(Assumptions!H83*12)-(40-36))),AS72+AS73)) -> 0.98191586 | AT74: =IF(41<36,0,IF((Assumptions!H83*12)-(41-36)>0,MIN(AT72+AT73,(AT72+AT73)/MAX(1,(Assumptions!H83*12)-(41-36))),AT72+AT73)) -> 0.98191586 | AU74: =IF(42<36,0,IF((Assumptions!H83*12)-(42-36)>0,MIN(AU72+AU73,(AU72+AU73)/MAX(1,(Assumptions!H83*12)-(42-36))),AU72+AU73)) -> 0.98191586 | AV74: =IF(43<36,0,IF((Assumptions!H83*12)-(43-36)>0,MIN(AV72+AV73,(AV72+AV73)/MAX(1,(Assumptions!H83*12)-(43-36))),AV72+AV73)) -> 0.98191586 | AW74: =IF(44<36,0,IF((Assumptions!H83*12)-(44-36)>0,MIN(AW72+AW73,(AW72+AW73)/MAX(1,(Assumptions!H83*12)-(44-36))),AW72+AW73)) -> 0.98191586 | AX74: =IF(45<36,0,IF((Assumptions!H83*12)-(45-36)>0,MIN(AX72+AX73,(AX72+AX73)/MAX(1,(Assumptions!H83*12)-(45-36))),AX72+AX73)) -> 0.98191586 | AY74: =IF(46<36,0,IF((Assumptions!H83*12)-(46-36)>0,MIN(AY72+AY73,(AY72+AY73)/MAX(1,(Assumptions!H83*12)-(46-36))),AY72+AY73)) -> 0.98191586 | AZ74: =IF(47<36,0,IF((Assumptions!H83*12)-(47-36)>0,MIN(AZ72+AZ73,(AZ72+AZ73)/MAX(1,(Assumptions!H83*12)-(47-36))),AZ72+AZ73)) -> 0.98191586 | BA74: =IF(48<36,0,IF((Assumptions!H83*12)-(48-36)>0,MIN(BA72+BA73,(BA72+BA73)/MAX(1,(Assumptions!H83*12)-(48-36))),BA72+BA73)) -> 0.98191586 | BB74: =IF(49<36,0,IF((Assumptions!H83*12)-(49-36)>0,MIN(BB72+BB73,(BB72+BB73)/MAX(1,(Assumptions!H83*12)-(49-36))),BB72+BB73)) -> 0.98191586 | BC74: =IF(50<36,0,IF((Assumptions!H83*12)-(50-36)>0,MIN(BC72+BC73,(BC72+BC73)/MAX(1,(Assumptions!H83*12)-(50-36))),BC72+BC73)) -> 0.91387761 | BD74: =IF(51<36,0,IF((Assumptions!H83*12)-(51-36)>0,MIN(BD72+BD73,(BD72+BD73)/MAX(1,(Assumptions!H83*12)-(51-36))),BD72+BD73)) -> 0.91387761 | BE74: =IF(52<36,0,IF((Assumptions!H83*12)-(52-36)>0,MIN(BE72+BE73,(BE72+BE73)/MAX(1,(Assumptions!H83*12)-(52-36))),BE72+BE73)) -> 0.91387761 | BF74: =IF(53<36,0,IF((Assumptions!H83*12)-(53-36)>0,MIN(BF72+BF73,(BF72+BF73)/MAX(1,(Assumptions!H83*12)-(53-36))),BF72+BF73)) -> 0.91387761 | BG74: =IF(54<36,0,IF((Assumptions!H83*12)-(54-36)>0,MIN(BG72+BG73,(BG72+BG73)/MAX(1,(Assumptions!H83*12)-(54-36))),BG72+BG73)) -> 0.91387761 | BH74: =IF(55<36,0,IF((Assumptions!H83*12)-(55-36)>0,MIN(BH72+BH73,(BH72+BH73)/MAX(1,(Assumptions!H83*12)-(55-36))),BH72+BH73)) -> 0.91387761 | BI74: =IF(56<36,0,IF((Assumptions!H83*12)-(56-36)>0,MIN(BI72+BI73,(BI72+BI73)/MAX(1,(Assumptions!H83*12)-(56-36))),BI72+BI73)) -> 0.91387761 | BJ74: =IF(57<36,0,IF((Assumptions!H83*12)-(57-36)>0,MIN(BJ72+BJ73,(BJ72+BJ73)/MAX(1,(Assumptions!H83*12)-(57-36))),BJ72+BJ73)) -> 0.91387761 | BK74: =IF(58<36,0,IF((Assumptions!H83*12)-(58-36)>0,MIN(BK72+BK73,(BK72+BK73)/MAX(1,(Assumptions!H83*12)-(58-36))),BK72+BK73)) -> 0.91387761 | BL74: =IF(59<36,0,IF((Assumptions!H83*12)-(59-36)>0,MIN(BL72+BL73,(BL72+BL73)/MAX(1,(Assumptions!H83*12)-(59-36))),BL72+BL73)) -> 0.91387761
C75: Pre-sale NBV | E75: =E72+E73-E74 -> 0 | F75: =F72+F73-F74 -> 0 | G75: =G72+G73-G74 -> 0 | H75: =H72+H73-H74 -> 0 | I75: =I72+I73-I74 -> 0 | J75: =J72+J73-J74 -> 0 | K75: =K72+K73-K74 -> 0 | L75: =L72+L73-L74 -> 0 | ... BL75: =BL72+BL73-BL74 -> 32.899594
C76: Allocated disposal NBV | E76: =IF(E91>0,E75/E91*Transfers!E24,0) -> 0 | F76: =IF(F91>0,F75/F91*Transfers!F24,0) -> 0 | G76: =IF(G91>0,G75/G91*Transfers!G24,0) -> 0 | H76: =IF(H91>0,H75/H91*Transfers!H24,0) -> 0 | I76: =IF(I91>0,I75/I91*Transfers!I24,0) -> 0 | J76: =IF(J91>0,J75/J91*Transfers!J24,0) -> 0 | K76: =IF(K91>0,K75/K91*Transfers!K24,0) -> 0 | L76: =IF(L91>0,L75/L91*Transfers!L24,0) -> 0 | ... BL76: =IF(BL91>0,BL75/BL91*Transfers!BL24,0) -> 0
C77: Closing NBV | E77: =E75-E76 -> 0 | F77: =F75-F76 -> 0 | G77: =G75-G76 -> 0 | H77: =H75-H76 -> 0 | I77: =I75-I76 -> 0 | J77: =J75-J76 -> 0 | K77: =K75-K76 -> 0 | L77: =L75-L76 -> 0 | ... BL77: =BL75-BL76 -> 32.899594
C78: FY2031 new investment
C79: Opening NBV | E79: =0 -> 0 | F79: =E84 -> 0 | G79: =F84 -> 0 | H79: =G84 -> 0 | I79: =H84 -> 0 | J79: =I84 -> 0 | K79: =J84 -> 0 | L79: =K84 -> 0 | M79: =L84 -> 0 | ... BL79: =BK84 -> 47.284679
C80: Additions | E80: =0 -> 0 | F80: =0 -> 0 | G80: =0 -> 0 | H80: =0 -> 0 | I80: =0 -> 0 | J80: =0 -> 0 | K80: =0 -> 0 | L80: =0 -> 0 | ... AZ80: =0 -> 0 | BA80: =Transfers!BA10+Transfers!BA12 -> 62.210236 | BB80: =Transfers!BB10+Transfers!BB12 -> 0 | BC80: =Transfers!BC10+Transfers!BC12 -> 0 | BD80: =Transfers!BD10+Transfers!BD12 -> 0 | BE80: =Transfers!BE10+Transfers!BE12 -> 0 | BF80: =Transfers!BF10+Transfers!BF12 -> 0 | BG80: =Transfers!BG10+Transfers!BG12 -> 0 | BH80: =Transfers!BH10+Transfers!BH12 -> 0 | ... BL80: =Transfers!BL10+Transfers!BL12 -> 0
C81: Amortisation | E81: =IF(0<48,0,IF((Assumptions!I83*12)-(0-48)>0,MIN(E79+E80,(E79+E80)/MAX(1,(Assumptions!I83*12)-(0-48))),E79+E80)) -> 0 | F81: =IF(1<48,0,IF((Assumptions!I83*12)-(1-48)>0,MIN(F79+F80,(F79+F80)/MAX(1,(Assumptions!I83*12)-(1-48))),F79+F80)) -> 0 | G81: =IF(2<48,0,IF((Assumptions!I83*12)-(2-48)>0,MIN(G79+G80,(G79+G80)/MAX(1,(Assumptions!I83*12)-(2-48))),G79+G80)) -> 0 | H81: =IF(3<48,0,IF((Assumptions!I83*12)-(3-48)>0,MIN(H79+H80,(H79+H80)/MAX(1,(Assumptions!I83*12)-(3-48))),H79+H80)) -> 0 | I81: =IF(4<48,0,IF((Assumptions!I83*12)-(4-48)>0,MIN(I79+I80,(I79+I80)/MAX(1,(Assumptions!I83*12)-(4-48))),I79+I80)) -> 0 | J81: =IF(5<48,0,IF((Assumptions!I83*12)-(5-48)>0,MIN(J79+J80,(J79+J80)/MAX(1,(Assumptions!I83*12)-(5-48))),J79+J80)) -> 0 | K81: =IF(6<48,0,IF((Assumptions!I83*12)-(6-48)>0,MIN(K79+K80,(K79+K80)/MAX(1,(Assumptions!I83*12)-(6-48))),K79+K80)) -> 0 | L81: =IF(7<48,0,IF((Assumptions!I83*12)-(7-48)>0,MIN(L79+L80,(L79+L80)/MAX(1,(Assumptions!I83*12)-(7-48))),L79+L80)) -> 0 | M81: =IF(8<48,0,IF((Assumptions!I83*12)-(8-48)>0,MIN(M79+M80,(M79+M80)/MAX(1,(Assumptions!I83*12)-(8-48))),M79+M80)) -> 0 | N81: =IF(9<48,0,IF((Assumptions!I83*12)-(9-48)>0,MIN(N79+N80,(N79+N80)/MAX(1,(Assumptions!I83*12)-(9-48))),N79+N80)) -> 0 | O81: =IF(10<48,0,IF((Assumptions!I83*12)-(10-48)>0,MIN(O79+O80,(O79+O80)/MAX(1,(Assumptions!I83*12)-(10-48))),O79+O80)) -> 0 | P81: =IF(11<48,0,IF((Assumptions!I83*12)-(11-48)>0,MIN(P79+P80,(P79+P80)/MAX(1,(Assumptions!I83*12)-(11-48))),P79+P80)) -> 0 | Q81: =IF(12<48,0,IF((Assumptions!I83*12)-(12-48)>0,MIN(Q79+Q80,(Q79+Q80)/MAX(1,(Assumptions!I83*12)-(12-48))),Q79+Q80)) -> 0 | R81: =IF(13<48,0,IF((Assumptions!I83*12)-(13-48)>0,MIN(R79+R80,(R79+R80)/MAX(1,(Assumptions!I83*12)-(13-48))),R79+R80)) -> 0 | S81: =IF(14<48,0,IF((Assumptions!I83*12)-(14-48)>0,MIN(S79+S80,(S79+S80)/MAX(1,(Assumptions!I83*12)-(14-48))),S79+S80)) -> 0 | T81: =IF(15<48,0,IF((Assumptions!I83*12)-(15-48)>0,MIN(T79+T80,(T79+T80)/MAX(1,(Assumptions!I83*12)-(15-48))),T79+T80)) -> 0 | U81: =IF(16<48,0,IF((Assumptions!I83*12)-(16-48)>0,MIN(U79+U80,(U79+U80)/MAX(1,(Assumptions!I83*12)-(16-48))),U79+U80)) -> 0 | V81: =IF(17<48,0,IF((Assumptions!I83*12)-(17-48)>0,MIN(V79+V80,(V79+V80)/MAX(1,(Assumptions!I83*12)-(17-48))),V79+V80)) -> 0 | W81: =IF(18<48,0,IF((Assumptions!I83*12)-(18-48)>0,MIN(W79+W80,(W79+W80)/MAX(1,(Assumptions!I83*12)-(18-48))),W79+W80)) -> 0 | X81: =IF(19<48,0,IF((Assumptions!I83*12)-(19-48)>0,MIN(X79+X80,(X79+X80)/MAX(1,(Assumptions!I83*12)-(19-48))),X79+X80)) -> 0 | Y81: =IF(20<48,0,IF((Assumptions!I83*12)-(20-48)>0,MIN(Y79+Y80,(Y79+Y80)/MAX(1,(Assumptions!I83*12)-(20-48))),Y79+Y80)) -> 0 | Z81: =IF(21<48,0,IF((Assumptions!I83*12)-(21-48)>0,MIN(Z79+Z80,(Z79+Z80)/MAX(1,(Assumptions!I83*12)-(21-48))),Z79+Z80)) -> 0 | AA81: =IF(22<48,0,IF((Assumptions!I83*12)-(22-48)>0,MIN(AA79+AA80,(AA79+AA80)/MAX(1,(Assumptions!I83*12)-(22-48))),AA79+AA80)) -> 0 | AB81: =IF(23<48,0,IF((Assumptions!I83*12)-(23-48)>0,MIN(AB79+AB80,(AB79+AB80)/MAX(1,(Assumptions!I83*12)-(23-48))),AB79+AB80)) -> 0 | AC81: =IF(24<48,0,IF((Assumptions!I83*12)-(24-48)>0,MIN(AC79+AC80,(AC79+AC80)/MAX(1,(Assumptions!I83*12)-(24-48))),AC79+AC80)) -> 0 | AD81: =IF(25<48,0,IF((Assumptions!I83*12)-(25-48)>0,MIN(AD79+AD80,(AD79+AD80)/MAX(1,(Assumptions!I83*12)-(25-48))),AD79+AD80)) -> 0 | AE81: =IF(26<48,0,IF((Assumptions!I83*12)-(26-48)>0,MIN(AE79+AE80,(AE79+AE80)/MAX(1,(Assumptions!I83*12)-(26-48))),AE79+AE80)) -> 0 | AF81: =IF(27<48,0,IF((Assumptions!I83*12)-(27-48)>0,MIN(AF79+AF80,(AF79+AF80)/MAX(1,(Assumptions!I83*12)-(27-48))),AF79+AF80)) -> 0 | AG81: =IF(28<48,0,IF((Assumptions!I83*12)-(28-48)>0,MIN(AG79+AG80,(AG79+AG80)/MAX(1,(Assumptions!I83*12)-(28-48))),AG79+AG80)) -> 0 | AH81: =IF(29<48,0,IF((Assumptions!I83*12)-(29-48)>0,MIN(AH79+AH80,(AH79+AH80)/MAX(1,(Assumptions!I83*12)-(29-48))),AH79+AH80)) -> 0 | AI81: =IF(30<48,0,IF((Assumptions!I83*12)-(30-48)>0,MIN(AI79+AI80,(AI79+AI80)/MAX(1,(Assumptions!I83*12)-(30-48))),AI79+AI80)) -> 0 | AJ81: =IF(31<48,0,IF((Assumptions!I83*12)-(31-48)>0,MIN(AJ79+AJ80,(AJ79+AJ80)/MAX(1,(Assumptions!I83*12)-(31-48))),AJ79+AJ80)) -> 0 | AK81: =IF(32<48,0,IF((Assumptions!I83*12)-(32-48)>0,MIN(AK79+AK80,(AK79+AK80)/MAX(1,(Assumptions!I83*12)-(32-48))),AK79+AK80)) -> 0 | AL81: =IF(33<48,0,IF((Assumptions!I83*12)-(33-48)>0,MIN(AL79+AL80,(AL79+AL80)/MAX(1,(Assumptions!I83*12)-(33-48))),AL79+AL80)) -> 0 | AM81: =IF(34<48,0,IF((Assumptions!I83*12)-(34-48)>0,MIN(AM79+AM80,(AM79+AM80)/MAX(1,(Assumptions!I83*12)-(34-48))),AM79+AM80)) -> 0 | AN81: =IF(35<48,0,IF((Assumptions!I83*12)-(35-48)>0,MIN(AN79+AN80,(AN79+AN80)/MAX(1,(Assumptions!I83*12)-(35-48))),AN79+AN80)) -> 0 | AO81: =IF(36<48,0,IF((Assumptions!I83*12)-(36-48)>0,MIN(AO79+AO80,(AO79+AO80)/MAX(1,(Assumptions!I83*12)-(36-48))),AO79+AO80)) -> 0 | AP81: =IF(37<48,0,IF((Assumptions!I83*12)-(37-48)>0,MIN(AP79+AP80,(AP79+AP80)/MAX(1,(Assumptions!I83*12)-(37-48))),AP79+AP80)) -> 0 | AQ81: =IF(38<48,0,IF((Assumptions!I83*12)-(38-48)>0,MIN(AQ79+AQ80,(AQ79+AQ80)/MAX(1,(Assumptions!I83*12)-(38-48))),AQ79+AQ80)) -> 0 | AR81: =IF(39<48,0,IF((Assumptions!I83*12)-(39-48)>0,MIN(AR79+AR80,(AR79+AR80)/MAX(1,(Assumptions!I83*12)-(39-48))),AR79+AR80)) -> 0 | AS81: =IF(40<48,0,IF((Assumptions!I83*12)-(40-48)>0,MIN(AS79+AS80,(AS79+AS80)/MAX(1,(Assumptions!I83*12)-(40-48))),AS79+AS80)) -> 0 | AT81: =IF(41<48,0,IF((Assumptions!I83*12)-(41-48)>0,MIN(AT79+AT80,(AT79+AT80)/MAX(1,(Assumptions!I83*12)-(41-48))),AT79+AT80)) -> 0 | AU81: =IF(42<48,0,IF((Assumptions!I83*12)-(42-48)>0,MIN(AU79+AU80,(AU79+AU80)/MAX(1,(Assumptions!I83*12)-(42-48))),AU79+AU80)) -> 0 | AV81: =IF(43<48,0,IF((Assumptions!I83*12)-(43-48)>0,MIN(AV79+AV80,(AV79+AV80)/MAX(1,(Assumptions!I83*12)-(43-48))),AV79+AV80)) -> 0 | AW81: =IF(44<48,0,IF((Assumptions!I83*12)-(44-48)>0,MIN(AW79+AW80,(AW79+AW80)/MAX(1,(Assumptions!I83*12)-(44-48))),AW79+AW80)) -> 0 | AX81: =IF(45<48,0,IF((Assumptions!I83*12)-(45-48)>0,MIN(AX79+AX80,(AX79+AX80)/MAX(1,(Assumptions!I83*12)-(45-48))),AX79+AX80)) -> 0 | AY81: =IF(46<48,0,IF((Assumptions!I83*12)-(46-48)>0,MIN(AY79+AY80,(AY79+AY80)/MAX(1,(Assumptions!I83*12)-(46-48))),AY79+AY80)) -> 0 | AZ81: =IF(47<48,0,IF((Assumptions!I83*12)-(47-48)>0,MIN(AZ79+AZ80,(AZ79+AZ80)/MAX(1,(Assumptions!I83*12)-(47-48))),AZ79+AZ80)) -> 0 | BA81: =IF(48<48,0,IF((Assumptions!I83*12)-(48-48)>0,MIN(BA79+BA80,(BA79+BA80)/MAX(1,(Assumptions!I83*12)-(48-48))),BA79+BA80)) -> 1.0368373 | BB81: =IF(49<48,0,IF((Assumptions!I83*12)-(49-48)>0,MIN(BB79+BB80,(BB79+BB80)/MAX(1,(Assumptions!I83*12)-(49-48))),BB79+BB80)) -> 1.0368373 | BC81: =IF(50<48,0,IF((Assumptions!I83*12)-(50-48)>0,MIN(BC79+BC80,(BC79+BC80)/MAX(1,(Assumptions!I83*12)-(50-48))),BC79+BC80)) -> 0.96499345 | BD81: =IF(51<48,0,IF((Assumptions!I83*12)-(51-48)>0,MIN(BD79+BD80,(BD79+BD80)/MAX(1,(Assumptions!I83*12)-(51-48))),BD79+BD80)) -> 0.96499345 | BE81: =IF(52<48,0,IF((Assumptions!I83*12)-(52-48)>0,MIN(BE79+BE80,(BE79+BE80)/MAX(1,(Assumptions!I83*12)-(52-48))),BE79+BE80)) -> 0.96499345 | BF81: =IF(53<48,0,IF((Assumptions!I83*12)-(53-48)>0,MIN(BF79+BF80,(BF79+BF80)/MAX(1,(Assumptions!I83*12)-(53-48))),BF79+BF80)) -> 0.96499345 | BG81: =IF(54<48,0,IF((Assumptions!I83*12)-(54-48)>0,MIN(BG79+BG80,(BG79+BG80)/MAX(1,(Assumptions!I83*12)-(54-48))),BG79+BG80)) -> 0.96499345 | BH81: =IF(55<48,0,IF((Assumptions!I83*12)-(55-48)>0,MIN(BH79+BH80,(BH79+BH80)/MAX(1,(Assumptions!I83*12)-(55-48))),BH79+BH80)) -> 0.96499345 | BI81: =IF(56<48,0,IF((Assumptions!I83*12)-(56-48)>0,MIN(BI79+BI80,(BI79+BI80)/MAX(1,(Assumptions!I83*12)-(56-48))),BI79+BI80)) -> 0.96499345 | BJ81: =IF(57<48,0,IF((Assumptions!I83*12)-(57-48)>0,MIN(BJ79+BJ80,(BJ79+BJ80)/MAX(1,(Assumptions!I83*12)-(57-48))),BJ79+BJ80)) -> 0.96499345 | BK81: =IF(58<48,0,IF((Assumptions!I83*12)-(58-48)>0,MIN(BK79+BK80,(BK79+BK80)/MAX(1,(Assumptions!I83*12)-(58-48))),BK79+BK80)) -> 0.96499345 | BL81: =IF(59<48,0,IF((Assumptions!I83*12)-(59-48)>0,MIN(BL79+BL80,(BL79+BL80)/MAX(1,(Assumptions!I83*12)-(59-48))),BL79+BL80)) -> 0.96499345
C82: Pre-sale NBV | E82: =E79+E80-E81 -> 0 | F82: =F79+F80-F81 -> 0 | G82: =G79+G80-G81 -> 0 | H82: =H79+H80-H81 -> 0 | I82: =I79+I80-I81 -> 0 | J82: =J79+J80-J81 -> 0 | K82: =K79+K80-K81 -> 0 | L82: =L79+L80-L81 -> 0 | ... BL82: =BL79+BL80-BL81 -> 46.319685
C83: Allocated disposal NBV | E83: =IF(E91>0,E82/E91*Transfers!E24,0) -> 0 | F83: =IF(F91>0,F82/F91*Transfers!F24,0) -> 0 | G83: =IF(G91>0,G82/G91*Transfers!G24,0) -> 0 | H83: =IF(H91>0,H82/H91*Transfers!H24,0) -> 0 | I83: =IF(I91>0,I82/I91*Transfers!I24,0) -> 0 | J83: =IF(J91>0,J82/J91*Transfers!J24,0) -> 0 | K83: =IF(K91>0,K82/K91*Transfers!K24,0) -> 0 | L83: =IF(L91>0,L82/L91*Transfers!L24,0) -> 0 | ... BL83: =IF(BL91>0,BL82/BL91*Transfers!BL24,0) -> 0
C84: Closing NBV | E84: =E82-E83 -> 0 | F84: =F82-F83 -> 0 | G84: =G82-G83 -> 0 | H84: =H82-H83 -> 0 | I84: =I82-I83 -> 0 | J84: =J82-J83 -> 0 | K84: =K82-K83 -> 0 | L84: =L82-L83 -> 0 | ... BL84: =BL82-BL83 -> 46.319685
C89: Total registration amortisation | E89: =E11+E18+E25+E32+E39+E46+E53+E60+E67+E74+E81 -> 13.008333 | F89: =F11+F18+F25+F32+F39+F46+F53+F60+F67+F74+F81 -> 13.008333 | G89: =G11+G18+G25+G32+G39+G46+G53+G60+G67+G74+G81 -> 15.760648 | H89: =H11+H18+H25+H32+H39+H46+H53+H60+H67+H74+H81 -> 15.741937 | I89: =I11+I18+I25+I32+I39+I46+I53+I60+I67+I74+I81 -> 15.741937 | J89: =J11+J18+J25+J32+J39+J46+J53+J60+J67+J74+J81 -> 15.741937 | K89: =K11+K18+K25+K32+K39+K46+K53+K60+K67+K74+K81 -> 15.825271 | L89: =L11+L18+L25+L32+L39+L46+L53+L60+L67+L74+L81 -> 15.825271 | ... BL89: =BL11+BL18+BL25+BL32+BL39+BL46+BL53+BL60+BL67+BL74+BL81 -> 7.901067
C90: Total registration additions | E90: =E10+E17+E24+E31+E38+E45+E52+E59+E66+E73+E80 -> 0 | F90: =F10+F17+F24+F31+F38+F45+F52+F59+F66+F73+F80 -> 0 | G90: =G10+G17+G24+G31+G38+G45+G52+G59+G66+G73+G80 -> 181.07586 | H90: =H10+H17+H24+H31+H38+H45+H52+H59+H66+H73+H80 -> 0 | I90: =I10+I17+I24+I31+I38+I45+I52+I59+I66+I73+I80 -> 0 | J90: =J10+J17+J24+J31+J38+J45+J52+J59+J66+J73+J80 -> 0 | K90: =K10+K17+K24+K31+K38+K45+K52+K59+K66+K73+K80 -> 5 | L90: =L10+L17+L24+L31+L38+L45+L52+L59+L66+L73+L80 -> 0 | ... BL90: =BL10+BL17+BL24+BL31+BL38+BL45+BL52+BL59+BL66+BL73+BL80 -> 0
C91: Total pre-sale NBV | E91: =E12+E19+E26+E33+E40+E47+E54+E61+E68+E75+E82 -> 439.28367 | F91: =F12+F19+F26+F33+F40+F47+F54+F61+F68+F75+F82 -> 426.27533 | G91: =G12+G19+G26+G33+G40+G47+G54+G61+G68+G75+G82 -> 582.88647 | H91: =H12+H19+H26+H33+H40+H47+H54+H61+H68+H75+H82 -> 566.45253 | I91: =I12+I19+I26+I33+I40+I47+I54+I61+I68+I75+I82 -> 550.71059 | J91: =J12+J19+J26+J33+J40+J47+J54+J61+J68+J75+J82 -> 534.96866 | K91: =K12+K19+K26+K33+K40+K47+K54+K61+K68+K75+K82 -> 524.14339 | L91: =L12+L19+L26+L33+L40+L47+L54+L61+L68+L75+L82 -> 508.31811 | ... BL91: =BL12+BL19+BL26+BL33+BL40+BL47+BL54+BL61+BL68+BL75+BL82 -> 115.84211
C92: Total closing registration NBV | E92: =E14+E21+E28+E35+E42+E49+E56+E63+E70+E77+E84 -> 439.28367 | F92: =F14+F21+F28+F35+F42+F49+F56+F63+F70+F77+F84 -> 417.57125 | G92: =G14+G21+G28+G35+G42+G49+G56+G63+G70+G77+G84 -> 582.19447 | H92: =H14+H21+H28+H35+H42+H49+H56+H63+H70+H77+H84 -> 566.45253 | I92: =I14+I21+I28+I35+I42+I49+I56+I63+I70+I77+I84 -> 550.71059 | J92: =J14+J21+J28+J35+J42+J49+J56+J63+J70+J77+J84 -> 534.96866 | K92: =K14+K21+K28+K35+K42+K49+K56+K63+K70+K77+K84 -> 524.14339 | L92: =L14+L21+L28+L35+L42+L49+L56+L63+L70+L77+L84 -> 508.31811 | ... BL92: =BL14+BL21+BL28+BL35+BL42+BL49+BL56+BL63+BL70+BL77+BL84 -> 115.84211

Sheet Transfers
C2: Transfers
C3: £m unless stated. Evidence cut-off: 8 October 2026.
C4: Case selected | E4: =CHOOSE(Assumptions!$E$5,"Base","Downside","Upside") -> Base
C7: Month | E7: 46204 | F7: 46235 | G7: 46266 | H7: 46296 | I7: 46327 | J7: 46357 | K7: 46388 | L7: 46419 | M7: 46447 | N7: 46478 | O7: 46508 | P7: 46539 | Q7: 46569 | R7: 46600 | S7: 46631 | T7: 46661 | U7: 46692 | V7: 46722 | W7: 46753 | X7: 46784 | Y7: 46813 | Z7: 46844 | AA7: 46874 | AB7: 46905 | AC7: 46935 | AD7: 46966 | AE7: 46997 | AF7: 47027 | AG7: 47058 | AH7: 47088 | AI7: 47119 | AJ7: 47150 | AK7: 47178 | AL7: 47209 | AM7: 47239 | AN7: 47270 | AO7: 47300 | AP7: 47331 | AQ7: 47362 | AR7: 47392 | AS7: 47423 | AT7: 47453 | AU7: 47484 | AV7: 47515 | AW7: 47543 | AX7: 47574 | AY7: 47604 | AZ7: 47635 | BA7: 47665 | BB7: 47696 | BC7: 47727 | BD7: 47757 | BE7: 47788 | BF7: 47818 | BG7: 47849 | BH7: 47880 | BI7: 47908 | BJ7: 47939 | BK7: 47969 | BL7: 48000
C8: Discretionary acquisition face consideration | E8: =0 -> 0 | F8: =0 -> 0 | G8: =0 -> 0 | H8: =0 -> 0 | I8: =0 -> 0 | J8: =0 -> 0 | K8: =Capacity!$E$6 -> 0 | L8: =0 -> 0 | M8: =0 -> 0 | N8: =0 -> 0 | O8: =0 -> 0 | P8: =0 -> 0 | Q8: =Assumptions!F63 -> 60 | R8: =0 -> 0 | S8: =0 -> 0 | T8: =0 -> 0 | U8: =0 -> 0 | V8: =0 -> 0 | W8: =0 -> 0 | X8: =0 -> 0 | Y8: =0 -> 0 | ... AB8: =0 -> 0 | AC8: =Assumptions!G63 -> 60 | AD8: =0 -> 0 | AE8: =0 -> 0 | AF8: =0 -> 0 | AG8: =0 -> 0 | AH8: =0 -> 0 | AI8: =0 -> 0 | AJ8: =0 -> 0 | AK8: =0 -> 0 | ... AN8: =0 -> 0 | AO8: =Assumptions!H63 -> 60 | AP8: =0 -> 0 | AQ8: =0 -> 0 | AR8: =0 -> 0 | AS8: =0 -> 0 | AT8: =0 -> 0 | AU8: =0 -> 0 | AV8: =0 -> 0 | AW8: =0 -> 0 | ... AZ8: =0 -> 0 | BA8: =Assumptions!I63 -> 60 | BB8: =0 -> 0 | BC8: =0 -> 0 | BD8: =0 -> 0 | BE8: =0 -> 0 | BF8: =0 -> 0 | BG8: =0 -> 0 | BH8: =0 -> 0 | BI8: =0 -> 0 | ... BL8: =0 -> 0
C9: Acquisition PV factor | E9: =Assumptions!E98+Assumptions!E103/(1+Assumptions!E93)+Assumptions!E108/(1+Assumptions!E93)^2+Assumptions!E113/(1+Assumptions!E93)^3 -> 0.95350394 | F9: =Assumptions!E98+Assumptions!E103/(1+Assumptions!E93)+Assumptions!E108/(1+Assumptions!E93)^2+Assumptions!E113/(1+Assumptions!E93)^3 -> 0.95350394 | G9: =Assumptions!E98+Assumptions!E103/(1+Assumptions!E93)+Assumptions!E108/(1+Assumptions!E93)^2+Assumptions!E113/(1+Assumptions!E93)^3 -> 0.95350394 | H9: =Assumptions!E98+Assumptions!E103/(1+Assumptions!E93)+Assumptions!E108/(1+Assumptions!E93)^2+Assumptions!E113/(1+Assumptions!E93)^3 -> 0.95350394 | I9: =Assumptions!E98+Assumptions!E103/(1+Assumptions!E93)+Assumptions!E108/(1+Assumptions!E93)^2+Assumptions!E113/(1+Assumptions!E93)^3 -> 0.95350394 | J9: =Assumptions!E98+Assumptions!E103/(1+Assumptions!E93)+Assumptions!E108/(1+Assumptions!E93)^2+Assumptions!E113/(1+Assumptions!E93)^3 -> 0.95350394 | K9: =Assumptions!E98+Assumptions!E103/(1+Assumptions!E93)+Assumptions!E108/(1+Assumptions!E93)^2+Assumptions!E113/(1+Assumptions!E93)^3 -> 0.95350394 | L9: =Assumptions!E98+Assumptions!E103/(1+Assumptions!E93)+Assumptions!E108/(1+Assumptions!E93)^2+Assumptions!E113/(1+Assumptions!E93)^3 -> 0.95350394 | M9: =Assumptions!E98+Assumptions!E103/(1+Assumptions!E93)+Assumptions!E108/(1+Assumptions!E93)^2+Assumptions!E113/(1+Assumptions!E93)^3 -> 0.95350394 | N9: =Assumptions!E98+Assumptions!E103/(1+Assumptions!E93)+Assumptions!E108/(1+Assumptions!E93)^2+Assumptions!E113/(1+Assumptions!E93)^3 -> 0.95350394 | O9: =Assumptions!E98+Assumptions!E103/(1+Assumptions!E93)+Assumptions!E108/(1+Assumptions!E93)^2+Assumptions!E113/(1+Assumptions!E93)^3 -> 0.95350394 | P9: =Assumptions!E98+Assumptions!E103/(1+Assumptions!E93)+Assumptions!E108/(1+Assumptions!E93)^2+Assumptions!E113/(1+Assumptions!E93)^3 -> 0.95350394 | Q9: =Assumptions!F98+Assumptions!F103/(1+Assumptions!F93)+Assumptions!F108/(1+Assumptions!F93)^2+Assumptions!F113/(1+Assumptions!F93)^3 -> 0.95350394 | R9: =Assumptions!F98+Assumptions!F103/(1+Assumptions!F93)+Assumptions!F108/(1+Assumptions!F93)^2+Assumptions!F113/(1+Assumptions!F93)^3 -> 0.95350394 | S9: =Assumptions!F98+Assumptions!F103/(1+Assumptions!F93)+Assumptions!F108/(1+Assumptions!F93)^2+Assumptions!F113/(1+Assumptions!F93)^3 -> 0.95350394 | T9: =Assumptions!F98+Assumptions!F103/(1+Assumptions!F93)+Assumptions!F108/(1+Assumptions!F93)^2+Assumptions!F113/(1+Assumptions!F93)^3 -> 0.95350394 | U9: =Assumptions!F98+Assumptions!F103/(1+Assumptions!F93)+Assumptions!F108/(1+Assumptions!F93)^2+Assumptions!F113/(1+Assumptions!F93)^3 -> 0.95350394 | V9: =Assumptions!F98+Assumptions!F103/(1+Assumptions!F93)+Assumptions!F108/(1+Assumptions!F93)^2+Assumptions!F113/(1+Assumptions!F93)^3 -> 0.95350394 | W9: =Assumptions!F98+Assumptions!F103/(1+Assumptions!F93)+Assumptions!F108/(1+Assumptions!F93)^2+Assumptions!F113/(1+Assumptions!F93)^3 -> 0.95350394 | X9: =Assumptions!F98+Assumptions!F103/(1+Assumptions!F93)+Assumptions!F108/(1+Assumptions!F93)^2+Assumptions!F113/(1+Assumptions!F93)^3 -> 0.95350394 | Y9: =Assumptions!F98+Assumptions!F103/(1+Assumptions!F93)+Assumptions!F108/(1+Assumptions!F93)^2+Assumptions!F113/(1+Assumptions!F93)^3 -> 0.95350394 | Z9: =Assumptions!F98+Assumptions!F103/(1+Assumptions!F93)+Assumptions!F108/(1+Assumptions!F93)^2+Assumptions!F113/(1+Assumptions!F93)^3 -> 0.95350394 | AA9: =Assumptions!F98+Assumptions!F103/(1+Assumptions!F93)+Assumptions!F108/(1+Assumptions!F93)^2+Assumptions!F113/(1+Assumptions!F93)^3 -> 0.95350394 | AB9: =Assumptions!F98+Assumptions!F103/(1+Assumptions!F93)+Assumptions!F108/(1+Assumptions!F93)^2+Assumptions!F113/(1+Assumptions!F93)^3 -> 0.95350394 | AC9: =Assumptions!G98+Assumptions!G103/(1+Assumptions!G93)+Assumptions!G108/(1+Assumptions!G93)^2+Assumptions!G113/(1+Assumptions!G93)^3 -> 0.95350394 | AD9: =Assumptions!G98+Assumptions!G103/(1+Assumptions!G93)+Assumptions!G108/(1+Assumptions!G93)^2+Assumptions!G113/(1+Assumptions!G93)^3 -> 0.95350394 | AE9: =Assumptions!G98+Assumptions!G103/(1+Assumptions!G93)+Assumptions!G108/(1+Assumptions!G93)^2+Assumptions!G113/(1+Assumptions!G93)^3 -> 0.95350394 | AF9: =Assumptions!G98+Assumptions!G103/(1+Assumptions!G93)+Assumptions!G108/(1+Assumptions!G93)^2+Assumptions!G113/(1+Assumptions!G93)^3 -> 0.95350394 | AG9: =Assumptions!G98+Assumptions!G103/(1+Assumptions!G93)+Assumptions!G108/(1+Assumptions!G93)^2+Assumptions!G113/(1+Assumptions!G93)^3 -> 0.95350394 | AH9: =Assumptions!G98+Assumptions!G103/(1+Assumptions!G93)+Assumptions!G108/(1+Assumptions!G93)^2+Assumptions!G113/(1+Assumptions!G93)^3 -> 0.95350394 | AI9: =Assumptions!G98+Assumptions!G103/(1+Assumptions!G93)+Assumptions!G108/(1+Assumptions!G93)^2+Assumptions!G113/(1+Assumptions!G93)^3 -> 0.95350394 | AJ9: =Assumptions!G98+Assumptions!G103/(1+Assumptions!G93)+Assumptions!G108/(1+Assumptions!G93)^2+Assumptions!G113/(1+Assumptions!G93)^3 -> 0.95350394 | AK9: =Assumptions!G98+Assumptions!G103/(1+Assumptions!G93)+Assumptions!G108/(1+Assumptions!G93)^2+Assumptions!G113/(1+Assumptions!G93)^3 -> 0.95350394 | AL9: =Assumptions!G98+Assumptions!G103/(1+Assumptions!G93)+Assumptions!G108/(1+Assumptions!G93)^2+Assumptions!G113/(1+Assumptions!G93)^3 -> 0.95350394 | AM9: =Assumptions!G98+Assumptions!G103/(1+Assumptions!G93)+Assumptions!G108/(1+Assumptions!G93)^2+Assumptions!G113/(1+Assumptions!G93)^3 -> 0.95350394 | AN9: =Assumptions!G98+Assumptions!G103/(1+Assumptions!G93)+Assumptions!G108/(1+Assumptions!G93)^2+Assumptions!G113/(1+Assumptions!G93)^3 -> 0.95350394 | AO9: =Assumptions!H98+Assumptions!H103/(1+Assumptions!H93)+Assumptions!H108/(1+Assumptions!H93)^2+Assumptions!H113/(1+Assumptions!H93)^3 -> 0.95350394 | AP9: =Assumptions!H98+Assumptions!H103/(1+Assumptions!H93)+Assumptions!H108/(1+Assumptions!H93)^2+Assumptions!H113/(1+Assumptions!H93)^3 -> 0.95350394 | AQ9: =Assumptions!H98+Assumptions!H103/(1+Assumptions!H93)+Assumptions!H108/(1+Assumptions!H93)^2+Assumptions!H113/(1+Assumptions!H93)^3 -> 0.95350394 | AR9: =Assumptions!H98+Assumptions!H103/(1+Assumptions!H93)+Assumptions!H108/(1+Assumptions!H93)^2+Assumptions!H113/(1+Assumptions!H93)^3 -> 0.95350394 | AS9: =Assumptions!H98+Assumptions!H103/(1+Assumptions!H93)+Assumptions!H108/(1+Assumptions!H93)^2+Assumptions!H113/(1+Assumptions!H93)^3 -> 0.95350394 | AT9: =Assumptions!H98+Assumptions!H103/(1+Assumptions!H93)+Assumptions!H108/(1+Assumptions!H93)^2+Assumptions!H113/(1+Assumptions!H93)^3 -> 0.95350394 | AU9: =Assumptions!H98+Assumptions!H103/(1+Assumptions!H93)+Assumptions!H108/(1+Assumptions!H93)^2+Assumptions!H113/(1+Assumptions!H93)^3 -> 0.95350394 | AV9: =Assumptions!H98+Assumptions!H103/(1+Assumptions!H93)+Assumptions!H108/(1+Assumptions!H93)^2+Assumptions!H113/(1+Assumptions!H93)^3 -> 0.95350394 | AW9: =Assumptions!H98+Assumptions!H103/(1+Assumptions!H93)+Assumptions!H108/(1+Assumptions!H93)^2+Assumptions!H113/(1+Assumptions!H93)^3 -> 0.95350394 | AX9: =Assumptions!H98+Assumptions!H103/(1+Assumptions!H93)+Assumptions!H108/(1+Assumptions!H93)^2+Assumptions!H113/(1+Assumptions!H93)^3 -> 0.95350394 | AY9: =Assumptions!H98+Assumptions!H103/(1+Assumptions!H93)+Assumptions!H108/(1+Assumptions!H93)^2+Assumptions!H113/(1+Assumptions!H93)^3 -> 0.95350394 | AZ9: =Assumptions!H98+Assumptions!H103/(1+Assumptions!H93)+Assumptions!H108/(1+Assumptions!H93)^2+Assumptions!H113/(1+Assumptions!H93)^3 -> 0.95350394 | BA9: =Assumptions!I98+Assumptions!I103/(1+Assumptions!I93)+Assumptions!I108/(1+Assumptions!I93)^2+Assumptions!I113/(1+Assumptions!I93)^3 -> 0.95350394 | BB9: =Assumptions!I98+Assumptions!I103/(1+Assumptions!I93)+Assumptions!I108/(1+Assumptions!I93)^2+Assumptions!I113/(1+Assumptions!I93)^3 -> 0.95350394 | BC9: =Assumptions!I98+Assumptions!I103/(1+Assumptions!I93)+Assumptions!I108/(1+Assumptions!I93)^2+Assumptions!I113/(1+Assumptions!I93)^3 -> 0.95350394 | BD9: =Assumptions!I98+Assumptions!I103/(1+Assumptions!I93)+Assumptions!I108/(1+Assumptions!I93)^2+Assumptions!I113/(1+Assumptions!I93)^3 -> 0.95350394 | BE9: =Assumptions!I98+Assumptions!I103/(1+Assumptions!I93)+Assumptions!I108/(1+Assumptions!I93)^2+Assumptions!I113/(1+Assumptions!I93)^3 -> 0.95350394 | BF9: =Assumptions!I98+Assumptions!I103/(1+Assumptions!I93)+Assumptions!I108/(1+Assumptions!I93)^2+Assumptions!I113/(1+Assumptions!I93)^3 -> 0.95350394 | BG9: =Assumptions!I98+Assumptions!I103/(1+Assumptions!I93)+Assumptions!I108/(1+Assumptions!I93)^2+Assumptions!I113/(1+Assumptions!I93)^3 -> 0.95350394 | BH9: =Assumptions!I98+Assumptions!I103/(1+Assumptions!I93)+Assumptions!I108/(1+Assumptions!I93)^2+Assumptions!I113/(1+Assumptions!I93)^3 -> 0.95350394 | BI9: =Assumptions!I98+Assumptions!I103/(1+Assumptions!I93)+Assumptions!I108/(1+Assumptions!I93)^2+Assumptions!I113/(1+Assumptions!I93)^3 -> 0.95350394 | BJ9: =Assumptions!I98+Assumptions!I103/(1+Assumptions!I93)+Assumptions!I108/(1+Assumptions!I93)^2+Assumptions!I113/(1+Assumptions!I93)^3 -> 0.95350394 | BK9: =Assumptions!I98+Assumptions!I103/(1+Assumptions!I93)+Assumptions!I108/(1+Assumptions!I93)^2+Assumptions!I113/(1+Assumptions!I93)^3 -> 0.95350394 | BL9: =Assumptions!I98+Assumptions!I103/(1+Assumptions!I93)+Assumptions!I108/(1+Assumptions!I93)^2+Assumptions!I113/(1+Assumptions!I93)^3 -> 0.95350394
C10: Discretionary capitalised cost | E10: =E8*E9 -> 0 | F10: =F8*F9 -> 0 | G10: =G8*G9 -> 0 | H10: =H8*H9 -> 0 | I10: =I8*I9 -> 0 | J10: =J8*J9 -> 0 | K10: =K8*K9 -> 0 | L10: =L8*L9 -> 0 | ... BL10: =BL8*BL9 -> 0
C11: Known subsequent event capitalised cost | E11: =0 -> 0 | F11: =0 -> 0 | G11: =191.731*(Assumptions!E118/(1+Assumptions!E93)^0+Assumptions!E123/(1+Assumptions!E93)^1+Assumptions!E128/(1+Assumptions!E93)^2+Assumptions!E133/(1+Assumptions!E93)^3+Assumptions!E138/(1+Assumptions!E93)^4)+1.16 -> 181.07586 | H11: =0 -> 0 | I11: =0 -> 0 | J11: =0 -> 0 | K11: =0 -> 0 | L11: =0 -> 0 | M11: =0 -> 0 | N11: =0 -> 0 | O11: =0 -> 0 | ... BL11: =0 -> 0
C12: Contingent triggered additions | E12: =0 -> 0 | F12: =0 -> 0 | G12: =0 -> 0 | H12: =0 -> 0 | I12: =0 -> 0 | J12: =0 -> 0 | K12: =Assumptions!E198 -> 5 | L12: =0 -> 0 | M12: =0 -> 0 | N12: =0 -> 0 | O12: =0 -> 0 | P12: =0 -> 0 | Q12: =Assumptions!F198 -> 5 | R12: =0 -> 0 | S12: =0 -> 0 | T12: =0 -> 0 | U12: =0 -> 0 | V12: =0 -> 0 | W12: =0 -> 0 | X12: =0 -> 0 | Y12: =0 -> 0 | ... AB12: =0 -> 0 | AC12: =Assumptions!G198 -> 5 | AD12: =0 -> 0 | AE12: =0 -> 0 | AF12: =0 -> 0 | AG12: =0 -> 0 | AH12: =0 -> 0 | AI12: =0 -> 0 | AJ12: =0 -> 0 | AK12: =0 -> 0 | ... AN12: =0 -> 0 | AO12: =Assumptions!H198 -> 5 | AP12: =0 -> 0 | AQ12: =0 -> 0 | AR12: =0 -> 0 | AS12: =0 -> 0 | AT12: =0 -> 0 | AU12: =0 -> 0 | AV12: =0 -> 0 | AW12: =0 -> 0 | ... AZ12: =0 -> 0 | BA12: =Assumptions!I198 -> 5 | BB12: =0 -> 0 | BC12: =0 -> 0 | BD12: =0 -> 0 | BE12: =0 -> 0 | BF12: =0 -> 0 | BG12: =0 -> 0 | BH12: =0 -> 0 | BI12: =0 -> 0 | ... BL12: =0 -> 0
C13: Total registration additions | E13: =SUM(E10:E12) -> 0 | F13: =SUM(F10:F12) -> 0 | G13: =SUM(G10:G12) -> 181.07586 | H13: =SUM(H10:H12) -> 0 | I13: =SUM(I10:I12) -> 0 | J13: =SUM(J10:J12) -> 0 | K13: =SUM(K10:K12) -> 5 | L13: =SUM(L10:L12) -> 0 | ... BL13: =SUM(BL10:BL12) -> 0
